Workbook
Name _Hlk178865892: Instructions!$E$57
Name AprPie: 'PIE Tracker'!$V$3:$Z$34
Name FEBpie: 'PIE Tracker'!$H$3:$M$34
Name JANPIE: 'PIE Tracker'!$A$3:$F$34
Name MARPIE: 'PIE Tracker'!$O$3:$T$34

Sheet Goals & Fees
A1: This sheet is protected, input details in the blue outlined cells.
A2: Yearly Goals and Fees
C3: 1. Enter Your Gross Commissions Income Goal | J3: Annual Gross Commission GOAL
D4: Do not leave blank. Calculations depend on this number. | L4: 200000
C8: 2. Do you pay a franchise fee on each transaction? | J8: Franchise Fee
C9: If yes, fill in the flat fee to be deducted from each transaction or % deducted from each transaction.
D10: Leave blank if no franchise fee. | L10: Flat Fee | N10: Franchise Fee as a %.
C12: Is there a franchise fees cap? | J12: Franchise Fee Cap
C13: If you contribute franchise fees from each transaction until you have reached a specific threshold, the answer is yes. Enter your "franchise fee cap" here.
D14: Leave blank if no franchise fee and/or no franchise fee cap.
C17: 3. Do you pay a marketing fee on each transaction? | J17: Marketing Fee
C18: If yes, fill in the flat fee to be deducted from each transaction or % deducted from each transaction.
D19: Leave blank if no per transaction marketing fee. | L19: Flat Fee | N19: Marketing Fee as a %.
C21: Is there a "marketing fee cap"? | J21: Marketing Fee Cap
C22: If you contribute marketing fees from each transaction until you have reached a specific threshold, the answer is yes. Enter your "marketing fee cap" here.
D23: Leave blank if no marketing fee and/or no marketing fee cap.
A26: 4. Commission Structure -
A27: Is your split dependent on an Office Cap or Fair Share? | K27: Do you have a progressive split structure?
L28: If your split is on a sliding scale, sometimes referred to as a progressive split, based on total earned income year to date, enter the upper end of each of the tiers below along with the corresponding split as a %.
B29: Enter office cap or fair share here. | D29: Office Cap / Fair Share
A30: For example, if you have a fair share or office cap of $40,000. You may start the year with a 50/50 split until you have paid the office $40,000. Once you have met your fair share/office cap, your split would change. | E30: 8000 | K30: % of gross commission | N30: Fill-In Earned Income Tiers .
N32: 0 | P32: to
A33: What is your starting split at the beginning of each year?
E34: Starting Split as a % | N34: =Q32+1 -> 1 | P34: to
B35: Enter this as your percentage. | F35: 0.68 | K35: Must contain a value greater than 0 | Q35: Leave blank if last tier.
A36: For example, if you are on a 60/40 split, where you receive 60% and 40% goes to the office, enter 60%. | F36: Must enter a value. | N36: =Q34+1 -> 1 | P36: to
K37: Must contain a value greater than 0 | Q37: Leave blank if last tier.
A38: What is your split after office cap/fair share has been met? | N38: =Q36+1 -> 1 | P38: to
E39: Secondary Split as a % | K39: Enter 100% unless split is applied | Q39: Leave blank if last tier.
B40: Enter this as your percentage. | F40: 0.85 | N40: =Q38+1 -> 1 | P40: to
A41: For example, if you are on a 80/20 split, where you receive 80% and 20% goes to the office, enter 80%. | K41: Enter 100% unless split is applied | Q41: Leave blank if last tier.
E42: Note: If you go to 100% commission once you meet your cap/fair share, enter 100% here. | N42: =Q40+1 -> 1 | P42: +
K43: Enter 100% unless split is applied | Q43: **Blue outlined boxes indicate a value is needed.

Sheet Business Tracker
K1: 2025 Business Tracker
A2: "Warm" Prospects | I2: "Hot" and Active Prospects | Q2: Under Contract | Y2: Closed Transactions
AC3: Buy
AC4: Sell
B5: Contact Date (mm/dd) | C5: Client Name | D5: P/P Rating | E5: Estimated Sales Price | F5: % | G5: Potential Gross Commission Income | J5: Contact Date (mm/dd) | K5: Client Name | L5: P/P Rating | M5: Estimated Sales Price | N5: % | O5: Potential Gross Commission Income | Q5: Client Name | R5: Notes: Buy/Sell, signed agreements, status, updates | S5: Closing date | T5: For PIE Summary | U5: Sales Price | V5: % | W5: Estimated GCI | Z5: Closing date | AA5: Closing Month-for PIE Summary | AB5: Client Name | AC5: Buy/ Sell | AD5: Sales Price | AE5: % | AF5: Gross Commission Income
B6: 45895 | C6: Dennis Greza | E6: 650000 | F6: 0.03 | G6: =E6*F6 -> 19500 | J6: 45945 | K6: Andrew Papantoniou | M6: 600000 | N6: 0.03 | O6: =N6*M6 -> 18000 | Q6: Karla & Daniel | R6: rent | S6: 46006 | U6: 2350 | V6: 0 | W6: =U6*V6 -> 0 | Z6: =IF('Closed Transactions'!A3="", "",'Closed Transactions'!A3) -> 45667 | AA6: =MONTH(Z6) -> 1 | AB6: =IF('Closed Transactions'!F3="","",'Closed Transactions'!F3) -> Kevin Zhao | AC6: =IF(AND('Closed Transactions'!B3="",'Closed Transactions'!C3=""),"",IF('Closed Transactions'!B3="","Sell","Buy")) -> Buy | AD6: ='Closed Transactions'!I3 -> 610000 | AE6: =IF('Closed Transactions'!J3="","",'Closed Transactions'!J3) -> 0.025 | AF6: =IF('Closed Transactions'!K3="","", 'Closed Transactions'!K3) -> 15250
B7: 45896 | C7: Zia Hassanzadeh | E7: 700000 | F7: 0.03 | G7: =E7*F7 -> 21000 | J7: 45975 | K7: Leonard Abreu | M7: 500000 | N7: 0.025 | O7: =N7*M7 -> 12500 | W7: =U7*V7 -> 0 | Z7: =IF('Closed Transactions'!A4="", "",'Closed Transactions'!A4) -> 45706 | AA7: =MONTH(Z7) -> 2 | AB7: =IF('Closed Transactions'!F4="","",'Closed Transactions'!F4) -> Cristina Samaha | AC7: =IF(AND('Closed Transactions'!B4="",'Closed Transactions'!C4=""),"",IF('Closed Transactions'!B4="","Sell","Buy")) -> Buy | AD7: ='Closed Transactions'!I4 -> 415900 | AE7: =IF('Closed Transactions'!J4="","",'Closed Transactions'!J4) -> 0.024044241 | AF7: =IF('Closed Transactions'!K4="","", 'Closed Transactions'!K4) -> 10000
B8: 45930 | C8: Kyria | E8: 250000 | F8: 0.0075 | G8: =E8*F8 -> 1875 | J8: 45994 | K8: Sarah & Sam Bellet | M8: 1250000 | N8: 0.03 | O8: =N8*M8 -> 37500 | W8: =U8*V8 -> 0 | Z8: =IF('Closed Transactions'!A5="", "",'Closed Transactions'!A5) -> 45717 | AA8: =MONTH(Z8) -> 3 | AB8: =IF('Closed Transactions'!F5="","",'Closed Transactions'!F5) -> Kim & Damon Sidur | AC8: =IF(AND('Closed Transactions'!B5="",'Closed Transactions'!C5=""),"",IF('Closed Transactions'!B5="","Sell","Buy")) -> Buy | AD8: ='Closed Transactions'!I5 -> 2650 | AE8: =IF('Closed Transactions'!J5="","",'Closed Transactions'!J5) -> 0.25 | AF8: =IF('Closed Transactions'!K5="","", 'Closed Transactions'!K5) -> 662.5
B9: 45933 | C9: Amelia Stansell | E9: 750000 | F9: 0.03 | G9: =E9*F9 -> 22500 | J9: 45995 | K9: Michael Passante | M9: 250000 | N9: 0.03 | O9: =N9*M9 -> 7500 | W9: =U9*V9 -> 0 | Z9: =IF('Closed Transactions'!A6="", "",'Closed Transactions'!A6) -> 45724 | AA9: =MONTH(Z9) -> 3 | AB9: =IF('Closed Transactions'!F6="","",'Closed Transactions'!F6) -> Anne Duffy, Elizabeth & Ariel | AC9: =IF(AND('Closed Transactions'!B6="",'Closed Transactions'!C6=""),"",IF('Closed Transactions'!B6="","Sell","Buy")) -> Buy | AD9: ='Closed Transactions'!I6 -> 2995 | AE9: =IF('Closed Transactions'!J6="","",'Closed Transactions'!J6) -> 1 | AF9: =IF('Closed Transactions'!K6="","", 'Closed Transactions'!K6) -> 2995
B10: 45933 | C10: Joe Catalano | E10: 500000 | F10: 0.03 | G10: =E10*F10 -> 15000 | J10: 46000 | K10: Robert Yates | M10: 350000 | N10: 0.03 | O10: =N10*M10 -> 10500 | W10: =U10*V10 -> 0 | Z10: =IF('Closed Transactions'!A7="", "",'Closed Transactions'!A7) -> 45757 | AA10: =MONTH(Z10) -> 4 | AB10: =IF('Closed Transactions'!F7="","",'Closed Transactions'!F7) -> Lindsey Jasper & Ben Fielder | AC10: =IF(AND('Closed Transactions'!B7="",'Closed Transactions'!C7=""),"",IF('Closed Transactions'!B7="","Sell","Buy")) -> Buy | AD10: ='Closed Transactions'!I7 -> 750000 | AE10: =IF('Closed Transactions'!J7="","",'Closed Transactions'!J7) -> 0.03 | AF10: =IF('Closed Transactions'!K7="","", 'Closed Transactions'!K7) -> 22500
B11: 45936 | C11: Tom Palmer | E11: 500000 | F11: 0.03 | G11: =E11*F11 -> 15000 | J11: 46000 | K11: Zubeda & Ashraf Kadri | M11: 550000 | N11: 0.03 | O11: =N11*M11 -> 16500 | T11: =MONTH(S11) -> 1 | W11: =U11*V11 -> 0 | Z11: =IF('Closed Transactions'!A8="", "",'Closed Transactions'!A8) -> 45758 | AA11: =MONTH(Z11) -> 4 | AB11: =IF('Closed Transactions'!F8="","",'Closed Transactions'!F8) -> Doug Church | AC11: =IF(AND('Closed Transactions'!B8="",'Closed Transactions'!C8=""),"",IF('Closed Transactions'!B8="","Sell","Buy")) -> Sell | AD11: ='Closed Transactions'!I8 -> 1300000 | AE11: =IF('Closed Transactions'!J8="","",'Closed Transactions'!J8) -> 0.03 | AF11: =IF('Closed Transactions'!K8="","", 'Closed Transactions'!K8) -> 39000
B12: 45952 | C12: Joe Garon - Richmond referral | E12: 600000 | F12: 0.0075 | G12: =E12*F12 -> 4500 | J12: 46001 | K12: Alec Hurley | M12: 800000 | N12: 0.025 | O12: =N12*M12 -> 20000 | T12: =MONTH(S12) -> 1 | W12: =U12*V12 -> 0 | Z12: =IF('Closed Transactions'!A9="", "",'Closed Transactions'!A9) -> 45828 | AA12: =MONTH(Z12) -> 6 | AB12: =IF('Closed Transactions'!F9="","",'Closed Transactions'!F9) -> Ashraf Kadri | AC12: =IF(AND('Closed Transactions'!B9="",'Closed Transactions'!C9=""),"",IF('Closed Transactions'!B9="","Sell","Buy")) -> Buy | AD12: ='Closed Transactions'!I9 -> 390000 | AE12: =IF('Closed Transactions'!J9="","",'Closed Transactions'!J9) -> 0.0075 | AF12: =IF('Closed Transactions'!K9="","", 'Closed Transactions'!K9) -> 2925
B13: 45957 | C13: Carolyn Chappell | E13: 650000 | F13: 0.03 | G13: =E13*F13 -> 19500 | J13: 46002 | K13: Jon Lindenberg - investment | M13: 650000 | N13: 0.03 | O13: =N13*M13 -> 19500 | T13: =MONTH(S13) -> 1 | W13: =U13*V13 -> 0 | Z13: =IF('Closed Transactions'!A10="", "",'Closed Transactions'!A10) -> 45838 | AA13: =MONTH(Z13) -> 6 | AB13: =IF('Closed Transactions'!F10="","",'Closed Transactions'!F10) -> Nathan Desnoyers | AC13: =IF(AND('Closed Transactions'!B10="",'Closed Transactions'!C10=""),"",IF('Closed Transactions'!B10="","Sell","Buy")) -> Sell | AD13: ='Closed Transactions'!I10 -> 365000 | AE13: =IF('Closed Transactions'!J10="","",'Closed Transactions'!J10) -> 0 | AF13: =IF('Closed Transactions'!K10="","", 'Closed Transactions'!K10) -> 0
B14: 45958 | C14: Ronald Joseph - Vorsa | E14: 1800000 | F14: 0.025 | G14: =E14*F14 -> 45000 | J14: 46004 | K14: James T Bonner III | M14: 500000 | N14: 0.0225 | O14: =N14*M14 -> 11250 | T14: =MONTH(S14) -> 1 | W14: =U14*V14 -> 0 | Z14: =IF('Closed Transactions'!A11="", "",'Closed Transactions'!A11) -> 45839 | AA14: =MONTH(Z14) -> 7 | AB14: =IF('Closed Transactions'!F11="","",'Closed Transactions'!F11) -> Saria Alshaikhalia | AC14: =IF(AND('Closed Transactions'!B11="",'Closed Transactions'!C11=""),"",IF('Closed Transactions'!B11="","Sell","Buy")) -> Buy | AD14: ='Closed Transactions'!I11 -> 2195 | AE14: =IF('Closed Transactions'!J11="","",'Closed Transactions'!J11) -> 0.25 | AF14: =IF('Closed Transactions'!K11="","", 'Closed Transactions'!K11) -> 548.75
B15: 45960 | C15: Kevin Governor | E15: 1100000 | F15: 0.03 | G15: =E15*F15 -> 33000 | J15: 46004 | K15: Jordan Northrup | M15: 400000 | N15: 0.02 | O15: =N15*M15 -> 8000 | T15: =MONTH(S15) -> 1 | W15: =U15*V15 -> 0 | Z15: =IF('Closed Transactions'!A12="", "",'Closed Transactions'!A12) -> 45839 | AA15: =MONTH(Z15) -> 7 | AB15: =IF('Closed Transactions'!F12="","",'Closed Transactions'!F12) -> Sneha Durgapal & Alex Hennessy | AC15: =IF(AND('Closed Transactions'!B12="",'Closed Transactions'!C12=""),"",IF('Closed Transactions'!B12="","Sell","Buy")) -> Buy | AD15: ='Closed Transactions'!I12 -> 3150 | AE15: =IF('Closed Transactions'!J12="","",'Closed Transactions'!J12) -> 0 | AF15: =IF('Closed Transactions'!K12="","", 'Closed Transactions'!K12) -> 0
B16: 45968 | C16: JR Spear | E16: 500000 | F16: 0.03 | G16: =E16*F16 -> 15000 | J16: 46005 | K16: Ramzi Samaha | M16: 600000 | N16: 0.03 | O16: =N16*M16 -> 18000 | T16: =MONTH(S16) -> 1 | W16: =U16*V16 -> 0 | Z16: =IF('Closed Transactions'!A13="", "",'Closed Transactions'!A13) -> 45845 | AA16: =MONTH(Z16) -> 7 | AB16: =IF('Closed Transactions'!F13="","",'Closed Transactions'!F13) -> Jared Traggic & Kiana Spearman | AC16: =IF(AND('Closed Transactions'!B13="",'Closed Transactions'!C13=""),"",IF('Closed Transactions'!B13="","Sell","Buy")) -> Buy | AD16: ='Closed Transactions'!I13 -> 2400 | AE16: =IF('Closed Transactions'!J13="","",'Closed Transactions'!J13) -> 0.25 | AF16: =IF('Closed Transactions'!K13="","", 'Closed Transactions'!K13) -> 600
B17: 45969 | C17: Melisa & Rob Banks | E17: 1700000 | F17: 0.03 | G17: =E17*F17 -> 51000 | J17: 46006 | K17: Miguel Shaban | M17: 750000 | N17: 0.03 | O17: =N17*M17 -> 22500 | T17: =MONTH(S17) -> 1 | W17: =U17*V17 -> 0 | Z17: =IF('Closed Transactions'!A14="", "",'Closed Transactions'!A14) -> 45853 | AA17: =MONTH(Z17) -> 7 | AB17: =IF('Closed Transactions'!F14="","",'Closed Transactions'!F14) -> Kristine & Ken Delos Reyes | AC17: =IF(AND('Closed Transactions'!B14="",'Closed Transactions'!C14=""),"",IF('Closed Transactions'!B14="","Sell","Buy")) -> Buy | AD17: ='Closed Transactions'!I14 -> 665280 | AE17: =IF('Closed Transactions'!J14="","",'Closed Transactions'!J14) -> 0.00901876 | AF17: =IF('Closed Transactions'!K14="","", 'Closed Transactions'!K14) -> 6000.0007
B18: 45992 | C18: Liam Mulcahy | E18: 850000 | F18: 0.03 | G18: =E18*F18 -> 25500 | J18: 46003 | K18: Jon Jeyachandran | M18: 400000 | N18: 0.03 | O18: =N18*M18 -> 12000 | T18: =MONTH(S18) -> 1 | W18: =U18*V18 -> 0 | Z18: =IF('Closed Transactions'!A15="", "",'Closed Transactions'!A15) -> 45884 | AA18: =MONTH(Z18) -> 8 | AB18: =IF('Closed Transactions'!F15="","",'Closed Transactions'!F15) -> Anne Duffy, Joshua Foote, Kate McCusker | AC18: =IF(AND('Closed Transactions'!B15="",'Closed Transactions'!C15=""),"",IF('Closed Transactions'!B15="","Sell","Buy")) -> Buy | AD18: ='Closed Transactions'!I15 -> 3295 | AE18: =IF('Closed Transactions'!J15="","",'Closed Transactions'!J15) -> 1 | AF18: =IF('Closed Transactions'!K15="","", 'Closed Transactions'!K15) -> 3295
B19: 45993 | C19: Norberto Daluz | E19: 1400000 | F19: 0.03 | G19: =E19*F19 -> 42000 | J19: 46006 | K19: Dave Eluma | M19: 650000 | N19: 0.03 | O19: =N19*M19 -> 19500 | T19: =MONTH(S19) -> 1 | W19: =U19*V19 -> 0 | Z19: =IF('Closed Transactions'!A16="", "",'Closed Transactions'!A16) -> 45903 | AA19: =MONTH(Z19) -> 9 | AB19: =IF('Closed Transactions'!F16="","",'Closed Transactions'!F16) -> Cintia Samaha Desnoyers | AC19: =IF(AND('Closed Transactions'!B16="",'Closed Transactions'!C16=""),"",IF('Closed Transactions'!B16="","Sell","Buy")) -> Buy | AD19: ='Closed Transactions'!I16 -> 615000 | AE19: =IF('Closed Transactions'!J16="","",'Closed Transactions'!J16) -> 0 | AF19: =IF('Closed Transactions'!K16="","", 'Closed Transactions'!K16) -> 0
B20: 45994 | C20: Rachel McQuillen | E20: 600000 | F20: 0.03 | G20: =E20*F20 -> 18000 | O20: =N20*M20 -> 0 | T20: =MONTH(S20) -> 1 | W20: =U20*V20 -> 0 | Z20: =IF('Closed Transactions'!A17="", "",'Closed Transactions'!A17) -> 45910 | AA20: =MONTH(Z20) -> 9 | AB20: =IF('Closed Transactions'!F17="","",'Closed Transactions'!F17) -> Ashleigh Verma & Tapinder Garcha | AC20: =IF(AND('Closed Transactions'!B17="",'Closed Transactions'!C17=""),"",IF('Closed Transactions'!B17="","Sell","Buy")) -> Sell | AD20: ='Closed Transactions'!I17 -> 770000 | AE20: =IF('Closed Transactions'!J17="","",'Closed Transactions'!J17) -> 0.02 | AF20: =IF('Closed Transactions'!K17="","", 'Closed Transactions'!K17) -> 15400
B21: 45995 | C21: Allen Liu | E21: 750000 | F21: 0.03 | G21: =E21*F21 -> 22500 | O21: =N21*M21 -> 0 | T21: =MONTH(S21) -> 1 | W21: =U21*V21 -> 0 | Z21: =IF('Closed Transactions'!A18="", "",'Closed Transactions'!A18) -> 45920 | AA21: =MONTH(Z21) -> 9 | AB21: =IF('Closed Transactions'!F18="","",'Closed Transactions'!F18) -> Cintia Samaha Desnoyers | AC21: =IF(AND('Closed Transactions'!B18="",'Closed Transactions'!C18=""),"",IF('Closed Transactions'!B18="","Sell","Buy")) -> Sell | AD21: ='Closed Transactions'!I18 -> 2400 | AE21: =IF('Closed Transactions'!J18="","",'Closed Transactions'!J18) -> 0 | AF21: =IF('Closed Transactions'!K18="","", 'Closed Transactions'!K18) -> 0
B22: 45995 | C22: Nick Minanago | E22: 750000 | F22: 0.03 | G22: =E22*F22 -> 22500 | O22: =N22*M22 -> 0 | T22: =MONTH(S22) -> 1 | W22: =U22*V22 -> 0 | Z22: =IF('Closed Transactions'!A19="", "",'Closed Transactions'!A19) -> 45981 | AA22: =MONTH(Z22) -> 11 | AB22: =IF('Closed Transactions'!F19="","",'Closed Transactions'!F19) -> Noel Contreras | AC22: =IF(AND('Closed Transactions'!B19="",'Closed Transactions'!C19=""),"",IF('Closed Transactions'!B19="","Sell","Buy")) -> Sell | AD22: ='Closed Transactions'!I19 -> 1500 | AE22: =IF('Closed Transactions'!J19="","",'Closed Transactions'!J19) -> 0 | AF22: =IF('Closed Transactions'!K19="","", 'Closed Transactions'!K19) -> 0
B23: 45995 | C23: Cheryl Zellmer | E23: 350000 | F23: 0.03 | G23: =E23*F23 -> 10500 | O23: =N23*M23 -> 0 | T23: =MONTH(S23) -> 1 | W23: =U23*V23 -> 0 | Z23: =IF('Closed Transactions'!A20="", "",'Closed Transactions'!A20) | AA23: =MONTH(Z23) -> #VALUE! | AB23: =IF('Closed Transactions'!F20="","",'Closed Transactions'!F20) | AC23: =IF(AND('Closed Transactions'!B20="",'Closed Transactions'!C20=""),"",IF('Closed Transactions'!B20="","Sell","Buy")) | AD23: ='Closed Transactions'!I20 -> 0 | AE23: =IF('Closed Transactions'!J20="","",'Closed Transactions'!J20) | AF23: =IF('Closed Transactions'!K20="","", 'Closed Transactions'!K20)
B24: 45995 | C24: Jay Chikobe | E24: 550000 | F24: 0.03 | G24: =E24*F24 -> 16500 | O24: =N24*M24 -> 0 | T24: =MONTH(S24) -> 1 | W24: =U24*V24 -> 0 | Z24: =IF('Closed Transactions'!A21="", "",'Closed Transactions'!A21) | AA24: =MONTH(Z24) -> #VALUE! | AB24: =IF('Closed Transactions'!F21="","",'Closed Transactions'!F21) | AC24: =IF(AND('Closed Transactions'!B21="",'Closed Transactions'!C21=""),"",IF('Closed Transactions'!B21="","Sell","Buy")) | AD24: ='Closed Transactions'!I21 -> 0 | AE24: =IF('Closed Transactions'!J21="","",'Closed Transactions'!J21) | AF24: =IF('Closed Transactions'!K21="","", 'Closed Transactions'!K21)
B25: 45995 | C25: Julia Taylor | E25: 550000 | F25: 0.03 | G25: =E25*F25 -> 16500 | O25: =N25*M25 -> 0 | T25: =MONTH(S25) -> 1 | W25: =U25*V25 -> 0 | Z25: =IF('Closed Transactions'!A22="", "",'Closed Transactions'!A22) | AA25: =MONTH(Z25) -> #VALUE! | AB25: =IF('Closed Transactions'!F22="","",'Closed Transactions'!F22) | AC25: =IF(AND('Closed Transactions'!B22="",'Closed Transactions'!C22=""),"",IF('Closed Transactions'!B22="","Sell","Buy")) | AD25: ='Closed Transactions'!I22 -> 0 | AE25: =IF('Closed Transactions'!J22="","",'Closed Transactions'!J22) | AF25: =IF('Closed Transactions'!K22="","", 'Closed Transactions'!K22)
B26: 45995 | C26: Raja Bala | E26: 550000 | F26: 0.03 | G26: =E26*F26 -> 16500 | O26: =N26*M26 -> 0 | T26: =MONTH(S26) -> 1 | W26: =U26*V26 -> 0 | Z26: =IF('Closed Transactions'!A23="", "",'Closed Transactions'!A23) | AA26: =MONTH(Z26) -> #VALUE! | AB26: =IF('Closed Transactions'!F23="","",'Closed Transactions'!F23) | AC26: =IF(AND('Closed Transactions'!B23="",'Closed Transactions'!C23=""),"",IF('Closed Transactions'!B23="","Sell","Buy")) | AD26: ='Closed Transactions'!I23 -> 0 | AE26: =IF('Closed Transactions'!J23="","",'Closed Transactions'!J23) | AF26: =IF('Closed Transactions'!K23="","", 'Closed Transactions'!K23)
B27: 45995 | C27: Cris Gains | E27: 500000 | F27: 0.03 | G27: =E27*F27 -> 15000 | O27: =N27*M27 -> 0 | T27: =MONTH(S27) -> 1 | W27: =U27*V27 -> 0 | Z27: =IF('Closed Transactions'!A24="", "",'Closed Transactions'!A24) | AA27: =MONTH(Z27) -> #VALUE! | AB27: =IF('Closed Transactions'!F24="","",'Closed Transactions'!F24) | AC27: =IF(AND('Closed Transactions'!B24="",'Closed Transactions'!C24=""),"",IF('Closed Transactions'!B24="","Sell","Buy")) | AD27: ='Closed Transactions'!I24 -> 0 | AE27: =IF('Closed Transactions'!J24="","",'Closed Transactions'!J24) | AF27: =IF('Closed Transactions'!K24="","", 'Closed Transactions'!K24)
B28: 45995 | C28: Samantha Jennings | E28: 750000 | F28: 0.03 | G28: =E28*F28 -> 22500 | O28: =N28*M28 -> 0 | T28: =MONTH(S28) -> 1 | W28: =U28*V28 -> 0 | Z28: =IF('Closed Transactions'!A25="", "",'Closed Transactions'!A25) | AA28: =MONTH(Z28) -> #VALUE! | AB28: =IF('Closed Transactions'!F25="","",'Closed Transactions'!F25) | AC28: =IF(AND('Closed Transactions'!B25="",'Closed Transactions'!C25=""),"",IF('Closed Transactions'!B25="","Sell","Buy")) | AD28: ='Closed Transactions'!I25 -> 0 | AE28: =IF('Closed Transactions'!J25="","",'Closed Transactions'!J25) | AF28: =IF('Closed Transactions'!K25="","", 'Closed Transactions'!K25)
B29: 45995 | C29: The Miravis | E29: 750000 | F29: 0.03 | G29: =E29*F29 -> 22500 | O29: =N29*M29 -> 0 | T29: =MONTH(S29) -> 1 | W29: =U29*V29 -> 0 | Z29: =IF('Closed Transactions'!A26="", "",'Closed Transactions'!A26) | AA29: =MONTH(Z29) -> #VALUE! | AB29: =IF('Closed Transactions'!F26="","",'Closed Transactions'!F26) | AC29: =IF(AND('Closed Transactions'!B26="",'Closed Transactions'!C26=""),"",IF('Closed Transactions'!B26="","Sell","Buy")) | AD29: ='Closed Transactions'!I26 -> 0 | AE29: =IF('Closed Transactions'!J26="","",'Closed Transactions'!J26) | AF29: =IF('Closed Transactions'!K26="","", 'Closed Transactions'!K26)
B30: 45996 | C30: Henry Asherbranner | E30: 550000 | F30: 0.03 | G30: =E30*F30 -> 16500 | O30: =N30*M30 -> 0 | T30: =MONTH(S30) -> 1 | W30: =U30*V30 -> 0 | Z30: =IF('Closed Transactions'!A27="", "",'Closed Transactions'!A27) | AA30: =MONTH(Z30) -> #VALUE! | AB30: =IF('Closed Transactions'!F27="","",'Closed Transactions'!F27) | AC30: =IF(AND('Closed Transactions'!B27="",'Closed Transactions'!C27=""),"",IF('Closed Transactions'!B27="","Sell","Buy")) | AD30: ='Closed Transactions'!I27 -> 0 | AE30: =IF('Closed Transactions'!J27="","",'Closed Transactions'!J27) | AF30: =IF('Closed Transactions'!K27="","", 'Closed Transactions'!K27)
B31: 45996 | C31: Ben Martin | E31: 450000 | F31: 0.0075 | G31: =E31*F31 -> 3375 | O31: =N31*M31 -> 0 | T31: =MONTH(S31) -> 1 | W31: =U31*V31 -> 0 | Z31: =IF('Closed Transactions'!A28="", "",'Closed Transactions'!A28) | AA31: =MONTH(Z31) -> #VALUE! | AB31: =IF('Closed Transactions'!F28="","",'Closed Transactions'!F28) | AC31: =IF(AND('Closed Transactions'!B28="",'Closed Transactions'!C28=""),"",IF('Closed Transactions'!B28="","Sell","Buy")) | AD31: ='Closed Transactions'!I28 -> 0 | AE31: =IF('Closed Transactions'!J28="","",'Closed Transactions'!J28) | AF31: =IF('Closed Transactions'!K28="","", 'Closed Transactions'!K28)
... B34: 45999 | C34: Austin Kennedy | E34: 750000 | F34: 0.03 | G34: =E34*F34 -> 22500 | O34: =N34*M34 -> 0 | T34: =MONTH(S34) -> 1 | W34: =U34*V34 -> 0 | Z34: =IF('Closed Transactions'!A31="", "",'Closed Transactions'!A31) | AA34: =MONTH(Z34) -> #VALUE! | AB34: =IF('Closed Transactions'!F31="","",'Closed Transactions'!F31) | AC34: =IF(AND('Closed Transactions'!B31="",'Closed Transactions'!C31=""),"",IF('Closed Transactions'!B31="","Sell","Buy")) | AD34: ='Closed Transactions'!I31 -> 0 | AE34: =IF('Closed Transactions'!J31="","",'Closed Transactions'!J31) | AF34: =IF('Closed Transactions'!K31="","", 'Closed Transactions'!K31)
B35: 46000 | C35: Victor Rhoder | E35: 1200000 | F35: 0.03 | G35: =E35*F35 -> 36000 | O35: =N35*M35 -> 0 | Q35: Total Under Contract | W35: =SUM(W6:W34) -> 0 | Z35: =IF('Closed Transactions'!A32="", "",'Closed Transactions'!A32) | AA35: =MONTH(Z35) -> #VALUE! | AB35: =IF('Closed Transactions'!F32="","",'Closed Transactions'!F32) | AC35: =IF(AND('Closed Transactions'!B32="",'Closed Transactions'!C32=""),"",IF('Closed Transactions'!B32="","Sell","Buy")) | AD35: ='Closed Transactions'!I32 -> 0 | AE35: =IF('Closed Transactions'!J32="","",'Closed Transactions'!J32) | AF35: =IF('Closed Transactions'!K32="","", 'Closed Transactions'!K32)
B36: 46000 | C36: Quinton - Richmond referral | E36: 500000 | F36: 0.0075 | G36: =E36*F36 -> 3750 | I36: "Hot" and Confused Prospects | Q36: Signed Listing Agreements | Z36: =IF('Closed Transactions'!A33="", "",'Closed Transactions'!A33) | AA36: =MONTH(Z36) -> #VALUE! | AB36: =IF('Closed Transactions'!F33="","",'Closed Transactions'!F33) | AC36: =IF(AND('Closed Transactions'!B33="",'Closed Transactions'!C33=""),"",IF('Closed Transactions'!B33="","Sell","Buy")) | AD36: ='Closed Transactions'!I33 -> 0 | AE36: =IF('Closed Transactions'!J33="","",'Closed Transactions'!J33) | AF36: =IF('Closed Transactions'!K33="","", 'Closed Transactions'!K33)
B37: 46000 | C37: Roland | E37: 400000 | F37: 0.03 | G37: =E37*F37 -> 12000 | Z37: =IF('Closed Transactions'!A34="", "",'Closed Transactions'!A34) | AA37: =MONTH(Z37) -> #VALUE! | AB37: =IF('Closed Transactions'!F34="","",'Closed Transactions'!F34) | AC37: =IF(AND('Closed Transactions'!B34="",'Closed Transactions'!C34=""),"",IF('Closed Transactions'!B34="","Sell","Buy")) | AD37: ='Closed Transactions'!I34 -> 0 | AE37: =IF('Closed Transactions'!J34="","",'Closed Transactions'!J34) | AF37: =IF('Closed Transactions'!K34="","", 'Closed Transactions'!K34)
B38: 46000 | C38: Johnny Sower | E38: 650000 | F38: 0.03 | G38: =E38*F38 -> 19500 | J38: Date | K38: Client Name | L38: P/P Rating | M38: Est. Sales Price | N38: % | O38: Potential GCI | Q38: Client Name | R38: Notes: Buy/Sell, signed agreements, status, updates | S38: Closing date | T38: For PIE Summary | U38: Sales Price | V38: % | W38: Estimated GCI | Z38: =IF('Closed Transactions'!A35="", "",'Closed Transactions'!A35) | AA38: =MONTH(Z38) -> #VALUE! | AB38: =IF('Closed Transactions'!F35="","",'Closed Transactions'!F35) | AC38: =IF(AND('Closed Transactions'!B35="",'Closed Transactions'!C35=""),"",IF('Closed Transactions'!B35="","Sell","Buy")) | AD38: ='Closed Transactions'!I35 -> 0 | AE38: =IF('Closed Transactions'!J35="","",'Closed Transactions'!J35) | AF38: =IF('Closed Transactions'!K35="","", 'Closed Transactions'!K35)
B39: 46001 | C39: John McGeehan | E39: 350000 | F39: 0.03 | G39: =E39*F39 -> 10500 | J39: 46001 | K39: Lucy Pearl | M39: 700000 | N39: 0.03 | O39: =N39*M39 -> 21000 | T39: =MONTH(S39) -> 1 | W39: =U39*V39 -> 0 | Z39: =IF('Closed Transactions'!A36="", "",'Closed Transactions'!A36) | AA39: =MONTH(Z39) -> #VALUE! | AB39: =IF('Closed Transactions'!F36="","",'Closed Transactions'!F36) | AC39: =IF(AND('Closed Transactions'!B36="",'Closed Transactions'!C36=""),"",IF('Closed Transactions'!B36="","Sell","Buy")) | AD39: ='Closed Transactions'!I36 -> 0 | AE39: =IF('Closed Transactions'!J36="","",'Closed Transactions'!J36) | AF39: =IF('Closed Transactions'!K36="","", 'Closed Transactions'!K36)
B40: 46001 | C40: Linh Huynh | E40: 600000 | F40: 0.03 | G40: =E40*F40 -> 18000 | O40: =N40*M40 -> 0 | T40: =MONTH(S40) -> 1 | W40: =U40*V40 -> 0 | Z40: =IF('Closed Transactions'!A37="", "",'Closed Transactions'!A37) | AA40: =MONTH(Z40) -> #VALUE! | AB40: =IF('Closed Transactions'!F37="","",'Closed Transactions'!F37) | AC40: =IF(AND('Closed Transactions'!B37="",'Closed Transactions'!C37=""),"",IF('Closed Transactions'!B37="","Sell","Buy")) | AD40: ='Closed Transactions'!I37 -> 0 | AE40: =IF('Closed Transactions'!J37="","",'Closed Transactions'!J37) | AF40: =IF('Closed Transactions'!K37="","", 'Closed Transactions'!K37)
B41: 46001 | C41: Art Hamerschlag | E41: 1600000 | F41: 0.03 | G41: =E41*F41 -> 48000 | O41: =N41*M41 -> 0 | T41: =MONTH(S41) -> 1 | W41: =U41*V41 -> 0 | Z41: =IF('Closed Transactions'!A38="", "",'Closed Transactions'!A38) | AA41: =MONTH(Z41) -> #VALUE! | AB41: =IF('Closed Transactions'!F38="","",'Closed Transactions'!F38) | AC41: =IF(AND('Closed Transactions'!B38="",'Closed Transactions'!C38=""),"",IF('Closed Transactions'!B38="","Sell","Buy")) | AD41: ='Closed Transactions'!I38 -> 0 | AE41: =IF('Closed Transactions'!J38="","",'Closed Transactions'!J38) | AF41: =IF('Closed Transactions'!K38="","", 'Closed Transactions'!K38)
B42: 46001 | C42: Victor Kremer | E42: 500000 | F42: 0.03 | G42: =E42*F42 -> 15000 | O42: =N42*M42 -> 0 | T42: =MONTH(S42) -> 1 | W42: =U42*V42 -> 0 | Z42: =IF('Closed Transactions'!A39="", "",'Closed Transactions'!A39) | AA42: =MONTH(Z42) -> #VALUE! | AB42: =IF('Closed Transactions'!F39="","",'Closed Transactions'!F39) | AC42: =IF(AND('Closed Transactions'!B39="",'Closed Transactions'!C39=""),"",IF('Closed Transactions'!B39="","Sell","Buy")) | AD42: ='Closed Transactions'!I39 -> 0 | AE42: =IF('Closed Transactions'!J39="","",'Closed Transactions'!J39) | AF42: =IF('Closed Transactions'!K39="","", 'Closed Transactions'!K39)
B43: 46002 | C43: Sarah Miller | E43: 550000 | F43: 0.03 | G43: =E43*F43 -> 16500 | O43: =N43*M43 -> 0 | T43: =MONTH(S43) -> 1 | W43: =U43*V43 -> 0 | Z43: =IF('Closed Transactions'!A40="", "",'Closed Transactions'!A40) | AA43: =MONTH(Z43) -> #VALUE! | AB43: =IF('Closed Transactions'!F40="","",'Closed Transactions'!F40) | AC43: =IF(AND('Closed Transactions'!B40="",'Closed Transactions'!C40=""),"",IF('Closed Transactions'!B40="","Sell","Buy")) | AD43: ='Closed Transactions'!I40 -> 0 | AE43: =IF('Closed Transactions'!J40="","",'Closed Transactions'!J40) | AF43: =IF('Closed Transactions'!K40="","", 'Closed Transactions'!K40)
B44: 46002 | C44: Darren Harvey | E44: 500000 | F44: 0.03 | G44: =E44*F44 -> 15000 | O44: =N44*M44 -> 0 | T44: =MONTH(S44) -> 1 | W44: =U44*V44 -> 0 | Z44: =IF('Closed Transactions'!A41="", "",'Closed Transactions'!A41) | AA44: =MONTH(Z44) -> #VALUE! | AB44: =IF('Closed Transactions'!F41="","",'Closed Transactions'!F41) | AC44: =IF(AND('Closed Transactions'!B41="",'Closed Transactions'!C41=""),"",IF('Closed Transactions'!B41="","Sell","Buy")) | AD44: ='Closed Transactions'!I41 -> 0 | AE44: =IF('Closed Transactions'!J41="","",'Closed Transactions'!J41) | AF44: =IF('Closed Transactions'!K41="","", 'Closed Transactions'!K41)
B45: 46003 | C45: Al Kulynych | E45: 700000 | F45: 0.03 | G45: =E45*F45 -> 21000 | O45: =N45*M45 -> 0 | T45: =MONTH(S45) -> 1 | W45: =U45*V45 -> 0 | Z45: =IF('Closed Transactions'!A42="", "",'Closed Transactions'!A42) | AA45: =MONTH(Z45) -> #VALUE! | AB45: =IF('Closed Transactions'!F42="","",'Closed Transactions'!F42) | AC45: =IF(AND('Closed Transactions'!B42="",'Closed Transactions'!C42=""),"",IF('Closed Transactions'!B42="","Sell","Buy")) | AD45: ='Closed Transactions'!I42 -> 0 | AE45: =IF('Closed Transactions'!J42="","",'Closed Transactions'!J42) | AF45: =IF('Closed Transactions'!K42="","", 'Closed Transactions'!K42)
B46: 46003 | C46: Anita Dekhan | E46: 450000 | F46: 0.03 | G46: =E46*F46 -> 13500 | O46: =N46*M46 -> 0 | T46: =MONTH(S46) -> 1 | W46: =U46*V46 -> 0 | Z46: =IF('Closed Transactions'!A43="", "",'Closed Transactions'!A43) | AA46: =MONTH(Z46) -> #VALUE! | AB46: =IF('Closed Transactions'!F43="","",'Closed Transactions'!F43) | AC46: =IF(AND('Closed Transactions'!B43="",'Closed Transactions'!C43=""),"",IF('Closed Transactions'!B43="","Sell","Buy")) | AD46: ='Closed Transactions'!I43 -> 0 | AE46: =IF('Closed Transactions'!J43="","",'Closed Transactions'!J43) | AF46: =IF('Closed Transactions'!K43="","", 'Closed Transactions'!K43)
B47: 46003 | C47: Ashley Belin | E47: 1250000 | F47: 0.03 | G47: =E47*F47 -> 37500 | O47: =N47*M47 -> 0 | T47: =MONTH(S47) -> 1 | W47: =U47*V47 -> 0 | Z47: =IF('Closed Transactions'!A44="", "",'Closed Transactions'!A44) | AA47: =MONTH(Z47) -> #VALUE! | AB47: =IF('Closed Transactions'!F44="","",'Closed Transactions'!F44) | AC47: =IF(AND('Closed Transactions'!B44="",'Closed Transactions'!C44=""),"",IF('Closed Transactions'!B44="","Sell","Buy")) | AD47: ='Closed Transactions'!I44 -> 0 | AE47: =IF('Closed Transactions'!J44="","",'Closed Transactions'!J44) | AF47: =IF('Closed Transactions'!K44="","", 'Closed Transactions'!K44)
B48: 46003 | C48: Brian & Becky | E48: 350000 | F48: 0.03 | G48: =E48*F48 -> 10500 | O48: =N48*M48 -> 0 | T48: =MONTH(S48) -> 1 | W48: =U48*V48 -> 0 | Z48: =IF('Closed Transactions'!A45="", "",'Closed Transactions'!A45) | AA48: =MONTH(Z48) -> #VALUE! | AB48: =IF('Closed Transactions'!F45="","",'Closed Transactions'!F45) | AC48: =IF(AND('Closed Transactions'!B45="",'Closed Transactions'!C45=""),"",IF('Closed Transactions'!B45="","Sell","Buy")) | AD48: ='Closed Transactions'!I45 -> 0 | AE48: =IF('Closed Transactions'!J45="","",'Closed Transactions'!J45) | AF48: =IF('Closed Transactions'!K45="","", 'Closed Transactions'!K45)
B49: 46003 | C49: Jess & Conor | E49: 400000 | F49: 0.03 | G49: =E49*F49 -> 12000 | O49: =N49*M49 -> 0 | T49: =MONTH(S49) -> 1 | W49: =U49*V49 -> 0 | Z49: =IF('Closed Transactions'!A46="", "",'Closed Transactions'!A46) | AA49: =MONTH(Z49) -> #VALUE! | AB49: =IF('Closed Transactions'!F46="","",'Closed Transactions'!F46) | AC49: =IF(AND('Closed Transactions'!B46="",'Closed Transactions'!C46=""),"",IF('Closed Transactions'!B46="","Sell","Buy")) | AD49: ='Closed Transactions'!I46 -> 0 | AE49: =IF('Closed Transactions'!J46="","",'Closed Transactions'!J46) | AF49: =IF('Closed Transactions'!K46="","", 'Closed Transactions'!K46)
B50: 46003 | C50: Sam Richardson | E50: 750000 | F50: 0.03 | G50: =E50*F50 -> 22500 | O50: =N50*M50 -> 0 | T50: =MONTH(S50) -> 1 | W50: =U50*V50 -> 0 | Z50: =IF('Closed Transactions'!A47="", "",'Closed Transactions'!A47) | AA50: =MONTH(Z50) -> #VALUE! | AB50: =IF('Closed Transactions'!F47="","",'Closed Transactions'!F47) | AC50: =IF(AND('Closed Transactions'!B47="",'Closed Transactions'!C47=""),"",IF('Closed Transactions'!B47="","Sell","Buy")) | AD50: ='Closed Transactions'!I47 -> 0 | AE50: =IF('Closed Transactions'!J47="","",'Closed Transactions'!J47) | AF50: =IF('Closed Transactions'!K47="","", 'Closed Transactions'!K47)
B51: 46003 | C51: Ben Michaelson | E51: 500000 | F51: 0.03 | G51: =E51*F51 -> 15000 | O51: =N51*M51 -> 0 | T51: =MONTH(S51) -> 1 | W51: =U51*V51 -> 0 | Z51: =IF('Closed Transactions'!A48="", "",'Closed Transactions'!A48) | AA51: =MONTH(Z51) -> #VALUE! | AB51: =IF('Closed Transactions'!F48="","",'Closed Transactions'!F48) | AC51: =IF(AND('Closed Transactions'!B48="",'Closed Transactions'!C48=""),"",IF('Closed Transactions'!B48="","Sell","Buy")) | AD51: ='Closed Transactions'!I48 -> 0 | AE51: =IF('Closed Transactions'!J48="","",'Closed Transactions'!J48) | AF51: =IF('Closed Transactions'!K48="","", 'Closed Transactions'!K48)
... B55: 46006 | C55: Devin Horn | E55: 400000 | F55: 0.03 | G55: =E55*F55 -> 12000 | O55: =N55*M55 -> 0 | T55: =MONTH(S55) -> 1 | W55: =U55*V55 -> 0 | Z55: =IF('Closed Transactions'!A52="", "",'Closed Transactions'!A52) | AA55: =MONTH(Z55) -> #VALUE! | AB55: =IF('Closed Transactions'!F52="","",'Closed Transactions'!F52) | AC55: =IF(AND('Closed Transactions'!B52="",'Closed Transactions'!C52=""),"",IF('Closed Transactions'!B52="","Sell","Buy")) | AD55: ='Closed Transactions'!I52 -> 0 | AE55: =IF('Closed Transactions'!J52="","",'Closed Transactions'!J52) | AF55: =IF('Closed Transactions'!K52="","", 'Closed Transactions'!K52)
G56: =E56*F56 -> 0 | O56: =N56*M56 -> 0 | T56: =MONTH(S56) -> 1 | W56: =U56*V56 -> 0 | Z56: =IF('Closed Transactions'!A53="", "",'Closed Transactions'!A53) | AA56: =MONTH(Z56) -> #VALUE! | AB56: =IF('Closed Transactions'!F53="","",'Closed Transactions'!F53) | AC56: =IF(AND('Closed Transactions'!B53="",'Closed Transactions'!C53=""),"",IF('Closed Transactions'!B53="","Sell","Buy")) | AD56: ='Closed Transactions'!I53 -> 0 | AE56: =IF('Closed Transactions'!J53="","",'Closed Transactions'!J53) | AF56: =IF('Closed Transactions'!K53="","", 'Closed Transactions'!K53)
G57: =E57*F57 -> 0 | O57: =N57*M57 -> 0 | T57: =MONTH(S57) -> 1 | W57: =U57*V57 -> 0 | Z57: =IF('Closed Transactions'!A54="", "",'Closed Transactions'!A54) | AA57: =MONTH(Z57) -> #VALUE! | AB57: =IF('Closed Transactions'!F54="","",'Closed Transactions'!F54) | AC57: =IF(AND('Closed Transactions'!B54="",'Closed Transactions'!C54=""),"",IF('Closed Transactions'!B54="","Sell","Buy")) | AD57: ='Closed Transactions'!I54 -> 0 | AE57: =IF('Closed Transactions'!J54="","",'Closed Transactions'!J54) | AF57: =IF('Closed Transactions'!K54="","", 'Closed Transactions'!K54)
G58: =E58*F58 -> 0 | O58: =N58*M58 -> 0 | T58: =MONTH(S58) -> 1 | W58: =U58*V58 -> 0 | Z58: =IF('Closed Transactions'!A55="", "",'Closed Transactions'!A55) | AA58: =MONTH(Z58) -> #VALUE! | AB58: =IF('Closed Transactions'!F55="","",'Closed Transactions'!F55) | AC58: =IF(AND('Closed Transactions'!B55="",'Closed Transactions'!C55=""),"",IF('Closed Transactions'!B55="","Sell","Buy")) | AD58: ='Closed Transactions'!I55 -> 0 | AE58: =IF('Closed Transactions'!J55="","",'Closed Transactions'!J55) | AF58: =IF('Closed Transactions'!K55="","", 'Closed Transactions'!K55)
G59: =E59*F59 -> 0 | O59: =N59*M59 -> 0 | T59: =MONTH(S59) -> 1 | W59: =U59*V59 -> 0 | Z59: =IF('Closed Transactions'!A56="", "",'Closed Transactions'!A56) | AA59: =MONTH(Z59) -> #VALUE! | AB59: =IF('Closed Transactions'!F56="","",'Closed Transactions'!F56) | AC59: =IF(AND('Closed Transactions'!B56="",'Closed Transactions'!C56=""),"",IF('Closed Transactions'!B56="","Sell","Buy")) | AD59: ='Closed Transactions'!I56 -> 0 | AE59: =IF('Closed Transactions'!J56="","",'Closed Transactions'!J56) | AF59: =IF('Closed Transactions'!K56="","", 'Closed Transactions'!K56)
G60: =E60*F60 -> 0 | O60: =N60*M60 -> 0 | T60: =MONTH(S60) -> 1 | W60: =U60*V60 -> 0 | Z60: =IF('Closed Transactions'!A57="", "",'Closed Transactions'!A57) | AA60: =MONTH(Z60) -> #VALUE! | AB60: =IF('Closed Transactions'!F57="","",'Closed Transactions'!F57) | AC60: =IF(AND('Closed Transactions'!B57="",'Closed Transactions'!C57=""),"",IF('Closed Transactions'!B57="","Sell","Buy")) | AD60: ='Closed Transactions'!I57 -> 0 | AE60: =IF('Closed Transactions'!J57="","",'Closed Transactions'!J57) | AF60: =IF('Closed Transactions'!K57="","", 'Closed Transactions'!K57)
G61: =E61*F61 -> 0 | O61: =N61*M61 -> 0 | T61: =MONTH(S61) -> 1 | W61: =U61*V61 -> 0 | Z61: =IF('Closed Transactions'!A58="", "",'Closed Transactions'!A58) | AA61: =MONTH(Z61) -> #VALUE! | AB61: =IF('Closed Transactions'!F58="","",'Closed Transactions'!F58) | AC61: =IF(AND('Closed Transactions'!B58="",'Closed Transactions'!C58=""),"",IF('Closed Transactions'!B58="","Sell","Buy")) | AD61: ='Closed Transactions'!I58 -> 0 | AE61: =IF('Closed Transactions'!J58="","",'Closed Transactions'!J58) | AF61: =IF('Closed Transactions'!K58="","", 'Closed Transactions'!K58)
G62: =E62*F62 -> 0 | O62: =N62*M62 -> 0 | T62: =MONTH(S62) -> 1 | W62: =U62*V62 -> 0 | Z62: =IF('Closed Transactions'!A59="", "",'Closed Transactions'!A59) | AA62: =MONTH(Z62) -> #VALUE! | AB62: =IF('Closed Transactions'!F59="","",'Closed Transactions'!F59) | AC62: =IF(AND('Closed Transactions'!B59="",'Closed Transactions'!C59=""),"",IF('Closed Transactions'!B59="","Sell","Buy")) | AD62: ='Closed Transactions'!I59 -> 0 | AE62: =IF('Closed Transactions'!J59="","",'Closed Transactions'!J59) | AF62: =IF('Closed Transactions'!K59="","", 'Closed Transactions'!K59)
G63: =E63*F63 -> 0 | O63: =N63*M63 -> 0 | T63: =MONTH(S63) -> 1 | W63: =U63*V63 -> 0 | Z63: =IF('Closed Transactions'!A60="", "",'Closed Transactions'!A60) | AA63: =MONTH(Z63) -> #VALUE! | AB63: =IF('Closed Transactions'!F60="","",'Closed Transactions'!F60) | AC63: =IF(AND('Closed Transactions'!B60="",'Closed Transactions'!C60=""),"",IF('Closed Transactions'!B60="","Sell","Buy")) | AD63: ='Closed Transactions'!I60 -> 0 | AE63: =IF('Closed Transactions'!J60="","",'Closed Transactions'!J60) | AF63: =IF('Closed Transactions'!K60="","", 'Closed Transactions'!K60)
G64: =E64*F64 -> 0 | O64: =N64*M64 -> 0 | T64: =MONTH(S64) -> 1 | W64: =U64*V64 -> 0 | Z64: =IF('Closed Transactions'!A61="", "",'Closed Transactions'!A61) | AA64: =MONTH(Z64) -> #VALUE! | AB64: =IF('Closed Transactions'!F61="","",'Closed Transactions'!F61) | AC64: =IF(AND('Closed Transactions'!B61="",'Closed Transactions'!C61=""),"",IF('Closed Transactions'!B61="","Sell","Buy")) | AD64: ='Closed Transactions'!I61 -> 0 | AE64: =IF('Closed Transactions'!J61="","",'Closed Transactions'!J61) | AF64: =IF('Closed Transactions'!K61="","", 'Closed Transactions'!K61)
G65: =E65*F65 -> 0 | O65: =N65*M65 -> 0 | T65: =MONTH(S65) -> 1 | W65: =U65*V65 -> 0 | Z65: =IF('Closed Transactions'!A62="", "",'Closed Transactions'!A62) | AA65: =MONTH(Z65) -> #VALUE! | AB65: =IF('Closed Transactions'!F62="","",'Closed Transactions'!F62) | AC65: =IF(AND('Closed Transactions'!B62="",'Closed Transactions'!C62=""),"",IF('Closed Transactions'!B62="","Sell","Buy")) | AD65: ='Closed Transactions'!I62 -> 0 | AE65: =IF('Closed Transactions'!J62="","",'Closed Transactions'!J62) | AF65: =IF('Closed Transactions'!K62="","", 'Closed Transactions'!K62)
G66: =E66*F66 -> 0 | O66: =N66*M66 -> 0 | T66: =MONTH(S66) -> 1 | W66: =U66*V66 -> 0 | Z66: =IF('Closed Transactions'!A63="", "",'Closed Transactions'!A63) | AA66: =MONTH(Z66) -> #VALUE! | AB66: =IF('Closed Transactions'!F63="","",'Closed Transactions'!F63) | AC66: =IF(AND('Closed Transactions'!B63="",'Closed Transactions'!C63=""),"",IF('Closed Transactions'!B63="","Sell","Buy")) | AD66: ='Closed Transactions'!I63 -> 0 | AE66: =IF('Closed Transactions'!J63="","",'Closed Transactions'!J63) | AF66: =IF('Closed Transactions'!K63="","", 'Closed Transactions'!K63)
G67: =E67*F67 -> 0 | O67: =N67*M67 -> 0 | Q67: Total Signed Listing Agreements | W67: =SUM(W39:W66) -> 0 | Z67: =IF('Closed Transactions'!A64="", "",'Closed Transactions'!A64) | AA67: =MONTH(Z67) -> #VALUE! | AB67: =IF('Closed Transactions'!F64="","",'Closed Transactions'!F64) | AC67: =IF(AND('Closed Transactions'!B64="",'Closed Transactions'!C64=""),"",IF('Closed Transactions'!B64="","Sell","Buy")) | AD67: ='Closed Transactions'!I64 -> 0 | AE67: =IF('Closed Transactions'!J64="","",'Closed Transactions'!J64) | AF67: =IF('Closed Transactions'!K64="","", 'Closed Transactions'!K64)
A68: Total Potential Sides in Warm List | D68: =COUNTIF(C6:C67,"*") -> 50 | E68: =SUM(E6:E67) -> 35500000 | F68: =SUM(G6:G67) -> 1015500 | L68: =COUNTIF(K6:K35,"*") +COUNTIF(K39:K67,"*") -> 15 | M68: =SUM(M6:M67) -> 8950000 | O68: =SUM(O6:O67) -> 254250 | S68: =COUNTIF(R6:R34,"*") +COUNTIF(R39:R66,"*") -> 1 | U68: =SUM(U6:U67) -> 2350 | W68: =W67+W35 -> 0 | AA68: =MONTH(Z68) -> 1 | AB68: Total Sides Closed | AC68: ='Closed Transactions'!A65 -> 17 | AD68: =SUM(AD6:AD67) -> 5901765 | AE68: =SUM(AF6:AF67) -> 119176.25
E69: POTENTIAL VOLUME in Warm List | G69: Total Potential GCI in Warm List | M69: POTENTIAL VOLUME in Hot List | O69: Total Potential GCI in Hot List | U69: VOLUME Under Contract | W69: Total GCI Under Contract | AA69: =MONTH(Z69) -> 1 | AD69: VOLUME | AF69: Total GCI To Date

Sheet Closed Transactions
A1: A transaction has closed! Enter closing details in tan cells.
A2: COE | B2: Buy | C2: Sell | D2: Source | E2: Referral Past Client | F2: Client Name | G2: Prop Address | H2: LP | I2: SP | J2: Comm % | K2: Gross Commission | L2: Enter Referral Fee in $ | M2: Agent Net Income (Minus Franchise, Marketing, Office, Referral) | N2: Brokerage Income (Franchise, Marketing, Office) | P2: SP | Q2: Jan | S2: Feb | U2: Mar | W2: Apr | Y2: May | AA2: Jun | AC2: Jul | AE2: Aug | AG2: Sep | AI2: Oct | AK2: Nov | AM2: Dec
A3: 45667 | B3: 1 | D3: BNI | F3: Kevin Zhao | G3: 6516 Medinah Ln, Alexandrria, 33132 | H3: 590000 | I3: 610000 | J3: 0.025 | K3: =IF(ISBLANK(A3),"",(I3*J3)) -> 15250 | L3: 0 | M3: =IF((ISBLANK(A3)),"",'Fee calc_closed Transactions'!F3) -> 10370 | N3: =IF(K3="","",'Fee calc_closed Transactions'!G3) -> 4880 | P3: =IF(ISBLANK(A3),"0",I3) -> 610000 | Q3: =IF(MONTH(A3)=1,IF((ISBLANK(B3)),0,(M3)),"0") -> 10370 | R3: =IF(MONTH(A3)=1,IF((ISBLANK(C3)),0,(M3)),"0") -> 0 | S3: =IF(MONTH(A3)=2,IF((ISBLANK(B3)),0,(M3)),"0") -> 0 | T3: =IF(MONTH(A3)=2,IF((ISBLANK(C3)),0,(M3)),"0") -> 0 | U3: =IF(MONTH(A3)=3,IF((ISBLANK(B3)),0,(M3)),"0") -> 0 | V3: =IF(MONTH(A3)=3,IF((ISBLANK(C3)),0,(M3)),"0") -> 0 | W3: =IF(MONTH(A3)=4,IF((ISBLANK(B3)),0,(M3)),"0") -> 0 | X3: =IF(MONTH(A3)=4,IF((ISBLANK(C3)),0,(M3)),"0") -> 0 | Y3: =IF(MONTH(A3)=5,IF((ISBLANK(B3)),0,(M3)),"0") -> 0 | Z3: =IF(MONTH(A3)=5,IF((ISBLANK(C3)),0,(M3)),"0") -> 0 | AA3: =IF(MONTH(A3)=6,IF((ISBLANK(B3)),0,(M3)),"0") -> 0 | AB3: =IF(MONTH(A3)=6,IF((ISBLANK(C3)),0,(M3)),"0") -> 0 | AC3: =IF(MONTH(A3)=7,IF((ISBLANK(B3)),0,(M3)),"0") -> 0 | AD3: =IF(MONTH(A3)=7,IF((ISBLANK(C3)),0,(M3)),"0") -> 0 | AE3: =IF(MONTH(A3)=8,IF((ISBLANK(B3)),0,(M3)),"0") -> 0 | AF3: =IF(MONTH(A3)=8,IF((ISBLANK(C3)),0,(M3)),"0") -> 0 | AG3: =IF(MONTH(A3)=9,IF((ISBLANK(B3)),0,(M3)),"0") -> 0 | AH3: =IF(MONTH(A3)=9,IF((ISBLANK(C3)),0,(M3)),"0") -> 0 | AI3: =IF(MONTH(A3)=10,IF((ISBLANK(B3)),0,(M3)),"0") -> 0 | AJ3: =IF(MONTH(A3)=10,IF((ISBLANK(C3)),0,(M3)),"0") -> 0 | AK3: =IF(MONTH(A3)=11,IF((ISBLANK(B3)),0,(M3)),"0") -> 0 | AL3: =IF(MONTH(A3)=11,IF((ISBLANK(C3)),0,(M3)),"0") -> 0 | AM3: =IF(MONTH(A3)=12,IF((ISBLANK(B3)),0,(M3)),"0") -> 0 | AN3: =IF(MONTH(A3)=12,IF((ISBLANK(C3)),0,(M3)),"0") -> 0
A4: 45706 | B4: 1 | D4: SOI | F4: Cristina Samaha | G4: 3452 Belleplain Ct, Dumfries | H4: 415900 | I4: 415900 | J4: 0.024044241 | K4: =IF(ISBLANK(A4),"",(I4*J4)) -> 10000 | L4: 0 | M4: =IF((ISBLANK(A4)),"",'Fee calc_closed Transactions'!F4) -> 6880 | N4: =IF(K4="","",'Fee calc_closed Transactions'!G4) -> 3120 | P4: =IF(ISBLANK(A4),"0",I4) -> 415900 | Q4: =IF(MONTH(A4)=1,IF((ISBLANK(B4)),0,(M4)),"0") -> 0 | R4: =IF(MONTH(A4)=1,IF((ISBLANK(C4)),0,(M4)),"0") -> 0 | S4: =IF(MONTH(A4)=2,IF((ISBLANK(B4)),0,(M4)),"0") -> 6880 | T4: =IF(MONTH(A4)=2,IF((ISBLANK(C4)),0,(M4)),"0") -> 0 | U4: =IF(MONTH(A4)=3,IF((ISBLANK(B4)),0,(M4)),"0") -> 0 | V4: =IF(MONTH(A4)=3,IF((ISBLANK(C4)),0,(M4)),"0") -> 0 | W4: =IF(MONTH(A4)=4,IF((ISBLANK(B4)),0,(M4)),"0") -> 0 | X4: =IF(MONTH(A4)=4,IF((ISBLANK(C4)),0,(M4)),"0") -> 0 | Y4: =IF(MONTH(A4)=5,IF((ISBLANK(B4)),0,(M4)),"0") -> 0 | Z4: =IF(MONTH(A4)=5,IF((ISBLANK(C4)),0,(M4)),"0") -> 0 | AA4: =IF(MONTH(A4)=6,IF((ISBLANK(B4)),0,(M4)),"0") -> 0 | AB4: =IF(MONTH(A4)=6,IF((ISBLANK(C4)),0,(M4)),"0") -> 0 | AC4: =IF(MONTH(A4)=7,IF((ISBLANK(B4)),0,(M4)),"0") -> 0 | AD4: =IF(MONTH(A4)=7,IF((ISBLANK(C4)),0,(M4)),"0") -> 0 | AE4: =IF(MONTH(A4)=8,IF((ISBLANK(B4)),0,(M4)),"0") -> 0 | AF4: =IF(MONTH(A4)=8,IF((ISBLANK(C4)),0,(M4)),"0") -> 0 | AG4: =IF(MONTH(A4)=9,IF((ISBLANK(B4)),0,(M4)),"0") -> 0 | AH4: =IF(MONTH(A4)=9,IF((ISBLANK(C4)),0,(M4)),"0") -> 0 | AI4: =IF(MONTH(A4)=10,IF((ISBLANK(B4)),0,(M4)),"0") -> 0 | AJ4: =IF(MONTH(A4)=10,IF((ISBLANK(C4)),0,(M4)),"0") -> 0 | AK4: =IF(MONTH(A4)=11,IF((ISBLANK(B4)),0,(M4)),"0") -> 0 | AL4: =IF(MONTH(A4)=11,IF((ISBLANK(C4)),0,(M4)),"0") -> 0 | AM4: =IF(MONTH(A4)=12,IF((ISBLANK(B4)),0,(M4)),"0") -> 0 | AN4: =IF(MONTH(A4)=12,IF((ISBLANK(C4)),0,(M4)),"0") -> 0
A5: 45717 | B5: 1 | D5: Sign Call | F5: Kim & Damon Sidur | G5: 3382 Gunston Rd, Alexandria | H5: 2600 | I5: 2650 | J5: 0.25 | K5: =IF(ISBLANK(A5),"",(I5*J5)) -> 662.5 | L5: 0 | M5: =IF((ISBLANK(A5)),"",'Fee calc_closed Transactions'!F5) -> 563.125 | N5: =IF(K5="","",'Fee calc_closed Transactions'!G5) -> 99.375 | P5: =IF(ISBLANK(A5),"0",I5) -> 2650 | Q5: =IF(MONTH(A5)=1,IF((ISBLANK(B5)),0,(M5)),"0") -> 0 | R5: =IF(MONTH(A5)=1,IF((ISBLANK(C5)),0,(M5)),"0") -> 0 | S5: =IF(MONTH(A5)=2,IF((ISBLANK(B5)),0,(M5)),"0") -> 0 | T5: =IF(MONTH(A5)=2,IF((ISBLANK(C5)),0,(M5)),"0") -> 0 | U5: =IF(MONTH(A5)=3,IF((ISBLANK(B5)),0,(M5)),"0") -> 563.125 | V5: =IF(MONTH(A5)=3,IF((ISBLANK(C5)),0,(M5)),"0") -> 0 | W5: =IF(MONTH(A5)=4,IF((ISBLANK(B5)),0,(M5)),"0") -> 0 | X5: =IF(MONTH(A5)=4,IF((ISBLANK(C5)),0,(M5)),"0") -> 0 | Y5: =IF(MONTH(A5)=5,IF((ISBLANK(B5)),0,(M5)),"0") -> 0 | Z5: =IF(MONTH(A5)=5,IF((ISBLANK(C5)),0,(M5)),"0") -> 0 | AA5: =IF(MONTH(A5)=6,IF((ISBLANK(B5)),0,(M5)),"0") -> 0 | AB5: =IF(MONTH(A5)=6,IF((ISBLANK(C5)),0,(M5)),"0") -> 0 | AC5: =IF(MONTH(A5)=7,IF((ISBLANK(B5)),0,(M5)),"0") -> 0 | AD5: =IF(MONTH(A5)=7,IF((ISBLANK(C5)),0,(M5)),"0") -> 0 | AE5: =IF(MONTH(A5)=8,IF((ISBLANK(B5)),0,(M5)),"0") -> 0 | AF5: =IF(MONTH(A5)=8,IF((ISBLANK(C5)),0,(M5)),"0") -> 0 | AG5: =IF(MONTH(A5)=9,IF((ISBLANK(B5)),0,(M5)),"0") -> 0 | AH5: =IF(MONTH(A5)=9,IF((ISBLANK(C5)),0,(M5)),"0") -> 0 | AI5: =IF(MONTH(A5)=10,IF((ISBLANK(B5)),0,(M5)),"0") -> 0 | AJ5: =IF(MONTH(A5)=10,IF((ISBLANK(C5)),0,(M5)),"0") -> 0 | AK5: =IF(MONTH(A5)=11,IF((ISBLANK(B5)),0,(M5)),"0") -> 0 | AL5: =IF(MONTH(A5)=11,IF((ISBLANK(C5)),0,(M5)),"0") -> 0 | AM5: =IF(MONTH(A5)=12,IF((ISBLANK(B5)),0,(M5)),"0") -> 0 | AN5: =IF(MONTH(A5)=12,IF((ISBLANK(C5)),0,(M5)),"0") -> 0
A6: 45724 | B6: 1 | C6: 1 | D6: realtor referral | F6: Anne Duffy, Elizabeth & Ariel | G6: 926 N Edgewood St #1, Arlington | H6: 2995 | I6: 2995 | J6: 1 | K6: =IF(ISBLANK(A6),"",(I6*J6)) -> 2995 | L6: 749 | M6: =IF((ISBLANK(A6)),"",'Fee calc_closed Transactions'!F6) -> 1909.1 | N6: =IF(K6="","",'Fee calc_closed Transactions'!G6) -> 336.9 | P6: =IF(ISBLANK(A6),"0",I6) -> 2995 | Q6: =IF(MONTH(A6)=1,IF((ISBLANK(B6)),0,(M6)),"0") -> 0 | R6: =IF(MONTH(A6)=1,IF((ISBLANK(C6)),0,(M6)),"0") -> 0 | S6: =IF(MONTH(A6)=2,IF((ISBLANK(B6)),0,(M6)),"0") -> 0 | T6: =IF(MONTH(A6)=2,IF((ISBLANK(C6)),0,(M6)),"0") -> 0 | U6: =IF(MONTH(A6)=3,IF((ISBLANK(B6)),0,(M6)),"0") -> 1909.1 | V6: =IF(MONTH(A6)=3,IF((ISBLANK(C6)),0,(M6)),"0") -> 1909.1 | W6: =IF(MONTH(A6)=4,IF((ISBLANK(B6)),0,(M6)),"0") -> 0 | X6: =IF(MONTH(A6)=4,IF((ISBLANK(C6)),0,(M6)),"0") -> 0 | Y6: =IF(MONTH(A6)=5,IF((ISBLANK(B6)),0,(M6)),"0") -> 0 | Z6: =IF(MONTH(A6)=5,IF((ISBLANK(C6)),0,(M6)),"0") -> 0 | AA6: =IF(MONTH(A6)=6,IF((ISBLANK(B6)),0,(M6)),"0") -> 0 | AB6: =IF(MONTH(A6)=6,IF((ISBLANK(C6)),0,(M6)),"0") -> 0 | AC6: =IF(MONTH(A6)=7,IF((ISBLANK(B6)),0,(M6)),"0") -> 0 | AD6: =IF(MONTH(A6)=7,IF((ISBLANK(C6)),0,(M6)),"0") -> 0 | AE6: =IF(MONTH(A6)=8,IF((ISBLANK(B6)),0,(M6)),"0") -> 0 | AF6: =IF(MONTH(A6)=8,IF((ISBLANK(C6)),0,(M6)),"0") -> 0 | AG6: =IF(MONTH(A6)=9,IF((ISBLANK(B6)),0,(M6)),"0") -> 0 | AH6: =IF(MONTH(A6)=9,IF((ISBLANK(C6)),0,(M6)),"0") -> 0 | AI6: =IF(MONTH(A6)=10,IF((ISBLANK(B6)),0,(M6)),"0") -> 0 | AJ6: =IF(MONTH(A6)=10,IF((ISBLANK(C6)),0,(M6)),"0") -> 0 | AK6: =IF(MONTH(A6)=11,IF((ISBLANK(B6)),0,(M6)),"0") -> 0 | AL6: =IF(MONTH(A6)=11,IF((ISBLANK(C6)),0,(M6)),"0") -> 0 | AM6: =IF(MONTH(A6)=12,IF((ISBLANK(B6)),0,(M6)),"0") -> 0 | AN6: =IF(MONTH(A6)=12,IF((ISBLANK(C6)),0,(M6)),"0") -> 0
A7: 45757 | B7: 1 | D7: referral | E7: Audra & Alex Macie | F7: Lindsey Jasper & Ben Fielder | G7: 1103 Criton St, Herndon, VA 20170 | H7: 750000 | I7: 750000 | J7: 0.03 | K7: =IF(ISBLANK(A7),"",(I7*J7)) -> 22500 | M7: =IF((ISBLANK(A7)),"",'Fee calc_closed Transactions'!F7) -> 19125 | N7: =IF(K7="","",'Fee calc_closed Transactions'!G7) -> 3375 | P7: =IF(ISBLANK(A7),"0",I7) -> 750000 | Q7: =IF(MONTH(A7)=1,IF((ISBLANK(B7)),0,(M7)),"0") -> 0 | R7: =IF(MONTH(A7)=1,IF((ISBLANK(C7)),0,(M7)),"0") -> 0 | S7: =IF(MONTH(A7)=2,IF((ISBLANK(B7)),0,(M7)),"0") -> 0 | T7: =IF(MONTH(A7)=2,IF((ISBLANK(C7)),0,(M7)),"0") -> 0 | U7: =IF(MONTH(A7)=3,IF((ISBLANK(B7)),0,(M7)),"0") -> 0 | V7: =IF(MONTH(A7)=3,IF((ISBLANK(C7)),0,(M7)),"0") -> 0 | W7: =IF(MONTH(A7)=4,IF((ISBLANK(B7)),0,(M7)),"0") -> 19125 | X7: =IF(MONTH(A7)=4,IF((ISBLANK(C7)),0,(M7)),"0") -> 0 | Y7: =IF(MONTH(A7)=5,IF((ISBLANK(B7)),0,(M7)),"0") -> 0 | Z7: =IF(MONTH(A7)=5,IF((ISBLANK(C7)),0,(M7)),"0") -> 0 | AA7: =IF(MONTH(A7)=6,IF((ISBLANK(B7)),0,(M7)),"0") -> 0 | AB7: =IF(MONTH(A7)=6,IF((ISBLANK(C7)),0,(M7)),"0") -> 0 | AC7: =IF(MONTH(A7)=7,IF((ISBLANK(B7)),0,(M7)),"0") -> 0 | AD7: =IF(MONTH(A7)=7,IF((ISBLANK(C7)),0,(M7)),"0") -> 0 | AE7: =IF(MONTH(A7)=8,IF((ISBLANK(B7)),0,(M7)),"0") -> 0 | AF7: =IF(MONTH(A7)=8,IF((ISBLANK(C7)),0,(M7)),"0") -> 0 | AG7: =IF(MONTH(A7)=9,IF((ISBLANK(B7)),0,(M7)),"0") -> 0 | AH7: =IF(MONTH(A7)=9,IF((ISBLANK(C7)),0,(M7)),"0") -> 0 | AI7: =IF(MONTH(A7)=10,IF((ISBLANK(B7)),0,(M7)),"0") -> 0 | AJ7: =IF(MONTH(A7)=10,IF((ISBLANK(C7)),0,(M7)),"0") -> 0 | AK7: =IF(MONTH(A7)=11,IF((ISBLANK(B7)),0,(M7)),"0") -> 0 | AL7: =IF(MONTH(A7)=11,IF((ISBLANK(C7)),0,(M7)),"0") -> 0 | AM7: =IF(MONTH(A7)=12,IF((ISBLANK(B7)),0,(M7)),"0") -> 0 | AN7: =IF(MONTH(A7)=12,IF((ISBLANK(C7)),0,(M7)),"0") -> 0
A8: 45758 | C8: 1 | D8: Rotary | F8: Doug Church | G8: 5713 15th Rd N, Arlington, VA 22205 | H8: 1350000 | I8: 1300000 | J8: 0.03 | K8: =IF(ISBLANK(A8),"",(I8*J8)) -> 39000 | M8: =IF((ISBLANK(A8)),"",'Fee calc_closed Transactions'!F8) -> 33150 | N8: =IF(K8="","",'Fee calc_closed Transactions'!G8) -> 5850 | P8: =IF(ISBLANK(A8),"0",I8) -> 1300000 | Q8: =IF(MONTH(A8)=1,IF((ISBLANK(B8)),0,(M8)),"0") -> 0 | R8: =IF(MONTH(A8)=1,IF((ISBLANK(C8)),0,(M8)),"0") -> 0 | S8: =IF(MONTH(A8)=2,IF((ISBLANK(B8)),0,(M8)),"0") -> 0 | T8: =IF(MONTH(A8)=2,IF((ISBLANK(C8)),0,(M8)),"0") -> 0 | U8: =IF(MONTH(A8)=3,IF((ISBLANK(B8)),0,(M8)),"0") -> 0 | V8: =IF(MONTH(A8)=3,IF((ISBLANK(C8)),0,(M8)),"0") -> 0 | W8: =IF(MONTH(A8)=4,IF((ISBLANK(B8)),0,(M8)),"0") -> 0 | X8: =IF(MONTH(A8)=4,IF((ISBLANK(C8)),0,(M8)),"0") -> 33150 | Y8: =IF(MONTH(A8)=5,IF((ISBLANK(B8)),0,(M8)),"0") -> 0 | Z8: =IF(MONTH(A8)=5,IF((ISBLANK(C8)),0,(M8)),"0") -> 0 | AA8: =IF(MONTH(A8)=6,IF((ISBLANK(B8)),0,(M8)),"0") -> 0 | AB8: =IF(MONTH(A8)=6,IF((ISBLANK(C8)),0,(M8)),"0") -> 0 | AC8: =IF(MONTH(A8)=7,IF((ISBLANK(B8)),0,(M8)),"0") -> 0 | AD8: =IF(MONTH(A8)=7,IF((ISBLANK(C8)),0,(M8)),"0") -> 0 | AE8: =IF(MONTH(A8)=8,IF((ISBLANK(B8)),0,(M8)),"0") -> 0 | AF8: =IF(MONTH(A8)=8,IF((ISBLANK(C8)),0,(M8)),"0") -> 0 | AG8: =IF(MONTH(A8)=9,IF((ISBLANK(B8)),0,(M8)),"0") -> 0 | AH8: =IF(MONTH(A8)=9,IF((ISBLANK(C8)),0,(M8)),"0") -> 0 | AI8: =IF(MONTH(A8)=10,IF((ISBLANK(B8)),0,(M8)),"0") -> 0 | AJ8: =IF(MONTH(A8)=10,IF((ISBLANK(C8)),0,(M8)),"0") -> 0 | AK8: =IF(MONTH(A8)=11,IF((ISBLANK(B8)),0,(M8)),"0") -> 0 | AL8: =IF(MONTH(A8)=11,IF((ISBLANK(C8)),0,(M8)),"0") -> 0 | AM8: =IF(MONTH(A8)=12,IF((ISBLANK(B8)),0,(M8)),"0") -> 0 | AN8: =IF(MONTH(A8)=12,IF((ISBLANK(C8)),0,(M8)),"0") -> 0
A9: 45828 | B9: 1 | C9: 1 | D9: CFCC | F9: Ashraf Kadri | G9: 901 Vista Terrace, Blacksburg, VA 24060 | I9: 390000 | J9: 0.0075 | K9: =IF(ISBLANK(A9),"",(I9*J9)) -> 2925 | M9: =IF((ISBLANK(A9)),"",'Fee calc_closed Transactions'!F9) -> 2486.25 | N9: =IF(K9="","",'Fee calc_closed Transactions'!G9) -> 438.75 | P9: =IF(ISBLANK(A9),"0",I9) -> 390000 | Q9: =IF(MONTH(A9)=1,IF((ISBLANK(B9)),0,(M9)),"0") -> 0 | R9: =IF(MONTH(A9)=1,IF((ISBLANK(C9)),0,(M9)),"0") -> 0 | S9: =IF(MONTH(A9)=2,IF((ISBLANK(B9)),0,(M9)),"0") -> 0 | T9: =IF(MONTH(A9)=2,IF((ISBLANK(C9)),0,(M9)),"0") -> 0 | U9: =IF(MONTH(A9)=3,IF((ISBLANK(B9)),0,(M9)),"0") -> 0 | V9: =IF(MONTH(A9)=3,IF((ISBLANK(C9)),0,(M9)),"0") -> 0 | W9: =IF(MONTH(A9)=4,IF((ISBLANK(B9)),0,(M9)),"0") -> 0 | X9: =IF(MONTH(A9)=4,IF((ISBLANK(C9)),0,(M9)),"0") -> 0 | Y9: =IF(MONTH(A9)=5,IF((ISBLANK(B9)),0,(M9)),"0") -> 0 | Z9: =IF(MONTH(A9)=5,IF((ISBLANK(C9)),0,(M9)),"0") -> 0 | AA9: =IF(MONTH(A9)=6,IF((ISBLANK(B9)),0,(M9)),"0") -> 2486.25 | AB9: =IF(MONTH(A9)=6,IF((ISBLANK(C9)),0,(M9)),"0") -> 2486.25 | AC9: =IF(MONTH(A9)=7,IF((ISBLANK(B9)),0,(M9)),"0") -> 0 | AD9: =IF(MONTH(A9)=7,IF((ISBLANK(C9)),0,(M9)),"0") -> 0 | AE9: =IF(MONTH(A9)=8,IF((ISBLANK(B9)),0,(M9)),"0") -> 0 | AF9: =IF(MONTH(A9)=8,IF((ISBLANK(C9)),0,(M9)),"0") -> 0 | AG9: =IF(MONTH(A9)=9,IF((ISBLANK(B9)),0,(M9)),"0") -> 0 | AH9: =IF(MONTH(A9)=9,IF((ISBLANK(C9)),0,(M9)),"0") -> 0 | AI9: =IF(MONTH(A9)=10,IF((ISBLANK(B9)),0,(M9)),"0") -> 0 | AJ9: =IF(MONTH(A9)=10,IF((ISBLANK(C9)),0,(M9)),"0") -> 0 | AK9: =IF(MONTH(A9)=11,IF((ISBLANK(B9)),0,(M9)),"0") -> 0 | AL9: =IF(MONTH(A9)=11,IF((ISBLANK(C9)),0,(M9)),"0") -> 0 | AM9: =IF(MONTH(A9)=12,IF((ISBLANK(B9)),0,(M9)),"0") -> 0 | AN9: =IF(MONTH(A9)=12,IF((ISBLANK(C9)),0,(M9)),"0") -> 0
A10: 45838 | C10: 1 | D10: my property | F10: Nathan Desnoyers | G10: 14451 Saguaro Pl, Centreville, VA 20121 | H10: 345000 | I10: 365000 | J10: 0 | K10: =IF(ISBLANK(A10),"",(I10*J10)) -> 0 | M10: =IF((ISBLANK(A10)),"",'Fee calc_closed Transactions'!F10) -> 0 | N10: =IF(K10="","",'Fee calc_closed Transactions'!G10) -> 0 | P10: =IF(ISBLANK(A10),"0",I10) -> 365000 | Q10: =IF(MONTH(A10)=1,IF((ISBLANK(B10)),0,(M10)),"0") -> 0 | R10: =IF(MONTH(A10)=1,IF((ISBLANK(C10)),0,(M10)),"0") -> 0 | S10: =IF(MONTH(A10)=2,IF((ISBLANK(B10)),0,(M10)),"0") -> 0 | T10: =IF(MONTH(A10)=2,IF((ISBLANK(C10)),0,(M10)),"0") -> 0 | U10: =IF(MONTH(A10)=3,IF((ISBLANK(B10)),0,(M10)),"0") -> 0 | V10: =IF(MONTH(A10)=3,IF((ISBLANK(C10)),0,(M10)),"0") -> 0 | W10: =IF(MONTH(A10)=4,IF((ISBLANK(B10)),0,(M10)),"0") -> 0 | X10: =IF(MONTH(A10)=4,IF((ISBLANK(C10)),0,(M10)),"0") -> 0 | Y10: =IF(MONTH(A10)=5,IF((ISBLANK(B10)),0,(M10)),"0") -> 0 | Z10: =IF(MONTH(A10)=5,IF((ISBLANK(C10)),0,(M10)),"0") -> 0 | AA10: =IF(MONTH(A10)=6,IF((ISBLANK(B10)),0,(M10)),"0") -> 0 | AB10: =IF(MONTH(A10)=6,IF((ISBLANK(C10)),0,(M10)),"0") -> 0 | AC10: =IF(MONTH(A10)=7,IF((ISBLANK(B10)),0,(M10)),"0") -> 0 | AD10: =IF(MONTH(A10)=7,IF((ISBLANK(C10)),0,(M10)),"0") -> 0 | AE10: =IF(MONTH(A10)=8,IF((ISBLANK(B10)),0,(M10)),"0") -> 0 | AF10: =IF(MONTH(A10)=8,IF((ISBLANK(C10)),0,(M10)),"0") -> 0 | AG10: =IF(MONTH(A10)=9,IF((ISBLANK(B10)),0,(M10)),"0") -> 0 | AH10: =IF(MONTH(A10)=9,IF((ISBLANK(C10)),0,(M10)),"0") -> 0 | AI10: =IF(MONTH(A10)=10,IF((ISBLANK(B10)),0,(M10)),"0") -> 0 | AJ10: =IF(MONTH(A10)=10,IF((ISBLANK(C10)),0,(M10)),"0") -> 0 | AK10: =IF(MONTH(A10)=11,IF((ISBLANK(B10)),0,(M10)),"0") -> 0 | AL10: =IF(MONTH(A10)=11,IF((ISBLANK(C10)),0,(M10)),"0") -> 0 | AM10: =IF(MONTH(A10)=12,IF((ISBLANK(B10)),0,(M10)),"0") -> 0 | AN10: =IF(MONTH(A10)=12,IF((ISBLANK(C10)),0,(M10)),"0") -> 0
A11: 45839 | B11: 1 | D11: BNI | F11: Saria Alshaikhalia | G11: 2833 Kalmi Lee Ct,#302 Falls Church, VA 22042 | H11: 2195 | I11: 2195 | J11: 0.25 | K11: =IF(ISBLANK(A11),"",(I11*J11)) -> 548.75 | M11: =IF((ISBLANK(A11)),"",'Fee calc_closed Transactions'!F11) -> 466.4375 | N11: =IF(K11="","",'Fee calc_closed Transactions'!G11) -> 82.3125 | P11: =IF(ISBLANK(A11),"0",I11) -> 2195 | Q11: =IF(MONTH(A11)=1,IF((ISBLANK(B11)),0,(M11)),"0") -> 0 | R11: =IF(MONTH(A11)=1,IF((ISBLANK(C11)),0,(M11)),"0") -> 0 | S11: =IF(MONTH(A11)=2,IF((ISBLANK(B11)),0,(M11)),"0") -> 0 | T11: =IF(MONTH(A11)=2,IF((ISBLANK(C11)),0,(M11)),"0") -> 0 | U11: =IF(MONTH(A11)=3,IF((ISBLANK(B11)),0,(M11)),"0") -> 0 | V11: =IF(MONTH(A11)=3,IF((ISBLANK(C11)),0,(M11)),"0") -> 0 | W11: =IF(MONTH(A11)=4,IF((ISBLANK(B11)),0,(M11)),"0") -> 0 | X11: =IF(MONTH(A11)=4,IF((ISBLANK(C11)),0,(M11)),"0") -> 0 | Y11: =IF(MONTH(A11)=5,IF((ISBLANK(B11)),0,(M11)),"0") -> 0 | Z11: =IF(MONTH(A11)=5,IF((ISBLANK(C11)),0,(M11)),"0") -> 0 | AA11: =IF(MONTH(A11)=6,IF((ISBLANK(B11)),0,(M11)),"0") -> 0 | AB11: =IF(MONTH(A11)=6,IF((ISBLANK(C11)),0,(M11)),"0") -> 0 | AC11: =IF(MONTH(A11)=7,IF((ISBLANK(B11)),0,(M11)),"0") -> 466.4375 | AD11: =IF(MONTH(A11)=7,IF((ISBLANK(C11)),0,(M11)),"0") -> 0 | AE11: =IF(MONTH(A11)=8,IF((ISBLANK(B11)),0,(M11)),"0") -> 0 | AF11: =IF(MONTH(A11)=8,IF((ISBLANK(C11)),0,(M11)),"0") -> 0 | AG11: =IF(MONTH(A11)=9,IF((ISBLANK(B11)),0,(M11)),"0") -> 0 | AH11: =IF(MONTH(A11)=9,IF((ISBLANK(C11)),0,(M11)),"0") -> 0 | AI11: =IF(MONTH(A11)=10,IF((ISBLANK(B11)),0,(M11)),"0") -> 0 | AJ11: =IF(MONTH(A11)=10,IF((ISBLANK(C11)),0,(M11)),"0") -> 0 | AK11: =IF(MONTH(A11)=11,IF((ISBLANK(B11)),0,(M11)),"0") -> 0 | AL11: =IF(MONTH(A11)=11,IF((ISBLANK(C11)),0,(M11)),"0") -> 0 | AM11: =IF(MONTH(A11)=12,IF((ISBLANK(B11)),0,(M11)),"0") -> 0 | AN11: =IF(MONTH(A11)=12,IF((ISBLANK(C11)),0,(M11)),"0") -> 0
A12: 45839 | B12: 1 | D12: sign call | F12: Sneha Durgapal & Alex Hennessy | G12: 820 N Pollard #316, Arlington VA | H12: 3150 | I12: 3150 | J12: 0 | K12: =IF(ISBLANK(A12),"",(I12*J12)) -> 0 | M12: =IF((ISBLANK(A12)),"",'Fee calc_closed Transactions'!F12) -> 0 | N12: =IF(K12="","",'Fee calc_closed Transactions'!G12) -> 0 | P12: =IF(ISBLANK(A12),"0",I12) -> 3150 | Q12: =IF(MONTH(A12)=1,IF((ISBLANK(B12)),0,(M12)),"0") -> 0 | R12: =IF(MONTH(A12)=1,IF((ISBLANK(C12)),0,(M12)),"0") -> 0 | S12: =IF(MONTH(A12)=2,IF((ISBLANK(B12)),0,(M12)),"0") -> 0 | T12: =IF(MONTH(A12)=2,IF((ISBLANK(C12)),0,(M12)),"0") -> 0 | U12: =IF(MONTH(A12)=3,IF((ISBLANK(B12)),0,(M12)),"0") -> 0 | V12: =IF(MONTH(A12)=3,IF((ISBLANK(C12)),0,(M12)),"0") -> 0 | W12: =IF(MONTH(A12)=4,IF((ISBLANK(B12)),0,(M12)),"0") -> 0 | X12: =IF(MONTH(A12)=4,IF((ISBLANK(C12)),0,(M12)),"0") -> 0 | Y12: =IF(MONTH(A12)=5,IF((ISBLANK(B12)),0,(M12)),"0") -> 0 | Z12: =IF(MONTH(A12)=5,IF((ISBLANK(C12)),0,(M12)),"0") -> 0 | AA12: =IF(MONTH(A12)=6,IF((ISBLANK(B12)),0,(M12)),"0") -> 0 | AB12: =IF(MONTH(A12)=6,IF((ISBLANK(C12)),0,(M12)),"0") -> 0 | AC12: =IF(MONTH(A12)=7,IF((ISBLANK(B12)),0,(M12)),"0") -> 0 | AD12: =IF(MONTH(A12)=7,IF((ISBLANK(C12)),0,(M12)),"0") -> 0 | AE12: =IF(MONTH(A12)=8,IF((ISBLANK(B12)),0,(M12)),"0") -> 0 | AF12: =IF(MONTH(A12)=8,IF((ISBLANK(C12)),0,(M12)),"0") -> 0 | AG12: =IF(MONTH(A12)=9,IF((ISBLANK(B12)),0,(M12)),"0") -> 0 | AH12: =IF(MONTH(A12)=9,IF((ISBLANK(C12)),0,(M12)),"0") -> 0 | AI12: =IF(MONTH(A12)=10,IF((ISBLANK(B12)),0,(M12)),"0") -> 0 | AJ12: =IF(MONTH(A12)=10,IF((ISBLANK(C12)),0,(M12)),"0") -> 0 | AK12: =IF(MONTH(A12)=11,IF((ISBLANK(B12)),0,(M12)),"0") -> 0 | AL12: =IF(MONTH(A12)=11,IF((ISBLANK(C12)),0,(M12)),"0") -> 0 | AM12: =IF(MONTH(A12)=12,IF((ISBLANK(B12)),0,(M12)),"0") -> 0 | AN12: =IF(MONTH(A12)=12,IF((ISBLANK(C12)),0,(M12)),"0") -> 0
A13: 45845 | B13: 1 | D13: Rotary | F13: Jared Traggic & Kiana Spearman | G13: 4200 MOZART BRIGADE LANE # 4200C, FAIRFAX, VA 22033 | H13: 2400 | I13: 2400 | J13: 0.25 | K13: =IF(ISBLANK(A13),"",(I13*J13)) -> 600 | M13: =IF((ISBLANK(A13)),"",'Fee calc_closed Transactions'!F13) -> 510 | N13: =IF(K13="","",'Fee calc_closed Transactions'!G13) -> 90 | P13: =IF(ISBLANK(A13),"0",I13) -> 2400 | Q13: =IF(MONTH(A13)=1,IF((ISBLANK(B13)),0,(M13)),"0") -> 0 | R13: =IF(MONTH(A13)=1,IF((ISBLANK(C13)),0,(M13)),"0") -> 0 | S13: =IF(MONTH(A13)=2,IF((ISBLANK(B13)),0,(M13)),"0") -> 0 | T13: =IF(MONTH(A13)=2,IF((ISBLANK(C13)),0,(M13)),"0") -> 0 | U13: =IF(MONTH(A13)=3,IF((ISBLANK(B13)),0,(M13)),"0") -> 0 | V13: =IF(MONTH(A13)=3,IF((ISBLANK(C13)),0,(M13)),"0") -> 0 | W13: =IF(MONTH(A13)=4,IF((ISBLANK(B13)),0,(M13)),"0") -> 0 | X13: =IF(MONTH(A13)=4,IF((ISBLANK(C13)),0,(M13)),"0") -> 0 | Y13: =IF(MONTH(A13)=5,IF((ISBLANK(B13)),0,(M13)),"0") -> 0 | Z13: =IF(MONTH(A13)=5,IF((ISBLANK(C13)),0,(M13)),"0") -> 0 | AA13: =IF(MONTH(A13)=6,IF((ISBLANK(B13)),0,(M13)),"0") -> 0 | AB13: =IF(MONTH(A13)=6,IF((ISBLANK(C13)),0,(M13)),"0") -> 0 | AC13: =IF(MONTH(A13)=7,IF((ISBLANK(B13)),0,(M13)),"0") -> 510 | AD13: =IF(MONTH(A13)=7,IF((ISBLANK(C13)),0,(M13)),"0") -> 0 | AE13: =IF(MONTH(A13)=8,IF((ISBLANK(B13)),0,(M13)),"0") -> 0 | AF13: =IF(MONTH(A13)=8,IF((ISBLANK(C13)),0,(M13)),"0") -> 0 | AG13: =IF(MONTH(A13)=9,IF((ISBLANK(B13)),0,(M13)),"0") -> 0 | AH13: =IF(MONTH(A13)=9,IF((ISBLANK(C13)),0,(M13)),"0") -> 0 | AI13: =IF(MONTH(A13)=10,IF((ISBLANK(B13)),0,(M13)),"0") -> 0 | AJ13: =IF(MONTH(A13)=10,IF((ISBLANK(C13)),0,(M13)),"0") -> 0 | AK13: =IF(MONTH(A13)=11,IF((ISBLANK(B13)),0,(M13)),"0") -> 0 | AL13: =IF(MONTH(A13)=11,IF((ISBLANK(C13)),0,(M13)),"0") -> 0 | AM13: =IF(MONTH(A13)=12,IF((ISBLANK(B13)),0,(M13)),"0") -> 0 | AN13: =IF(MONTH(A13)=12,IF((ISBLANK(C13)),0,(M13)),"0") -> 0
A14: 45853 | B14: 1 | D14: ninja referral | F14: Kristine & Ken Delos Reyes | G14: 8993 Katherine Johnson Dr, Manassas, VA 20109 | H14: 665280 | I14: 665280 | J14: 0.00901876 | K14: =IF(ISBLANK(A14),"",(I14*J14)) -> 6000.0007 | L14: 1800 | M14: =IF((ISBLANK(A14)),"",'Fee calc_closed Transactions'!F14) -> 3570.0006 | N14: =IF(K14="","",'Fee calc_closed Transactions'!G14) -> 630.0001 | P14: =IF(ISBLANK(A14),"0",I14) -> 665280 | Q14: =IF(MONTH(A14)=1,IF((ISBLANK(B14)),0,(M14)),"0") -> 0 | R14: =IF(MONTH(A14)=1,IF((ISBLANK(C14)),0,(M14)),"0") -> 0 | S14: =IF(MONTH(A14)=2,IF((ISBLANK(B14)),0,(M14)),"0") -> 0 | T14: =IF(MONTH(A14)=2,IF((ISBLANK(C14)),0,(M14)),"0") -> 0 | U14: =IF(MONTH(A14)=3,IF((ISBLANK(B14)),0,(M14)),"0") -> 0 | V14: =IF(MONTH(A14)=3,IF((ISBLANK(C14)),0,(M14)),"0") -> 0 | W14: =IF(MONTH(A14)=4,IF((ISBLANK(B14)),0,(M14)),"0") -> 0 | X14: =IF(MONTH(A14)=4,IF((ISBLANK(C14)),0,(M14)),"0") -> 0 | Y14: =IF(MONTH(A14)=5,IF((ISBLANK(B14)),0,(M14)),"0") -> 0 | Z14: =IF(MONTH(A14)=5,IF((ISBLANK(C14)),0,(M14)),"0") -> 0 | AA14: =IF(MONTH(A14)=6,IF((ISBLANK(B14)),0,(M14)),"0") -> 0 | AB14: =IF(MONTH(A14)=6,IF((ISBLANK(C14)),0,(M14)),"0") -> 0 | AC14: =IF(MONTH(A14)=7,IF((ISBLANK(B14)),0,(M14)),"0") -> 3570.0006 | AD14: =IF(MONTH(A14)=7,IF((ISBLANK(C14)),0,(M14)),"0") -> 0 | AE14: =IF(MONTH(A14)=8,IF((ISBLANK(B14)),0,(M14)),"0") -> 0 | AF14: =IF(MONTH(A14)=8,IF((ISBLANK(C14)),0,(M14)),"0") -> 0 | AG14: =IF(MONTH(A14)=9,IF((ISBLANK(B14)),0,(M14)),"0") -> 0 | AH14: =IF(MONTH(A14)=9,IF((ISBLANK(C14)),0,(M14)),"0") -> 0 | AI14: =IF(MONTH(A14)=10,IF((ISBLANK(B14)),0,(M14)),"0") -> 0 | AJ14: =IF(MONTH(A14)=10,IF((ISBLANK(C14)),0,(M14)),"0") -> 0 | AK14: =IF(MONTH(A14)=11,IF((ISBLANK(B14)),0,(M14)),"0") -> 0 | AL14: =IF(MONTH(A14)=11,IF((ISBLANK(C14)),0,(M14)),"0") -> 0 | AM14: =IF(MONTH(A14)=12,IF((ISBLANK(B14)),0,(M14)),"0") -> 0 | AN14: =IF(MONTH(A14)=12,IF((ISBLANK(C14)),0,(M14)),"0") -> 0
A15: 45884 | B15: 1 | C15: 1 | D15: realtor referral | F15: Anne Duffy, Joshua Foote, Kate McCusker | G15: 926 N Edgewood St #2, Arlington, VA 22201 | H15: 3295 | I15: 3295 | J15: 1 | K15: =IF(ISBLANK(A15),"",(I15*J15)) -> 3295 | L15: 823.75 | M15: =IF((ISBLANK(A15)),"",'Fee calc_closed Transactions'!F15) -> 2100.5625 | N15: =IF(K15="","",'Fee calc_closed Transactions'!G15) -> 370.6875 | P15: =IF(ISBLANK(A15),"0",I15) -> 3295 | Q15: =IF(MONTH(A15)=1,IF((ISBLANK(B15)),0,(M15)),"0") -> 0 | R15: =IF(MONTH(A15)=1,IF((ISBLANK(C15)),0,(M15)),"0") -> 0 | S15: =IF(MONTH(A15)=2,IF((ISBLANK(B15)),0,(M15)),"0") -> 0 | T15: =IF(MONTH(A15)=2,IF((ISBLANK(C15)),0,(M15)),"0") -> 0 | U15: =IF(MONTH(A15)=3,IF((ISBLANK(B15)),0,(M15)),"0") -> 0 | V15: =IF(MONTH(A15)=3,IF((ISBLANK(C15)),0,(M15)),"0") -> 0 | W15: =IF(MONTH(A15)=4,IF((ISBLANK(B15)),0,(M15)),"0") -> 0 | X15: =IF(MONTH(A15)=4,IF((ISBLANK(C15)),0,(M15)),"0") -> 0 | Y15: =IF(MONTH(A15)=5,IF((ISBLANK(B15)),0,(M15)),"0") -> 0 | Z15: =IF(MONTH(A15)=5,IF((ISBLANK(C15)),0,(M15)),"0") -> 0 | AA15: =IF(MONTH(A15)=6,IF((ISBLANK(B15)),0,(M15)),"0") -> 0 | AB15: =IF(MONTH(A15)=6,IF((ISBLANK(C15)),0,(M15)),"0") -> 0 | AC15: =IF(MONTH(A15)=7,IF((ISBLANK(B15)),0,(M15)),"0") -> 0 | AD15: =IF(MONTH(A15)=7,IF((ISBLANK(C15)),0,(M15)),"0") -> 0 | AE15: =IF(MONTH(A15)=8,IF((ISBLANK(B15)),0,(M15)),"0") -> 2100.5625 | AF15: =IF(MONTH(A15)=8,IF((ISBLANK(C15)),0,(M15)),"0") -> 2100.5625 | AG15: =IF(MONTH(A15)=9,IF((ISBLANK(B15)),0,(M15)),"0") -> 0 | AH15: =IF(MONTH(A15)=9,IF((ISBLANK(C15)),0,(M15)),"0") -> 0 | AI15: =IF(MONTH(A15)=10,IF((ISBLANK(B15)),0,(M15)),"0") -> 0 | AJ15: =IF(MONTH(A15)=10,IF((ISBLANK(C15)),0,(M15)),"0") -> 0 | AK15: =IF(MONTH(A15)=11,IF((ISBLANK(B15)),0,(M15)),"0") -> 0 | AL15: =IF(MONTH(A15)=11,IF((ISBLANK(C15)),0,(M15)),"0") -> 0 | AM15: =IF(MONTH(A15)=12,IF((ISBLANK(B15)),0,(M15)),"0") -> 0 | AN15: =IF(MONTH(A15)=12,IF((ISBLANK(C15)),0,(M15)),"0") -> 0
A16: 45903 | B16: 1 | D16: wife | F16: Cintia Samaha Desnoyers | G16: 14552 Woodgate Manor Pl, Centreville, VA 20120 | H16: 599990 | I16: 615000 | J16: 0 | K16: =IF(ISBLANK(A16),"",(I16*J16)) -> 0 | M16: =IF((ISBLANK(A16)),"",'Fee calc_closed Transactions'!F16) -> 0 | N16: =IF(K16="","",'Fee calc_closed Transactions'!G16) -> 0 | P16: =IF(ISBLANK(A16),"0",I16) -> 615000 | Q16: =IF(MONTH(A16)=1,IF((ISBLANK(B16)),0,(M16)),"0") -> 0 | R16: =IF(MONTH(A16)=1,IF((ISBLANK(C16)),0,(M16)),"0") -> 0 | S16: =IF(MONTH(A16)=2,IF((ISBLANK(B16)),0,(M16)),"0") -> 0 | T16: =IF(MONTH(A16)=2,IF((ISBLANK(C16)),0,(M16)),"0") -> 0 | U16: =IF(MONTH(A16)=3,IF((ISBLANK(B16)),0,(M16)),"0") -> 0 | V16: =IF(MONTH(A16)=3,IF((ISBLANK(C16)),0,(M16)),"0") -> 0 | W16: =IF(MONTH(A16)=4,IF((ISBLANK(B16)),0,(M16)),"0") -> 0 | X16: =IF(MONTH(A16)=4,IF((ISBLANK(C16)),0,(M16)),"0") -> 0 | Y16: =IF(MONTH(A16)=5,IF((ISBLANK(B16)),0,(M16)),"0") -> 0 | Z16: =IF(MONTH(A16)=5,IF((ISBLANK(C16)),0,(M16)),"0") -> 0 | AA16: =IF(MONTH(A16)=6,IF((ISBLANK(B16)),0,(M16)),"0") -> 0 | AB16: =IF(MONTH(A16)=6,IF((ISBLANK(C16)),0,(M16)),"0") -> 0 | AC16: =IF(MONTH(A16)=7,IF((ISBLANK(B16)),0,(M16)),"0") -> 0 | AD16: =IF(MONTH(A16)=7,IF((ISBLANK(C16)),0,(M16)),"0") -> 0 | AE16: =IF(MONTH(A16)=8,IF((ISBLANK(B16)),0,(M16)),"0") -> 0 | AF16: =IF(MONTH(A16)=8,IF((ISBLANK(C16)),0,(M16)),"0") -> 0 | AG16: =IF(MONTH(A16)=9,IF((ISBLANK(B16)),0,(M16)),"0") -> 0 | AH16: =IF(MONTH(A16)=9,IF((ISBLANK(C16)),0,(M16)),"0") -> 0 | AI16: =IF(MONTH(A16)=10,IF((ISBLANK(B16)),0,(M16)),"0") -> 0 | AJ16: =IF(MONTH(A16)=10,IF((ISBLANK(C16)),0,(M16)),"0") -> 0 | AK16: =IF(MONTH(A16)=11,IF((ISBLANK(B16)),0,(M16)),"0") -> 0 | AL16: =IF(MONTH(A16)=11,IF((ISBLANK(C16)),0,(M16)),"0") -> 0 | AM16: =IF(MONTH(A16)=12,IF((ISBLANK(B16)),0,(M16)),"0") -> 0 | AN16: =IF(MONTH(A16)=12,IF((ISBLANK(C16)),0,(M16)),"0") -> 0
A17: 45910 | C17: 1 | D17: SOI | F17: Ashleigh Verma & Tapinder Garcha | G17: 2820 Hokie Ln, Alexandria, VA 22314 | H17: 780000 | I17: 770000 | J17: 0.02 | K17: =IF(ISBLANK(A17),"",(I17*J17)) -> 15400 | M17: =IF((ISBLANK(A17)),"",'Fee calc_closed Transactions'!F17) -> 13090 | N17: =IF(K17="","",'Fee calc_closed Transactions'!G17) -> 2310 | P17: =IF(ISBLANK(A17),"0",I17) -> 770000 | Q17: =IF(MONTH(A17)=1,IF((ISBLANK(B17)),0,(M17)),"0") -> 0 | R17: =IF(MONTH(A17)=1,IF((ISBLANK(C17)),0,(M17)),"0") -> 0 | S17: =IF(MONTH(A17)=2,IF((ISBLANK(B17)),0,(M17)),"0") -> 0 | T17: =IF(MONTH(A17)=2,IF((ISBLANK(C17)),0,(M17)),"0") -> 0 | U17: =IF(MONTH(A17)=3,IF((ISBLANK(B17)),0,(M17)),"0") -> 0 | V17: =IF(MONTH(A17)=3,IF((ISBLANK(C17)),0,(M17)),"0") -> 0 | W17: =IF(MONTH(A17)=4,IF((ISBLANK(B17)),0,(M17)),"0") -> 0 | X17: =IF(MONTH(A17)=4,IF((ISBLANK(C17)),0,(M17)),"0") -> 0 | Y17: =IF(MONTH(A17)=5,IF((ISBLANK(B17)),0,(M17)),"0") -> 0 | Z17: =IF(MONTH(A17)=5,IF((ISBLANK(C17)),0,(M17)),"0") -> 0 | AA17: =IF(MONTH(A17)=6,IF((ISBLANK(B17)),0,(M17)),"0") -> 0 | AB17: =IF(MONTH(A17)=6,IF((ISBLANK(C17)),0,(M17)),"0") -> 0 | AC17: =IF(MONTH(A17)=7,IF((ISBLANK(B17)),0,(M17)),"0") -> 0 | AD17: =IF(MONTH(A17)=7,IF((ISBLANK(C17)),0,(M17)),"0") -> 0 | AE17: =IF(MONTH(A17)=8,IF((ISBLANK(B17)),0,(M17)),"0") -> 0 | AF17: =IF(MONTH(A17)=8,IF((ISBLANK(C17)),0,(M17)),"0") -> 0 | AG17: =IF(MONTH(A17)=9,IF((ISBLANK(B17)),0,(M17)),"0") -> 0 | AH17: =IF(MONTH(A17)=9,IF((ISBLANK(C17)),0,(M17)),"0") -> 13090 | AI17: =IF(MONTH(A17)=10,IF((ISBLANK(B17)),0,(M17)),"0") -> 0 | AJ17: =IF(MONTH(A17)=10,IF((ISBLANK(C17)),0,(M17)),"0") -> 0 | AK17: =IF(MONTH(A17)=11,IF((ISBLANK(B17)),0,(M17)),"0") -> 0 | AL17: =IF(MONTH(A17)=11,IF((ISBLANK(C17)),0,(M17)),"0") -> 0 | AM17: =IF(MONTH(A17)=12,IF((ISBLANK(B17)),0,(M17)),"0") -> 0 | AN17: =IF(MONTH(A17)=12,IF((ISBLANK(C17)),0,(M17)),"0") -> 0
A18: 45920 | C18: 1 | D18: wife | F18: Cintia Samaha Desnoyers | G18: 11122 Rock Garden Dr, Fairfax, 22030 | H18: 2300 | I18: 2400 | J18: 0 | K18: =IF(ISBLANK(A18),"",(I18*J18)) -> 0 | M18: =IF((ISBLANK(A18)),"",'Fee calc_closed Transactions'!F18) -> 0 | N18: =IF(K18="","",'Fee calc_closed Transactions'!G18) -> 0 | P18: =IF(ISBLANK(A18),"0",I18) -> 2400 | Q18: =IF(MONTH(A18)=1,IF((ISBLANK(B18)),0,(M18)),"0") -> 0 | R18: =IF(MONTH(A18)=1,IF((ISBLANK(C18)),0,(M18)),"0") -> 0 | S18: =IF(MONTH(A18)=2,IF((ISBLANK(B18)),0,(M18)),"0") -> 0 | T18: =IF(MONTH(A18)=2,IF((ISBLANK(C18)),0,(M18)),"0") -> 0 | U18: =IF(MONTH(A18)=3,IF((ISBLANK(B18)),0,(M18)),"0") -> 0 | V18: =IF(MONTH(A18)=3,IF((ISBLANK(C18)),0,(M18)),"0") -> 0 | W18: =IF(MONTH(A18)=4,IF((ISBLANK(B18)),0,(M18)),"0") -> 0 | X18: =IF(MONTH(A18)=4,IF((ISBLANK(C18)),0,(M18)),"0") -> 0 | Y18: =IF(MONTH(A18)=5,IF((ISBLANK(B18)),0,(M18)),"0") -> 0 | Z18: =IF(MONTH(A18)=5,IF((ISBLANK(C18)),0,(M18)),"0") -> 0 | AA18: =IF(MONTH(A18)=6,IF((ISBLANK(B18)),0,(M18)),"0") -> 0 | AB18: =IF(MONTH(A18)=6,IF((ISBLANK(C18)),0,(M18)),"0") -> 0 | AC18: =IF(MONTH(A18)=7,IF((ISBLANK(B18)),0,(M18)),"0") -> 0 | AD18: =IF(MONTH(A18)=7,IF((ISBLANK(C18)),0,(M18)),"0") -> 0 | AE18: =IF(MONTH(A18)=8,IF((ISBLANK(B18)),0,(M18)),"0") -> 0 | AF18: =IF(MONTH(A18)=8,IF((ISBLANK(C18)),0,(M18)),"0") -> 0 | AG18: =IF(MONTH(A18)=9,IF((ISBLANK(B18)),0,(M18)),"0") -> 0 | AH18: =IF(MONTH(A18)=9,IF((ISBLANK(C18)),0,(M18)),"0") -> 0 | AI18: =IF(MONTH(A18)=10,IF((ISBLANK(B18)),0,(M18)),"0") -> 0 | AJ18: =IF(MONTH(A18)=10,IF((ISBLANK(C18)),0,(M18)),"0") -> 0 | AK18: =IF(MONTH(A18)=11,IF((ISBLANK(B18)),0,(M18)),"0") -> 0 | AL18: =IF(MONTH(A18)=11,IF((ISBLANK(C18)),0,(M18)),"0") -> 0 | AM18: =IF(MONTH(A18)=12,IF((ISBLANK(B18)),0,(M18)),"0") -> 0 | AN18: =IF(MONTH(A18)=12,IF((ISBLANK(C18)),0,(M18)),"0") -> 0
A19: 45981 | C19: 1 | D19: wife | F19: Noel Contreras | G19: 14552 Woodgate Manor Pl, Centreville, VA 20120 | H19: 1500 | I19: 1500 | J19: 0 | K19: =IF(ISBLANK(A19),"",(I19*J19)) -> 0 | M19: =IF((ISBLANK(A19)),"",'Fee calc_closed Transactions'!F19) -> 0 | N19: =IF(K19="","",'Fee calc_closed Transactions'!G19) -> 0 | P19: =IF(ISBLANK(A19),"0",I19) -> 1500 | Q19: =IF(MONTH(A19)=1,IF((ISBLANK(B19)),0,(M19)),"0") -> 0 | R19: =IF(MONTH(A19)=1,IF((ISBLANK(C19)),0,(M19)),"0") -> 0 | S19: =IF(MONTH(A19)=2,IF((ISBLANK(B19)),0,(M19)),"0") -> 0 | T19: =IF(MONTH(A19)=2,IF((ISBLANK(C19)),0,(M19)),"0") -> 0 | U19: =IF(MONTH(A19)=3,IF((ISBLANK(B19)),0,(M19)),"0") -> 0 | V19: =IF(MONTH(A19)=3,IF((ISBLANK(C19)),0,(M19)),"0") -> 0 | W19: =IF(MONTH(A19)=4,IF((ISBLANK(B19)),0,(M19)),"0") -> 0 | X19: =IF(MONTH(A19)=4,IF((ISBLANK(C19)),0,(M19)),"0") -> 0 | Y19: =IF(MONTH(A19)=5,IF((ISBLANK(B19)),0,(M19)),"0") -> 0 | Z19: =IF(MONTH(A19)=5,IF((ISBLANK(C19)),0,(M19)),"0") -> 0 | AA19: =IF(MONTH(A19)=6,IF((ISBLANK(B19)),0,(M19)),"0") -> 0 | AB19: =IF(MONTH(A19)=6,IF((ISBLANK(C19)),0,(M19)),"0") -> 0 | AC19: =IF(MONTH(A19)=7,IF((ISBLANK(B19)),0,(M19)),"0") -> 0 | AD19: =IF(MONTH(A19)=7,IF((ISBLANK(C19)),0,(M19)),"0") -> 0 | AE19: =IF(MONTH(A19)=8,IF((ISBLANK(B19)),0,(M19)),"0") -> 0 | AF19: =IF(MONTH(A19)=8,IF((ISBLANK(C19)),0,(M19)),"0") -> 0 | AG19: =IF(MONTH(A19)=9,IF((ISBLANK(B19)),0,(M19)),"0") -> 0 | AH19: =IF(MONTH(A19)=9,IF((ISBLANK(C19)),0,(M19)),"0") -> 0 | AI19: =IF(MONTH(A19)=10,IF((ISBLANK(B19)),0,(M19)),"0") -> 0 | AJ19: =IF(MONTH(A19)=10,IF((ISBLANK(C19)),0,(M19)),"0") -> 0 | AK19: =IF(MONTH(A19)=11,IF((ISBLANK(B19)),0,(M19)),"0") -> 0 | AL19: =IF(MONTH(A19)=11,IF((ISBLANK(C19)),0,(M19)),"0") -> 0 | AM19: =IF(MONTH(A19)=12,IF((ISBLANK(B19)),0,(M19)),"0") -> 0 | AN19: =IF(MONTH(A19)=12,IF((ISBLANK(C19)),0,(M19)),"0") -> 0
K20: =IF(ISBLANK(A20),"",(I20*J20)) | M20: =IF((ISBLANK(A20)),"",'Fee calc_closed Transactions'!F20) | N20: =IF(K20="","",'Fee calc_closed Transactions'!G20) | P20: =IF(ISBLANK(A20),"0",I20) -> 0 | Q20: =IF(MONTH(A20)=1,IF((ISBLANK(B20)),0,(M20)),"0") -> 0 | R20: =IF(MONTH(A20)=1,IF((ISBLANK(C20)),0,(M20)),"0") -> 0 | S20: =IF(MONTH(A20)=2,IF((ISBLANK(B20)),0,(M20)),"0") -> 0 | T20: =IF(MONTH(A20)=2,IF((ISBLANK(C20)),0,(M20)),"0") -> 0 | U20: =IF(MONTH(A20)=3,IF((ISBLANK(B20)),0,(M20)),"0") -> 0 | V20: =IF(MONTH(A20)=3,IF((ISBLANK(C20)),0,(M20)),"0") -> 0 | W20: =IF(MONTH(A20)=4,IF((ISBLANK(B20)),0,(M20)),"0") -> 0 | X20: =IF(MONTH(A20)=4,IF((ISBLANK(C20)),0,(M20)),"0") -> 0 | Y20: =IF(MONTH(A20)=5,IF((ISBLANK(B20)),0,(M20)),"0") -> 0 | Z20: =IF(MONTH(A20)=5,IF((ISBLANK(C20)),0,(M20)),"0") -> 0 | AA20: =IF(MONTH(A20)=6,IF((ISBLANK(B20)),0,(M20)),"0") -> 0 | AB20: =IF(MONTH(A20)=6,IF((ISBLANK(C20)),0,(M20)),"0") -> 0 | AC20: =IF(MONTH(A20)=7,IF((ISBLANK(B20)),0,(M20)),"0") -> 0 | AD20: =IF(MONTH(A20)=7,IF((ISBLANK(C20)),0,(M20)),"0") -> 0 | AE20: =IF(MONTH(A20)=8,IF((ISBLANK(B20)),0,(M20)),"0") -> 0 | AF20: =IF(MONTH(A20)=8,IF((ISBLANK(C20)),0,(M20)),"0") -> 0 | AG20: =IF(MONTH(A20)=9,IF((ISBLANK(B20)),0,(M20)),"0") -> 0 | AH20: =IF(MONTH(A20)=9,IF((ISBLANK(C20)),0,(M20)),"0") -> 0 | AI20: =IF(MONTH(A20)=10,IF((ISBLANK(B20)),0,(M20)),"0") -> 0 | AJ20: =IF(MONTH(A20)=10,IF((ISBLANK(C20)),0,(M20)),"0") -> 0 | AK20: =IF(MONTH(A20)=11,IF((ISBLANK(B20)),0,(M20)),"0") -> 0 | AL20: =IF(MONTH(A20)=11,IF((ISBLANK(C20)),0,(M20)),"0") -> 0 | AM20: =IF(MONTH(A20)=12,IF((ISBLANK(B20)),0,(M20)),"0") -> 0 | AN20: =IF(MONTH(A20)=12,IF((ISBLANK(C20)),0,(M20)),"0") -> 0
K21: =IF(ISBLANK(A21),"",(I21*J21)) | M21: =IF((ISBLANK(A21)),"",'Fee calc_closed Transactions'!F21) | N21: =IF(K21="","",'Fee calc_closed Transactions'!G21) | P21: =IF(ISBLANK(A21),"0",I21) -> 0 | Q21: =IF(MONTH(A21)=1,IF((ISBLANK(B21)),0,(M21)),"0") -> 0 | R21: =IF(MONTH(A21)=1,IF((ISBLANK(C21)),0,(M21)),"0") -> 0 | S21: =IF(MONTH(A21)=2,IF((ISBLANK(B21)),0,(M21)),"0") -> 0 | T21: =IF(MONTH(A21)=2,IF((ISBLANK(C21)),0,(M21)),"0") -> 0 | U21: =IF(MONTH(A21)=3,IF((ISBLANK(B21)),0,(M21)),"0") -> 0 | V21: =IF(MONTH(A21)=3,IF((ISBLANK(C21)),0,(M21)),"0") -> 0 | W21: =IF(MONTH(A21)=4,IF((ISBLANK(B21)),0,(M21)),"0") -> 0 | X21: =IF(MONTH(A21)=4,IF((ISBLANK(C21)),0,(M21)),"0") -> 0 | Y21: =IF(MONTH(A21)=5,IF((ISBLANK(B21)),0,(M21)),"0") -> 0 | Z21: =IF(MONTH(A21)=5,IF((ISBLANK(C21)),0,(M21)),"0") -> 0 | AA21: =IF(MONTH(A21)=6,IF((ISBLANK(B21)),0,(M21)),"0") -> 0 | AB21: =IF(MONTH(A21)=6,IF((ISBLANK(C21)),0,(M21)),"0") -> 0 | AC21: =IF(MONTH(A21)=7,IF((ISBLANK(B21)),0,(M21)),"0") -> 0 | AD21: =IF(MONTH(A21)=7,IF((ISBLANK(C21)),0,(M21)),"0") -> 0 | AE21: =IF(MONTH(A21)=8,IF((ISBLANK(B21)),0,(M21)),"0") -> 0 | AF21: =IF(MONTH(A21)=8,IF((ISBLANK(C21)),0,(M21)),"0") -> 0 | AG21: =IF(MONTH(A21)=9,IF((ISBLANK(B21)),0,(M21)),"0") -> 0 | AH21: =IF(MONTH(A21)=9,IF((ISBLANK(C21)),0,(M21)),"0") -> 0 | AI21: =IF(MONTH(A21)=10,IF((ISBLANK(B21)),0,(M21)),"0") -> 0 | AJ21: =IF(MONTH(A21)=10,IF((ISBLANK(C21)),0,(M21)),"0") -> 0 | AK21: =IF(MONTH(A21)=11,IF((ISBLANK(B21)),0,(M21)),"0") -> 0 | AL21: =IF(MONTH(A21)=11,IF((ISBLANK(C21)),0,(M21)),"0") -> 0 | AM21: =IF(MONTH(A21)=12,IF((ISBLANK(B21)),0,(M21)),"0") -> 0 | AN21: =IF(MONTH(A21)=12,IF((ISBLANK(C21)),0,(M21)),"0") -> 0
K22: =IF(ISBLANK(A22),"",(I22*J22)) | M22: =IF((ISBLANK(A22)),"",'Fee calc_closed Transactions'!F22) | N22: =IF(K22="","",'Fee calc_closed Transactions'!G22) | P22: =IF(ISBLANK(A22),"0",I22) -> 0 | Q22: =IF(MONTH(A22)=1,IF((ISBLANK(B22)),0,(M22)),"0") -> 0 | R22: =IF(MONTH(A22)=1,IF((ISBLANK(C22)),0,(M22)),"0") -> 0 | S22: =IF(MONTH(A22)=2,IF((ISBLANK(B22)),0,(M22)),"0") -> 0 | T22: =IF(MONTH(A22)=2,IF((ISBLANK(C22)),0,(M22)),"0") -> 0 | U22: =IF(MONTH(A22)=3,IF((ISBLANK(B22)),0,(M22)),"0") -> 0 | V22: =IF(MONTH(A22)=3,IF((ISBLANK(C22)),0,(M22)),"0") -> 0 | W22: =IF(MONTH(A22)=4,IF((ISBLANK(B22)),0,(M22)),"0") -> 0 | X22: =IF(MONTH(A22)=4,IF((ISBLANK(C22)),0,(M22)),"0") -> 0 | Y22: =IF(MONTH(A22)=5,IF((ISBLANK(B22)),0,(M22)),"0") -> 0 | Z22: =IF(MONTH(A22)=5,IF((ISBLANK(C22)),0,(M22)),"0") -> 0 | AA22: =IF(MONTH(A22)=6,IF((ISBLANK(B22)),0,(M22)),"0") -> 0 | AB22: =IF(MONTH(A22)=6,IF((ISBLANK(C22)),0,(M22)),"0") -> 0 | AC22: =IF(MONTH(A22)=7,IF((ISBLANK(B22)),0,(M22)),"0") -> 0 | AD22: =IF(MONTH(A22)=7,IF((ISBLANK(C22)),0,(M22)),"0") -> 0 | AE22: =IF(MONTH(A22)=8,IF((ISBLANK(B22)),0,(M22)),"0") -> 0 | AF22: =IF(MONTH(A22)=8,IF((ISBLANK(C22)),0,(M22)),"0") -> 0 | AG22: =IF(MONTH(A22)=9,IF((ISBLANK(B22)),0,(M22)),"0") -> 0 | AH22: =IF(MONTH(A22)=9,IF((ISBLANK(C22)),0,(M22)),"0") -> 0 | AI22: =IF(MONTH(A22)=10,IF((ISBLANK(B22)),0,(M22)),"0") -> 0 | AJ22: =IF(MONTH(A22)=10,IF((ISBLANK(C22)),0,(M22)),"0") -> 0 | AK22: =IF(MONTH(A22)=11,IF((ISBLANK(B22)),0,(M22)),"0") -> 0 | AL22: =IF(MONTH(A22)=11,IF((ISBLANK(C22)),0,(M22)),"0") -> 0 | AM22: =IF(MONTH(A22)=12,IF((ISBLANK(B22)),0,(M22)),"0") -> 0 | AN22: =IF(MONTH(A22)=12,IF((ISBLANK(C22)),0,(M22)),"0") -> 0
K23: =IF(ISBLANK(A23),"",(I23*J23)) | M23: =IF((ISBLANK(A23)),"",'Fee calc_closed Transactions'!F23) | N23: =IF(K23="","",'Fee calc_closed Transactions'!G23) | P23: =IF(ISBLANK(A23),"0",I23) -> 0 | Q23: =IF(MONTH(A23)=1,IF((ISBLANK(B23)),0,(M23)),"0") -> 0 | R23: =IF(MONTH(A23)=1,IF((ISBLANK(C23)),0,(M23)),"0") -> 0 | S23: =IF(MONTH(A23)=2,IF((ISBLANK(B23)),0,(M23)),"0") -> 0 | T23: =IF(MONTH(A23)=2,IF((ISBLANK(C23)),0,(M23)),"0") -> 0 | U23: =IF(MONTH(A23)=3,IF((ISBLANK(B23)),0,(M23)),"0") -> 0 | V23: =IF(MONTH(A23)=3,IF((ISBLANK(C23)),0,(M23)),"0") -> 0 | W23: =IF(MONTH(A23)=4,IF((ISBLANK(B23)),0,(M23)),"0") -> 0 | X23: =IF(MONTH(A23)=4,IF((ISBLANK(C23)),0,(M23)),"0") -> 0 | Y23: =IF(MONTH(A23)=5,IF((ISBLANK(B23)),0,(M23)),"0") -> 0 | Z23: =IF(MONTH(A23)=5,IF((ISBLANK(C23)),0,(M23)),"0") -> 0 | AA23: =IF(MONTH(A23)=6,IF((ISBLANK(B23)),0,(M23)),"0") -> 0 | AB23: =IF(MONTH(A23)=6,IF((ISBLANK(C23)),0,(M23)),"0") -> 0 | AC23: =IF(MONTH(A23)=7,IF((ISBLANK(B23)),0,(M23)),"0") -> 0 | AD23: =IF(MONTH(A23)=7,IF((ISBLANK(C23)),0,(M23)),"0") -> 0 | AE23: =IF(MONTH(A23)=8,IF((ISBLANK(B23)),0,(M23)),"0") -> 0 | AF23: =IF(MONTH(A23)=8,IF((ISBLANK(C23)),0,(M23)),"0") -> 0 | AG23: =IF(MONTH(A23)=9,IF((ISBLANK(B23)),0,(M23)),"0") -> 0 | AH23: =IF(MONTH(A23)=9,IF((ISBLANK(C23)),0,(M23)),"0") -> 0 | AI23: =IF(MONTH(A23)=10,IF((ISBLANK(B23)),0,(M23)),"0") -> 0 | AJ23: =IF(MONTH(A23)=10,IF((ISBLANK(C23)),0,(M23)),"0") -> 0 | AK23: =IF(MONTH(A23)=11,IF((ISBLANK(B23)),0,(M23)),"0") -> 0 | AL23: =IF(MONTH(A23)=11,IF((ISBLANK(C23)),0,(M23)),"0") -> 0 | AM23: =IF(MONTH(A23)=12,IF((ISBLANK(B23)),0,(M23)),"0") -> 0 | AN23: =IF(MONTH(A23)=12,IF((ISBLANK(C23)),0,(M23)),"0") -> 0
K24: =IF(ISBLANK(A24),"",(I24*J24)) | M24: =IF((ISBLANK(A24)),"",'Fee calc_closed Transactions'!F24) | N24: =IF(K24="","",'Fee calc_closed Transactions'!G24) | P24: =IF(ISBLANK(A24),"0",I24) -> 0 | Q24: =IF(MONTH(A24)=1,IF((ISBLANK(B24)),0,(M24)),"0") -> 0 | R24: =IF(MONTH(A24)=1,IF((ISBLANK(C24)),0,(M24)),"0") -> 0 | S24: =IF(MONTH(A24)=2,IF((ISBLANK(B24)),0,(M24)),"0") -> 0 | T24: =IF(MONTH(A24)=2,IF((ISBLANK(C24)),0,(M24)),"0") -> 0 | U24: =IF(MONTH(A24)=3,IF((ISBLANK(B24)),0,(M24)),"0") -> 0 | V24: =IF(MONTH(A24)=3,IF((ISBLANK(C24)),0,(M24)),"0") -> 0 | W24: =IF(MONTH(A24)=4,IF((ISBLANK(B24)),0,(M24)),"0") -> 0 | X24: =IF(MONTH(A24)=4,IF((ISBLANK(C24)),0,(M24)),"0") -> 0 | Y24: =IF(MONTH(A24)=5,IF((ISBLANK(B24)),0,(M24)),"0") -> 0 | Z24: =IF(MONTH(A24)=5,IF((ISBLANK(C24)),0,(M24)),"0") -> 0 | AA24: =IF(MONTH(A24)=6,IF((ISBLANK(B24)),0,(M24)),"0") -> 0 | AB24: =IF(MONTH(A24)=6,IF((ISBLANK(C24)),0,(M24)),"0") -> 0 | AC24: =IF(MONTH(A24)=7,IF((ISBLANK(B24)),0,(M24)),"0") -> 0 | AD24: =IF(MONTH(A24)=7,IF((ISBLANK(C24)),0,(M24)),"0") -> 0 | AE24: =IF(MONTH(A24)=8,IF((ISBLANK(B24)),0,(M24)),"0") -> 0 | AF24: =IF(MONTH(A24)=8,IF((ISBLANK(C24)),0,(M24)),"0") -> 0 | AG24: =IF(MONTH(A24)=9,IF((ISBLANK(B24)),0,(M24)),"0") -> 0 | AH24: =IF(MONTH(A24)=9,IF((ISBLANK(C24)),0,(M24)),"0") -> 0 | AI24: =IF(MONTH(A24)=10,IF((ISBLANK(B24)),0,(M24)),"0") -> 0 | AJ24: =IF(MONTH(A24)=10,IF((ISBLANK(C24)),0,(M24)),"0") -> 0 | AK24: =IF(MONTH(A24)=11,IF((ISBLANK(B24)),0,(M24)),"0") -> 0 | AL24: =IF(MONTH(A24)=11,IF((ISBLANK(C24)),0,(M24)),"0") -> 0 | AM24: =IF(MONTH(A24)=12,IF((ISBLANK(B24)),0,(M24)),"0") -> 0 | AN24: =IF(MONTH(A24)=12,IF((ISBLANK(C24)),0,(M24)),"0") -> 0
K25: =IF(ISBLANK(A25),"",(I25*J25)) | M25: =IF((ISBLANK(A25)),"",'Fee calc_closed Transactions'!F25) | N25: =IF(K25="","",'Fee calc_closed Transactions'!G25) | P25: =IF(ISBLANK(A25),"0",I25) -> 0 | Q25: =IF(MONTH(A25)=1,IF((ISBLANK(B25)),0,(M25)),"0") -> 0 | R25: =IF(MONTH(A25)=1,IF((ISBLANK(C25)),0,(M25)),"0") -> 0 | S25: =IF(MONTH(A25)=2,IF((ISBLANK(B25)),0,(M25)),"0") -> 0 | T25: =IF(MONTH(A25)=2,IF((ISBLANK(C25)),0,(M25)),"0") -> 0 | U25: =IF(MONTH(A25)=3,IF((ISBLANK(B25)),0,(M25)),"0") -> 0 | V25: =IF(MONTH(A25)=3,IF((ISBLANK(C25)),0,(M25)),"0") -> 0 | W25: =IF(MONTH(A25)=4,IF((ISBLANK(B25)),0,(M25)),"0") -> 0 | X25: =IF(MONTH(A25)=4,IF((ISBLANK(C25)),0,(M25)),"0") -> 0 | Y25: =IF(MONTH(A25)=5,IF((ISBLANK(B25)),0,(M25)),"0") -> 0 | Z25: =IF(MONTH(A25)=5,IF((ISBLANK(C25)),0,(M25)),"0") -> 0 | AA25: =IF(MONTH(A25)=6,IF((ISBLANK(B25)),0,(M25)),"0") -> 0 | AB25: =IF(MONTH(A25)=6,IF((ISBLANK(C25)),0,(M25)),"0") -> 0 | AC25: =IF(MONTH(A25)=7,IF((ISBLANK(B25)),0,(M25)),"0") -> 0 | AD25: =IF(MONTH(A25)=7,IF((ISBLANK(C25)),0,(M25)),"0") -> 0 | AE25: =IF(MONTH(A25)=8,IF((ISBLANK(B25)),0,(M25)),"0") -> 0 | AF25: =IF(MONTH(A25)=8,IF((ISBLANK(C25)),0,(M25)),"0") -> 0 | AG25: =IF(MONTH(A25)=9,IF((ISBLANK(B25)),0,(M25)),"0") -> 0 | AH25: =IF(MONTH(A25)=9,IF((ISBLANK(C25)),0,(M25)),"0") -> 0 | AI25: =IF(MONTH(A25)=10,IF((ISBLANK(B25)),0,(M25)),"0") -> 0 | AJ25: =IF(MONTH(A25)=10,IF((ISBLANK(C25)),0,(M25)),"0") -> 0 | AK25: =IF(MONTH(A25)=11,IF((ISBLANK(B25)),0,(M25)),"0") -> 0 | AL25: =IF(MONTH(A25)=11,IF((ISBLANK(C25)),0,(M25)),"0") -> 0 | AM25: =IF(MONTH(A25)=12,IF((ISBLANK(B25)),0,(M25)),"0") -> 0 | AN25: =IF(MONTH(A25)=12,IF((ISBLANK(C25)),0,(M25)),"0") -> 0
K26: =IF(ISBLANK(A26),"",(I26*J26)) | M26: =IF((ISBLANK(A26)),"",'Fee calc_closed Transactions'!F26) | N26: =IF(K26="","",'Fee calc_closed Transactions'!G26) | P26: =IF(ISBLANK(A26),"0",I26) -> 0 | Q26: =IF(MONTH(A26)=1,IF((ISBLANK(B26)),0,(M26)),"0") -> 0 | R26: =IF(MONTH(A26)=1,IF((ISBLANK(C26)),0,(M26)),"0") -> 0 | S26: =IF(MONTH(A26)=2,IF((ISBLANK(B26)),0,(M26)),"0") -> 0 | T26: =IF(MONTH(A26)=2,IF((ISBLANK(C26)),0,(M26)),"0") -> 0 | U26: =IF(MONTH(A26)=3,IF((ISBLANK(B26)),0,(M26)),"0") -> 0 | V26: =IF(MONTH(A26)=3,IF((ISBLANK(C26)),0,(M26)),"0") -> 0 | W26: =IF(MONTH(A26)=4,IF((ISBLANK(B26)),0,(M26)),"0") -> 0 | X26: =IF(MONTH(A26)=4,IF((ISBLANK(C26)),0,(M26)),"0") -> 0 | Y26: =IF(MONTH(A26)=5,IF((ISBLANK(B26)),0,(M26)),"0") -> 0 | Z26: =IF(MONTH(A26)=5,IF((ISBLANK(C26)),0,(M26)),"0") -> 0 | AA26: =IF(MONTH(A26)=6,IF((ISBLANK(B26)),0,(M26)),"0") -> 0 | AB26: =IF(MONTH(A26)=6,IF((ISBLANK(C26)),0,(M26)),"0") -> 0 | AC26: =IF(MONTH(A26)=7,IF((ISBLANK(B26)),0,(M26)),"0") -> 0 | AD26: =IF(MONTH(A26)=7,IF((ISBLANK(C26)),0,(M26)),"0") -> 0 | AE26: =IF(MONTH(A26)=8,IF((ISBLANK(B26)),0,(M26)),"0") -> 0 | AF26: =IF(MONTH(A26)=8,IF((ISBLANK(C26)),0,(M26)),"0") -> 0 | AG26: =IF(MONTH(A26)=9,IF((ISBLANK(B26)),0,(M26)),"0") -> 0 | AH26: =IF(MONTH(A26)=9,IF((ISBLANK(C26)),0,(M26)),"0") -> 0 | AI26: =IF(MONTH(A26)=10,IF((ISBLANK(B26)),0,(M26)),"0") -> 0 | AJ26: =IF(MONTH(A26)=10,IF((ISBLANK(C26)),0,(M26)),"0") -> 0 | AK26: =IF(MONTH(A26)=11,IF((ISBLANK(B26)),0,(M26)),"0") -> 0 | AL26: =IF(MONTH(A26)=11,IF((ISBLANK(C26)),0,(M26)),"0") -> 0 | AM26: =IF(MONTH(A26)=12,IF((ISBLANK(B26)),0,(M26)),"0") -> 0 | AN26: =IF(MONTH(A26)=12,IF((ISBLANK(C26)),0,(M26)),"0") -> 0
K27: =IF(ISBLANK(A27),"",(I27*J27)) | M27: =IF((ISBLANK(A27)),"",'Fee calc_closed Transactions'!F27) | N27: =IF(K27="","",'Fee calc_closed Transactions'!G27) | P27: =IF(ISBLANK(A27),"0",I27) -> 0 | Q27: =IF(MONTH(A27)=1,IF((ISBLANK(B27)),0,(M27)),"0") -> 0 | R27: =IF(MONTH(A27)=1,IF((ISBLANK(C27)),0,(M27)),"0") -> 0 | S27: =IF(MONTH(A27)=2,IF((ISBLANK(B27)),0,(M27)),"0") -> 0 | T27: =IF(MONTH(A27)=2,IF((ISBLANK(C27)),0,(M27)),"0") -> 0 | U27: =IF(MONTH(A27)=3,IF((ISBLANK(B27)),0,(M27)),"0") -> 0 | V27: =IF(MONTH(A27)=3,IF((ISBLANK(C27)),0,(M27)),"0") -> 0 | W27: =IF(MONTH(A27)=4,IF((ISBLANK(B27)),0,(M27)),"0") -> 0 | X27: =IF(MONTH(A27)=4,IF((ISBLANK(C27)),0,(M27)),"0") -> 0 | Y27: =IF(MONTH(A27)=5,IF((ISBLANK(B27)),0,(M27)),"0") -> 0 | Z27: =IF(MONTH(A27)=5,IF((ISBLANK(C27)),0,(M27)),"0") -> 0 | AA27: =IF(MONTH(A27)=6,IF((ISBLANK(B27)),0,(M27)),"0") -> 0 | AB27: =IF(MONTH(A27)=6,IF((ISBLANK(C27)),0,(M27)),"0") -> 0 | AC27: =IF(MONTH(A27)=7,IF((ISBLANK(B27)),0,(M27)),"0") -> 0 | AD27: =IF(MONTH(A27)=7,IF((ISBLANK(C27)),0,(M27)),"0") -> 0 | AE27: =IF(MONTH(A27)=8,IF((ISBLANK(B27)),0,(M27)),"0") -> 0 | AF27: =IF(MONTH(A27)=8,IF((ISBLANK(C27)),0,(M27)),"0") -> 0 | AG27: =IF(MONTH(A27)=9,IF((ISBLANK(B27)),0,(M27)),"0") -> 0 | AH27: =IF(MONTH(A27)=9,IF((ISBLANK(C27)),0,(M27)),"0") -> 0 | AI27: =IF(MONTH(A27)=10,IF((ISBLANK(B27)),0,(M27)),"0") -> 0 | AJ27: =IF(MONTH(A27)=10,IF((ISBLANK(C27)),0,(M27)),"0") -> 0 | AK27: =IF(MONTH(A27)=11,IF((ISBLANK(B27)),0,(M27)),"0") -> 0 | AL27: =IF(MONTH(A27)=11,IF((ISBLANK(C27)),0,(M27)),"0") -> 0 | AM27: =IF(MONTH(A27)=12,IF((ISBLANK(B27)),0,(M27)),"0") -> 0 | AN27: =IF(MONTH(A27)=12,IF((ISBLANK(C27)),0,(M27)),"0") -> 0
K28: =IF(ISBLANK(A28),"",(I28*J28)) | M28: =IF((ISBLANK(A28)),"",'Fee calc_closed Transactions'!F28) | N28: =IF(K28="","",'Fee calc_closed Transactions'!G28) | P28: =IF(ISBLANK(A28),"0",I28) -> 0 | Q28: =IF(MONTH(A28)=1,IF((ISBLANK(B28)),0,(M28)),"0") -> 0 | R28: =IF(MONTH(A28)=1,IF((ISBLANK(C28)),0,(M28)),"0") -> 0 | S28: =IF(MONTH(A28)=2,IF((ISBLANK(B28)),0,(M28)),"0") -> 0 | T28: =IF(MONTH(A28)=2,IF((ISBLANK(C28)),0,(M28)),"0") -> 0 | U28: =IF(MONTH(A28)=3,IF((ISBLANK(B28)),0,(M28)),"0") -> 0 | V28: =IF(MONTH(A28)=3,IF((ISBLANK(C28)),0,(M28)),"0") -> 0 | W28: =IF(MONTH(A28)=4,IF((ISBLANK(B28)),0,(M28)),"0") -> 0 | X28: =IF(MONTH(A28)=4,IF((ISBLANK(C28)),0,(M28)),"0") -> 0 | Y28: =IF(MONTH(A28)=5,IF((ISBLANK(B28)),0,(M28)),"0") -> 0 | Z28: =IF(MONTH(A28)=5,IF((ISBLANK(C28)),0,(M28)),"0") -> 0 | AA28: =IF(MONTH(A28)=6,IF((ISBLANK(B28)),0,(M28)),"0") -> 0 | AB28: =IF(MONTH(A28)=6,IF((ISBLANK(C28)),0,(M28)),"0") -> 0 | AC28: =IF(MONTH(A28)=7,IF((ISBLANK(B28)),0,(M28)),"0") -> 0 | AD28: =IF(MONTH(A28)=7,IF((ISBLANK(C28)),0,(M28)),"0") -> 0 | AE28: =IF(MONTH(A28)=8,IF((ISBLANK(B28)),0,(M28)),"0") -> 0 | AF28: =IF(MONTH(A28)=8,IF((ISBLANK(C28)),0,(M28)),"0") -> 0 | AG28: =IF(MONTH(A28)=9,IF((ISBLANK(B28)),0,(M28)),"0") -> 0 | AH28: =IF(MONTH(A28)=9,IF((ISBLANK(C28)),0,(M28)),"0") -> 0 | AI28: =IF(MONTH(A28)=10,IF((ISBLANK(B28)),0,(M28)),"0") -> 0 | AJ28: =IF(MONTH(A28)=10,IF((ISBLANK(C28)),0,(M28)),"0") -> 0 | AK28: =IF(MONTH(A28)=11,IF((ISBLANK(B28)),0,(M28)),"0") -> 0 | AL28: =IF(MONTH(A28)=11,IF((ISBLANK(C28)),0,(M28)),"0") -> 0 | AM28: =IF(MONTH(A28)=12,IF((ISBLANK(B28)),0,(M28)),"0") -> 0 | AN28: =IF(MONTH(A28)=12,IF((ISBLANK(C28)),0,(M28)),"0") -> 0
K29: =IF(ISBLANK(A29),"",(I29*J29)) | M29: =IF((ISBLANK(A29)),"",'Fee calc_closed Transactions'!F29) | N29: =IF(K29="","",'Fee calc_closed Transactions'!G29) | P29: =IF(ISBLANK(A29),"0",I29) -> 0 | Q29: =IF(MONTH(A29)=1,IF((ISBLANK(B29)),0,(M29)),"0") -> 0 | R29: =IF(MONTH(A29)=1,IF((ISBLANK(C29)),0,(M29)),"0") -> 0 | S29: =IF(MONTH(A29)=2,IF((ISBLANK(B29)),0,(M29)),"0") -> 0 | T29: =IF(MONTH(A29)=2,IF((ISBLANK(C29)),0,(M29)),"0") -> 0 | U29: =IF(MONTH(A29)=3,IF((ISBLANK(B29)),0,(M29)),"0") -> 0 | V29: =IF(MONTH(A29)=3,IF((ISBLANK(C29)),0,(M29)),"0") -> 0 | W29: =IF(MONTH(A29)=4,IF((ISBLANK(B29)),0,(M29)),"0") -> 0 | X29: =IF(MONTH(A29)=4,IF((ISBLANK(C29)),0,(M29)),"0") -> 0 | Y29: =IF(MONTH(A29)=5,IF((ISBLANK(B29)),0,(M29)),"0") -> 0 | Z29: =IF(MONTH(A29)=5,IF((ISBLANK(C29)),0,(M29)),"0") -> 0 | AA29: =IF(MONTH(A29)=6,IF((ISBLANK(B29)),0,(M29)),"0") -> 0 | AB29: =IF(MONTH(A29)=6,IF((ISBLANK(C29)),0,(M29)),"0") -> 0 | AC29: =IF(MONTH(A29)=7,IF((ISBLANK(B29)),0,(M29)),"0") -> 0 | AD29: =IF(MONTH(A29)=7,IF((ISBLANK(C29)),0,(M29)),"0") -> 0 | AE29: =IF(MONTH(A29)=8,IF((ISBLANK(B29)),0,(M29)),"0") -> 0 | AF29: =IF(MONTH(A29)=8,IF((ISBLANK(C29)),0,(M29)),"0") -> 0 | AG29: =IF(MONTH(A29)=9,IF((ISBLANK(B29)),0,(M29)),"0") -> 0 | AH29: =IF(MONTH(A29)=9,IF((ISBLANK(C29)),0,(M29)),"0") -> 0 | AI29: =IF(MONTH(A29)=10,IF((ISBLANK(B29)),0,(M29)),"0") -> 0 | AJ29: =IF(MONTH(A29)=10,IF((ISBLANK(C29)),0,(M29)),"0") -> 0 | AK29: =IF(MONTH(A29)=11,IF((ISBLANK(B29)),0,(M29)),"0") -> 0 | AL29: =IF(MONTH(A29)=11,IF((ISBLANK(C29)),0,(M29)),"0") -> 0 | AM29: =IF(MONTH(A29)=12,IF((ISBLANK(B29)),0,(M29)),"0") -> 0 | AN29: =IF(MONTH(A29)=12,IF((ISBLANK(C29)),0,(M29)),"0") -> 0
K30: =IF(ISBLANK(A30),"",(I30*J30)) | M30: =IF((ISBLANK(A30)),"",'Fee calc_closed Transactions'!F30) | N30: =IF(K30="","",'Fee calc_closed Transactions'!G30) | P30: =IF(ISBLANK(A30),"0",I30) -> 0 | Q30: =IF(MONTH(A30)=1,IF((ISBLANK(B30)),0,(M30)),"0") -> 0 | R30: =IF(MONTH(A30)=1,IF((ISBLANK(C30)),0,(M30)),"0") -> 0 | S30: =IF(MONTH(A30)=2,IF((ISBLANK(B30)),0,(M30)),"0") -> 0 | T30: =IF(MONTH(A30)=2,IF((ISBLANK(C30)),0,(M30)),"0") -> 0 | U30: =IF(MONTH(A30)=3,IF((ISBLANK(B30)),0,(M30)),"0") -> 0 | V30: =IF(MONTH(A30)=3,IF((ISBLANK(C30)),0,(M30)),"0") -> 0 | W30: =IF(MONTH(A30)=4,IF((ISBLANK(B30)),0,(M30)),"0") -> 0 | X30: =IF(MONTH(A30)=4,IF((ISBLANK(C30)),0,(M30)),"0") -> 0 | Y30: =IF(MONTH(A30)=5,IF((ISBLANK(B30)),0,(M30)),"0") -> 0 | Z30: =IF(MONTH(A30)=5,IF((ISBLANK(C30)),0,(M30)),"0") -> 0 | AA30: =IF(MONTH(A30)=6,IF((ISBLANK(B30)),0,(M30)),"0") -> 0 | AB30: =IF(MONTH(A30)=6,IF((ISBLANK(C30)),0,(M30)),"0") -> 0 | AC30: =IF(MONTH(A30)=7,IF((ISBLANK(B30)),0,(M30)),"0") -> 0 | AD30: =IF(MONTH(A30)=7,IF((ISBLANK(C30)),0,(M30)),"0") -> 0 | AE30: =IF(MONTH(A30)=8,IF((ISBLANK(B30)),0,(M30)),"0") -> 0 | AF30: =IF(MONTH(A30)=8,IF((ISBLANK(C30)),0,(M30)),"0") -> 0 | AG30: =IF(MONTH(A30)=9,IF((ISBLANK(B30)),0,(M30)),"0") -> 0 | AH30: =IF(MONTH(A30)=9,IF((ISBLANK(C30)),0,(M30)),"0") -> 0 | AI30: =IF(MONTH(A30)=10,IF((ISBLANK(B30)),0,(M30)),"0") -> 0 | AJ30: =IF(MONTH(A30)=10,IF((ISBLANK(C30)),0,(M30)),"0") -> 0 | AK30: =IF(MONTH(A30)=11,IF((ISBLANK(B30)),0,(M30)),"0") -> 0 | AL30: =IF(MONTH(A30)=11,IF((ISBLANK(C30)),0,(M30)),"0") -> 0 | AM30: =IF(MONTH(A30)=12,IF((ISBLANK(B30)),0,(M30)),"0") -> 0 | AN30: =IF(MONTH(A30)=12,IF((ISBLANK(C30)),0,(M30)),"0") -> 0
K31: =IF(ISBLANK(A31),"",(I31*J31)) | M31: =IF((ISBLANK(A31)),"",'Fee calc_closed Transactions'!F31) | N31: =IF(K31="","",'Fee calc_closed Transactions'!G31) | P31: =IF(ISBLANK(A31),"0",I31) -> 0 | Q31: =IF(MONTH(A31)=1,IF((ISBLANK(B31)),0,(M31)),"0") -> 0 | R31: =IF(MONTH(A31)=1,IF((ISBLANK(C31)),0,(M31)),"0") -> 0 | S31: =IF(MONTH(A31)=2,IF((ISBLANK(B31)),0,(M31)),"0") -> 0 | T31: =IF(MONTH(A31)=2,IF((ISBLANK(C31)),0,(M31)),"0") -> 0 | U31: =IF(MONTH(A31)=3,IF((ISBLANK(B31)),0,(M31)),"0") -> 0 | V31: =IF(MONTH(A31)=3,IF((ISBLANK(C31)),0,(M31)),"0") -> 0 | W31: =IF(MONTH(A31)=4,IF((ISBLANK(B31)),0,(M31)),"0") -> 0 | X31: =IF(MONTH(A31)=4,IF((ISBLANK(C31)),0,(M31)),"0") -> 0 | Y31: =IF(MONTH(A31)=5,IF((ISBLANK(B31)),0,(M31)),"0") -> 0 | Z31: =IF(MONTH(A31)=5,IF((ISBLANK(C31)),0,(M31)),"0") -> 0 | AA31: =IF(MONTH(A31)=6,IF((ISBLANK(B31)),0,(M31)),"0") -> 0 | AB31: =IF(MONTH(A31)=6,IF((ISBLANK(C31)),0,(M31)),"0") -> 0 | AC31: =IF(MONTH(A31)=7,IF((ISBLANK(B31)),0,(M31)),"0") -> 0 | AD31: =IF(MONTH(A31)=7,IF((ISBLANK(C31)),0,(M31)),"0") -> 0 | AE31: =IF(MONTH(A31)=8,IF((ISBLANK(B31)),0,(M31)),"0") -> 0 | AF31: =IF(MONTH(A31)=8,IF((ISBLANK(C31)),0,(M31)),"0") -> 0 | AG31: =IF(MONTH(A31)=9,IF((ISBLANK(B31)),0,(M31)),"0") -> 0 | AH31: =IF(MONTH(A31)=9,IF((ISBLANK(C31)),0,(M31)),"0") -> 0 | AI31: =IF(MONTH(A31)=10,IF((ISBLANK(B31)),0,(M31)),"0") -> 0 | AJ31: =IF(MONTH(A31)=10,IF((ISBLANK(C31)),0,(M31)),"0") -> 0 | AK31: =IF(MONTH(A31)=11,IF((ISBLANK(B31)),0,(M31)),"0") -> 0 | AL31: =IF(MONTH(A31)=11,IF((ISBLANK(C31)),0,(M31)),"0") -> 0 | AM31: =IF(MONTH(A31)=12,IF((ISBLANK(B31)),0,(M31)),"0") -> 0 | AN31: =IF(MONTH(A31)=12,IF((ISBLANK(C31)),0,(M31)),"0") -> 0
... K64: =IF(ISBLANK(A64),"",(I64*J64)) | M64: =IF((ISBLANK(A64)),"",'Fee calc_closed Transactions'!F64) | N64: =IF(K64="","",'Fee calc_closed Transactions'!G64) | P64: =IF(ISBLANK(A64),"0",I64) -> 0 | Q64: =IF(MONTH(A64)=1,IF((ISBLANK(B64)),0,(M64)),"0") -> 0 | R64: =IF(MONTH(A64)=1,IF((ISBLANK(C64)),0,(M64)),"0") -> 0 | S64: =IF(MONTH(A64)=2,IF((ISBLANK(B64)),0,(M64)),"0") -> 0 | T64: =IF(MONTH(A64)=2,IF((ISBLANK(C64)),0,(M64)),"0") -> 0 | U64: =IF(MONTH(A64)=3,IF((ISBLANK(B64)),0,(M64)),"0") -> 0 | V64: =IF(MONTH(A64)=3,IF((ISBLANK(C64)),0,(M64)),"0") -> 0 | W64: =IF(MONTH(A64)=4,IF((ISBLANK(B64)),0,(M64)),"0") -> 0 | X64: =IF(MONTH(A64)=4,IF((ISBLANK(C64)),0,(M64)),"0") -> 0 | Y64: =IF(MONTH(A64)=5,IF((ISBLANK(B64)),0,(M64)),"0") -> 0 | Z64: =IF(MONTH(A64)=5,IF((ISBLANK(C64)),0,(M64)),"0") -> 0 | AA64: =IF(MONTH(A64)=6,IF((ISBLANK(B64)),0,(M64)),"0") -> 0 | AB64: =IF(MONTH(A64)=6,IF((ISBLANK(C64)),0,(M64)),"0") -> 0 | AC64: =IF(MONTH(A64)=7,IF((ISBLANK(B64)),0,(M64)),"0") -> 0 | AD64: =IF(MONTH(A64)=7,IF((ISBLANK(C64)),0,(M64)),"0") -> 0 | AE64: =IF(MONTH(A64)=8,IF((ISBLANK(B64)),0,(M64)),"0") -> 0 | AF64: =IF(MONTH(A64)=8,IF((ISBLANK(C64)),0,(M64)),"0") -> 0 | AG64: =IF(MONTH(A64)=9,IF((ISBLANK(B64)),0,(M64)),"0") -> 0 | AH64: =IF(MONTH(A64)=9,IF((ISBLANK(C64)),0,(M64)),"0") -> 0 | AI64: =IF(MONTH(A64)=10,IF((ISBLANK(B64)),0,(M64)),"0") -> 0 | AJ64: =IF(MONTH(A64)=10,IF((ISBLANK(C64)),0,(M64)),"0") -> 0 | AK64: =IF(MONTH(A64)=11,IF((ISBLANK(B64)),0,(M64)),"0") -> 0 | AL64: =IF(MONTH(A64)=11,IF((ISBLANK(C64)),0,(M64)),"0") -> 0 | AM64: =IF(MONTH(A64)=12,IF((ISBLANK(B64)),0,(M64)),"0") -> 0 | AN64: =IF(MONTH(A64)=12,IF((ISBLANK(C64)),0,(M64)),"0") -> 0
A65: =DCOUNT(A2:A64,"coe",A9:A10) -> 17 | B65: =SUM(B3:B64) -> 12 | C65: =SUM(C3:C64) -> 8 | E65: =DCOUNTA(E2:E64,E2,E2:E11) -> 1 | F65: Referral-to- Past Client Ratio: | G65: =IF(A65=0,0,E65/A65) -> 0.058823529 | Q65: Buy | R65: Sell | S65: Buy | T65: Sell | U65: Buy | V65: Sell | W65: Buy | X65: Sell | Y65: Buy | Z65: Sell | AA65: Buy | AB65: Sell | AC65: Buy | AD65: Sell | AE65: Buy | AF65: Sell | AG65: Buy | AH65: Sell | AI65: Buy | AJ65: Sell | AK65: Buy | AL65: Sell | AM65: Buy | AN65: Sell
B66: B:S | C66: =B65&":"&C65 -> 12:8 | F66: Seller Ratio | G66: =IF(A65=0,0,C65/A65) -> 0.47058824 | H66: =SUM(H3:H64) -> 5516605 | I66: =SUM(I3:I64) -> 5901765 | J66: =IF(J3=0,0,AVERAGE(J3:J64)) -> 0.17032724 | K66: =SUM(K3:K64) -> 119176.25 | L66: =COUNT(L3:L64) -> 6 | M66: =SUM(M3:M64) -> 94220.476 | N66: =SUM(N3:N64) -> 21583.025 | P66: =SUM(P9:P64) -> 2820220 | Q66: =SUM(Q3:Q64) -> 10370 | R66: =SUM(R3:R64) -> 0 | S66: =SUM(S3:S64) -> 6880 | T66: =SUM(T3:T64) -> 0 | U66: =SUM(U3:U64) -> 2472.225 | V66: =SUM(V3:V64) -> 1909.1 | W66: =SUM(W3:W64) -> 19125 | X66: =SUM(X3:X64) -> 33150 | ... AN66: =SUM(AN3:AN64) -> 0
O68: For Projected Chart | P68: Running Monthly Income | Q68: =SUM(Q66,R66) -> 10370 | S68: =SUM(S66,T66)+Q68 -> 17250 | U68: =SUM(U66,V66)+S68 -> 21631.325 | W68: =SUM(W66,X66)+U68 -> 73906.325 | Y68: =SUM(Y66,Z66)+W68 -> 73906.325 | AA68: =SUM(AA66,AB66)+Y68 -> 78878.825 | AC68: =SUM(AC66,AD66)+AA68 -> 83425.263 | AE68: =SUM(AE66,AF66)+AC68 -> 87626.388 | AG68: =SUM(AG66,AH66)+AE68 -> 100716.39 | AI68: =SUM(AI66,AJ66)+AG68 -> 100716.39 | AK68: =SUM(AK66,AL66)+AI68 -> 100716.39 | AM68: =SUM(AM66,AN66)+AK68 -> 100716.39
P69: Projected | Q69: 8333 | S69: =Q69+Budget!F4/12 -> 24999.667 | U69: =S69+Budget!F4/12 -> 41666.333 | W69: =U69+Budget!F4/12 -> 58333 | Y69: =W69+Budget!F4/12 -> 74999.667 | AA69: =Y69+Budget!F4/12 -> 91666.333 | AC69: =AA69+Budget!F4/12 -> 108333 | AE69: =AC69+Budget!F4/12 -> 124999.67 | AG69: =AE69+Budget!F4/12 -> 141666.33 | AI69: =AG69+Budget!F4/12 -> 158333 | AK69: =AI69+Budget!F4/12 -> 174999.67 | AM69: =AK69+Budget!F4/12 -> 191666.33

Sheet YTD Summary
B1: This sheet is a visual of your year to date.
B2: Gross Commission Goal | C2: ='Goals & Fees'!$L$4 -> 200000
B3: GCI YTD | C3: ='Closed Transactions'!K66 -> 119176.25 | F3: Commission Performance | G3: =C3/C2 -> 0.59588125 | H3: =IF(G3>100%,-1%,1-G3) -> 0.40411875
B4: Agent Net Income To Date Based on Closed Transactions (Commissions after referral fees, office split, franchise fees) | C4: ='Closed Transactions'!M66 -> 94220.476
B6: Total Number of Sides Year To Date (Based on Closed Transactions) | C6: ='Closed Transactions'!B65+'Closed Transactions'!C65 -> 20
B8: Total Sales Volume To Date (Based on Closed Transactions) | C8: ='Closed Transactions'!I66 -> 5901765
B10: Estimated Potential Gross Commission Income Business Tracker: (U/C + Hot List) | C10: ='Business Tracker'!O68+'Business Tracker'!W68 -> 254250
B12: Closed Transactions from Agent Referrals (Based on Closed Transactions) | C12: ='Closed Transactions'!L66 -> 6
B14: Number of Buying Sides to Listing Sides (Based on Closed Transactions data) | C14: ='Closed Transactions'!C66 -> 12:8
E15: Marketing paid to date: | H15: Franchise fee paid to date: | K15: Office fee paid to date:
E16: ='Fee calc_closed Transactions'!A10 -> 0 | H16: ='Fee calc_closed Transactions'!A6 -> 0 | K16: ='Fee calc_closed Transactions'!A15 -> 21583.025

Sheet PIE Tracker
B1: Enter T, I, P time spent for each day that you work. E is auto-calculated.
A2: January | H2: February | O2: March | W2: Insert month name in Blue cell for a PIE evaluation. | AC2: To be hidden. | AE2: Still need to test daily fill for the year
A3: Date | B3: Day | C3: T | D3: I | E3: P | F3: E | H3: Date | I3: Day | J3: T | K3: I | L3: P | M3: E | O3: Date | P3: Day | Q3: T | R3: I | S3: P | T3: E | W3: Month: | X3: February | Y3: Total Days: | Z3: =VLOOKUP(X3,'PIE Tracker'!$AC$4:$AH$15,6,FALSE) -> 27 | AC3: Monthly Totals | AD3: T | AE3: I | AF3: P | AG3: E | AH3: Days worked
A4: =DATEVALUE(CONCATENATE("1/1/",Budget!$A$1)) -> 45658 | B4: =IF(A4<>"",WEEKDAY(A4,1),"") -> 4 | C4: 4 | D4: 0.25 | E4: 1.5 | F4: =IF(C4="", " ",C4-D4-E4) -> 2.25 | H4: =DATEVALUE(CONCATENATE("2/1/",Budget!$A$1)) -> 45689 | I4: =IF(H4<>"",WEEKDAY(H4,1),"") -> 7 | J4: 0.5 | K4: 0.5 | L4: 0 | M4: =IF(J4="", " ",J4-K4-L4) -> 0 | O4: =DATEVALUE(CONCATENATE("3/1/",Budget!$A$1)) -> 45717 | P4: =IF(O4<>"",WEEKDAY(O4,1),"") -> 7 | Q4: 2 | R4: 1 | S4: 0 | T4: =IF(Q4="", " ",Q4-R4-S4) -> 1 | AC4: January | AD4: =SUM(C4:C34) -> 228.58333 | AE4: =SUM(D4:D34) -> 61.24 | AF4: =SUM(E4:E34) -> 23.75 | AG4: =SUM(F4:F34) -> 143.59333 | AH4: =COUNTIF(C4:C34,">0") -> 31
A5: =A4+1 -> 45659 | B5: =IF(A5<>"",WEEKDAY(A5,1),"") -> 5 | C5: 5 | D5: 0.25 | E5: 1.25 | F5: =IF(C5="", " ",C5-D5-E5) -> 3.5 | H5: =H4+1 -> 45690 | I5: =IF(H5<>"",WEEKDAY(H5,1),"") -> 1 | J5: 3 | K5: 1 | L5: 0 | M5: =IF(J5="", " ",J5-K5-L5) -> 2 | O5: =O4+1 -> 45718 | P5: =IF(O5<>"",WEEKDAY(O5,1),"") -> 1 | Q5: 0 | R5: 0 | S5: 0 | T5: =IF(Q5="", " ",Q5-R5-S5) -> 0 | AC5: February | AD5: =SUM(J4:J34) -> 205.5 | AE5: =SUM(K4:K34) -> 53.25 | AF5: =SUM(L4:L34) -> 8.5 | AG5: =SUM(M4:M34) -> 143.75 | AH5: =COUNTIF(J4:J34,">0") -> 27
A6: =A5+1 -> 45660 | B6: =IF(A6<>"",WEEKDAY(A6,1),"") -> 6 | C6: 9 | D6: 3.5 | E6: 0 | F6: =IF(C6="", " ",C6-D6-E6) -> 5.5 | H6: =H5+1 -> 45691 | I6: =IF(H6<>"",WEEKDAY(H6,1),"") -> 2 | J6: 8.5 | K6: 3.5 | L6: 0 | M6: =IF(J6="", " ",J6-K6-L6) -> 5 | O6: =O5+1 -> 45719 | P6: =IF(O6<>"",WEEKDAY(O6,1),"") -> 2 | Q6: 8 | R6: 2 | S6: 0 | T6: =IF(Q6="", " ",Q6-R6-S6) -> 6 | W6: Total Hrs | X6: Total "I" Hrs | Y6: Total "P" Hrs | Z6: Total "E" Hrs | AC6: March | AD6: =SUM(Q4:Q34) -> 216.83 | AE6: =SUM(R4:R34) -> 66.75 | AF6: =SUM(S4:S34) -> 21.75 | AG6: =SUM(T4:T34) -> 128.33 | AH6: =COUNTIF(Q4:Q34,">0") -> 29
A7: =A6+1 -> 45661 | B7: =IF(A7<>"",WEEKDAY(A7,1),"") -> 7 | C7: 3 | D7: 2 | E7: 0 | F7: =IF(C7="", " ",C7-D7-E7) -> 1 | H7: =H6+1 -> 45692 | I7: =IF(H7<>"",WEEKDAY(H7,1),"") -> 3 | J7: 7.5 | K7: 1.75 | L7: 0.5 | M7: =IF(J7="", " ",J7-K7-L7) -> 5.25 | O7: =O6+1 -> 45720 | P7: =IF(O7<>"",WEEKDAY(O7,1),"") -> 3 | Q7: 7 | R7: 1 | S7: 0 | T7: =IF(Q7="", " ",Q7-R7-S7) -> 6 | W7: =IFERROR(VLOOKUP(X3,'PIE Tracker'!$AC$4:$AG$15,2,FALSE),"Is the month spelled correctly in cell M1?") -> 205.5 | X7: =IFERROR(VLOOKUP(X3,'PIE Tracker'!$AC$4:$AG$15,3,FALSE),"Is the month spelled correctly in cell M1?") -> 53.25 | Y7: =IFERROR(VLOOKUP(X3,'PIE Tracker'!$AC$4:$AG$15,4,FALSE),"Is the month spelled correctly in cell M1?") -> 8.5 | Z7: =IFERROR(VLOOKUP(X3,'PIE Tracker'!$AC$4:$AG$15,5,FALSE),"Is the month spelled correctly in cell M1?") -> 143.75 | AC7: April | AD7: =SUM(C39:C68) -> 166 | AE7: =SUM(D39:D68) -> 50.25 | AF7: =SUM(E39:E68) -> 7.5 | AG7: =SUM(F39:F68) -> 108.25 | AH7: =COUNTIF(C39:C68,">0") -> 28
A8: =A7+1 -> 45662 | B8: =IF(A8<>"",WEEKDAY(A8,1),"") -> 1 | C8: 2.5 | D8: 2.5 | E8: 0 | F8: =IF(C8="", " ",C8-D8-E8) -> 0 | H8: =H7+1 -> 45693 | I8: =IF(H8<>"",WEEKDAY(H8,1),"") -> 4 | J8: 13 | K8: 4.5 | L8: 0 | M8: =IF(J8="", " ",J8-K8-L8) -> 8.5 | O8: =O7+1 -> 45721 | P8: =IF(O8<>"",WEEKDAY(O8,1),"") -> 4 | Q8: 12 | R8: 5 | S8: 0 | T8: =IF(Q8="", " ",Q8-R8-S8) -> 7 | AC8: May | AD8: =SUM(J39:J69) -> 164.75 | AE8: =SUM(K39:K69) -> 57.25 | AF8: =SUM(L39:L69) -> 6.25 | AG8: =SUM(M39:M69) -> 101.25 | AH8: =COUNTIF(J39:J69,">0") -> 29
A9: =A8+1 -> 45663 | B9: =IF(A9<>"",WEEKDAY(A9,1),"") -> 2 | C9: 7 | D9: 1 | E9: 0.75 | F9: =IF(C9="", " ",C9-D9-E9) -> 5.25 | H9: =H8+1 -> 45694 | I9: =IF(H9<>"",WEEKDAY(H9,1),"") -> 5 | J9: 10.5 | K9: 0.5 | L9: 0 | M9: =IF(J9="", " ",J9-K9-L9) -> 10 | O9: =O8+1 -> 45722 | P9: =IF(O9<>"",WEEKDAY(O9,1),"") -> 5 | Q9: 11 | R9: 2 | S9: 3.75 | T9: =IF(Q9="", " ",Q9-R9-S9) -> 5.25 | AC9: June | AD9: =SUM(Q39:Q68) -> 110.5 | AE9: =SUM(R39:R68) -> 35.25 | AF9: =SUM(S39:S68) -> 3.25 | AG9: =SUM(T39:T68) -> 72 | AH9: =COUNTIF(Q39:Q68,">0") -> 17
A10: =A9+1 -> 45664 | B10: =IF(A10<>"",WEEKDAY(A10,1),"") -> 3 | C10: 7.5 | D10: 2 | E10: 0 | F10: =IF(C10="", " ",C10-D10-E10) -> 5.5 | H10: =H9+1 -> 45695 | I10: =IF(H10<>"",WEEKDAY(H10,1),"") -> 6 | J10: 9 | K10: 3 | L10: 0 | M10: =IF(J10="", " ",J10-K10-L10) -> 6 | O10: =O9+1 -> 45723 | P10: =IF(O10<>"",WEEKDAY(O10,1),"") -> 6 | Q10: 2 | R10: 2 | S10: 0 | T10: =IF(Q10="", " ",Q10-R10-S10) -> 0 | X10: "I" Hrs % | Y10: "P" Hrs % | Z10: "E" Hrs % | AC10: July | AD10: =SUM(C74:C104) -> 186.75 | AE10: =SUM(D74:D104) -> 48.75 | AF10: =SUM(E74:E104) -> 11.5 | AG10: =SUM(F74:F104) -> 126.5 | AH10: =COUNTIF(C74:C104,">0") -> 24
A11: =A10+1 -> 45665 | B11: =IF(A11<>"",WEEKDAY(A11,1),"") -> 4 | C11: 11.33333 | D11: 5.24 | E11: 1 | F11: =IF(C11="", " ",C11-D11-E11) -> 5.09333 | H11: =H10+1 -> 45696 | I11: =IF(H11<>"",WEEKDAY(H11,1),"") -> 7 | J11: 10 | K11: 1 | L11: 5 | M11: =IF(J11="", " ",J11-K11-L11) -> 4 | O11: =O10+1 -> 45724 | P11: =IF(O11<>"",WEEKDAY(O11,1),"") -> 7 | Q11: 2 | R11: 2 | S11: 0 | T11: =IF(Q11="", " ",Q11-R11-S11) -> 0 | X11: =IF(W7=0,0,X7/W7) -> 0.25912409 | Y11: =IF(X7=0,0,Y7/W7) -> 0.04136253 | Z11: =IF(Y7=0,0,Z7/W7) -> 0.69951338 | AC11: August | AD11: =SUM(J74:J104) -> 186 | AE11: =SUM(K74:K104) -> 60 | AF11: =SUM(L74:L104) -> 4.5 | AG11: =SUM(M74:M104) -> 121.5 | AH11: =COUNTIF(J74:J104,">0") -> 31
A12: =A11+1 -> 45666 | B12: =IF(A12<>"",WEEKDAY(A12,1),"") -> 5 | C12: 11.5 | D12: 3.75 | E12: 0.5 | F12: =IF(C12="", " ",C12-D12-E12) -> 7.25 | H12: =H11+1 -> 45697 | I12: =IF(H12<>"",WEEKDAY(H12,1),"") -> 1 | J12: 1 | K12: 0.25 | L12: 0 | M12: =IF(J12="", " ",J12-K12-L12) -> 0.75 | O12: =O11+1 -> 45725 | P12: =IF(O12<>"",WEEKDAY(O12,1),"") -> 1 | Q12: 4 | R12: 1.5 | S12: 0 | T12: =IF(Q12="", " ",Q12-R12-S12) -> 2.5 | AC12: September | AD12: =SUM(Q74:Q103) -> 161 | AE12: =SUM(R74:R103) -> 44.5 | AF12: =SUM(S74:S103) -> 5 | AG12: =SUM(T74:T103) -> 111.5 | AH12: =COUNTIF(Q74:Q103,">0") -> 26
A13: =A12+1 -> 45667 | B13: =IF(A13<>"",WEEKDAY(A13,1),"") -> 6 | C13: 11 | D13: 2.5 | E13: 0.75 | F13: =IF(C13="", " ",C13-D13-E13) -> 7.75 | H13: =H12+1 -> 45698 | I13: =IF(H13<>"",WEEKDAY(H13,1),"") -> 2 | J13: 12 | K13: 4.5 | L13: 0 | M13: =IF(J13="", " ",J13-K13-L13) -> 7.5 | O13: =O12+1 -> 45726 | P13: =IF(O13<>"",WEEKDAY(O13,1),"") -> 2 | Q13: 7 | R13: 1 | S13: 0 | T13: =IF(Q13="", " ",Q13-R13-S13) -> 6 | AC13: October | AD13: =SUM(C109:C139) -> 172.3 | AE13: =SUM(D109:D139) -> 43.95 | AF13: =SUM(E109:E139) -> 3.25 | AG13: =SUM(F109:F139) -> 125.1 | AH13: =COUNTIF(C109:C139,">0") -> 27
A14: =A13+1 -> 45668 | B14: =IF(A14<>"",WEEKDAY(A14,1),"") -> 7 | C14: 4.5 | D14: 4.5 | E14: 0 | F14: =IF(C14="", " ",C14-D14-E14) -> 0 | H14: =H13+1 -> 45699 | I14: =IF(H14<>"",WEEKDAY(H14,1),"") -> 3 | J14: 8 | K14: 0.75 | L14: 0 | M14: =IF(J14="", " ",J14-K14-L14) -> 7.25 | O14: =O13+1 -> 45727 | P14: =IF(O14<>"",WEEKDAY(O14,1),"") -> 3 | Q14: 6 | R14: 2.75 | S14: 0 | T14: =IF(Q14="", " ",Q14-R14-S14) -> 3.25 | W14: Avg. Hrs | X14: Avg. "I" | Y14: Avg. "P" | Z14: Avg. "E" | AC14: November | AD14: =SUM(J109:J138) -> 106.75 | AE14: =SUM(K109:K138) -> 28.75 | AF14: =SUM(L109:L138) -> 4 | AG14: =SUM(M109:M138) -> #REF! | AH14: =COUNTIF(J109:J138,">0") -> 16
A15: =A14+1 -> 45669 | B15: =IF(A15<>"",WEEKDAY(A15,1),"") -> 1 | C15: 4.5 | D15: 1 | E15: 2.5 | F15: =IF(C15="", " ",C15-D15-E15) -> 1 | H15: =H14+1 -> 45700 | I15: =IF(H15<>"",WEEKDAY(H15,1),"") -> 4 | J15: 11.5 | K15: 1.5 | L15: 1 | M15: =IF(J15="", " ",J15-K15-L15) -> 9 | O15: =O14+1 -> 45728 | P15: =IF(O15<>"",WEEKDAY(O15,1),"") -> 4 | Q15: 9.33 | R15: 3 | S15: 0 | T15: =IF(Q15="", " ",Q15-R15-S15) -> 6.33 | W15: Per Day | X15: Hrs/Day | Y15: Hrs/Day | Z15: Hrs/Day | AC15: December | AD15: =SUM(Q109:Q139) -> 86.25 | AE15: =SUM(R109:R139) -> 26.75 | AF15: =SUM(S109:S139) -> 1.25 | AG15: =SUM(T109:T139) -> 58.25 | AH15: =COUNTIF(Q109:Q139,">0") -> 11
A16: =A15+1 -> 45670 | B16: =IF(A16<>"",WEEKDAY(A16,1),"") -> 2 | C16: 8 | D16: 2 | E16: 1 | F16: =IF(C16="", " ",C16-D16-E16) -> 5 | H16: =H15+1 -> 45701 | I16: =IF(H16<>"",WEEKDAY(H16,1),"") -> 5 | J16: 8 | K16: 2 | L16: 0 | M16: =IF(J16="", " ",J16-K16-L16) -> 6 | O16: =O15+1 -> 45729 | P16: =IF(O16<>"",WEEKDAY(O16,1),"") -> 5 | Q16: 11 | R16: 1.75 | S16: 0 | T16: =IF(Q16="", " ",Q16-R16-S16) -> 9.25 | W16: =IF(W7=0,0,W7/Z3) -> 7.6111111 | X16: =IF(X7=0,0,X7/Z3) -> 1.9722222 | Y16: =IF(Y7=0,0,Y7/Z3) -> 0.31481481 | Z16: =(W16)*(Z11) -> 5.3240741
A17: =A16+1 -> 45671 | B17: =IF(A17<>"",WEEKDAY(A17,1),"") -> 3 | C17: 8 | D17: 1.5 | E17: 0.5 | F17: =IF(C17="", " ",C17-D17-E17) -> 6 | H17: =H16+1 -> 45702 | I17: =IF(H17<>"",WEEKDAY(H17,1),"") -> 6 | J17: 7 | K17: 1 | L17: 0 | M17: =IF(J17="", " ",J17-K17-L17) -> 6 | O17: =O16+1 -> 45730 | P17: =IF(O17<>"",WEEKDAY(O17,1),"") -> 6 | Q17: 7.5 | R17: 2.25 | S17: 0.75 | T17: =IF(Q17="", " ",Q17-R17-S17) -> 4.5 | X17: Hourly Yield Ratio
A18: =A17+1 -> 45672 | B18: =IF(A18<>"",WEEKDAY(A18,1),"") -> 4 | C18: 13.5 | D18: 4 | E18: 1.75 | F18: =IF(C18="", " ",C18-D18-E18) -> 7.75 | H18: =H17+1 -> 45703 | I18: =IF(H18<>"",WEEKDAY(H18,1),"") -> 7 | J18: 0 | K18: 0 | L18: 0 | M18: =IF(J18="", " ",J18-K18-L18) -> 0 | O18: =O17+1 -> 45731 | P18: =IF(O18<>"",WEEKDAY(O18,1),"") -> 7 | Q18: 5 | R18: 2 | S18: 0 | T18: =IF(Q18="", " ",Q18-R18-S18) -> 3 | X18: =IF(W7=0,0,(X7)/(Y7)) -> 6.2647059 | Y18: to 1
A19: =A18+1 -> 45673 | B19: =IF(A19<>"",WEEKDAY(A19,1),"") -> 5 | C19: 13 | D19: 3.75 | E19: 1.5 | F19: =IF(C19="", " ",C19-D19-E19) -> 7.75 | H19: =H18+1 -> 45704 | I19: =IF(H19<>"",WEEKDAY(H19,1),"") -> 1 | J19: 4 | K19: 0 | L19: 0 | M19: =IF(J19="", " ",J19-K19-L19) -> 4 | O19: =O18+1 -> 45732 | P19: =IF(O19<>"",WEEKDAY(O19,1),"") -> 1 | Q19: 7 | R19: 2 | S19: 2 | T19: =IF(Q19="", " ",Q19-R19-S19) -> 3
A20: =A19+1 -> 45674 | B20: =IF(A20<>"",WEEKDAY(A20,1),"") -> 6 | C20: 8 | D20: 3.25 | E20: 0 | F20: =IF(C20="", " ",C20-D20-E20) -> 4.75 | H20: =H19+1 -> 45705 | I20: =IF(H20<>"",WEEKDAY(H20,1),"") -> 2 | J20: 4 | K20: 0 | L20: 0 | M20: =IF(J20="", " ",J20-K20-L20) -> 4 | O20: =O19+1 -> 45733 | P20: =IF(O20<>"",WEEKDAY(O20,1),"") -> 2 | Q20: 6 | R20: 1.5 | S20: 0 | T20: =IF(Q20="", " ",Q20-R20-S20) -> 4.5 | Y20: Under Contract for Next Month
A21: =A20+1 -> 45675 | B21: =IF(A21<>"",WEEKDAY(A21,1),"") -> 7 | C21: 4 | D21: 1 | E21: 0 | F21: =IF(C21="", " ",C21-D21-E21) -> 3 | H21: =H20+1 -> 45706 | I21: =IF(H21<>"",WEEKDAY(H21,1),"") -> 3 | J21: 11 | K21: 2 | L21: 0 | M21: =IF(J21="", " ",J21-K21-L21) -> 9 | O21: =O20+1 -> 45734 | P21: =IF(O21<>"",WEEKDAY(O21,1),"") -> 3 | Q21: 10 | R21: 2 | S21: 0 | T21: =IF(Q21="", " ",Q21-R21-S21) -> 8 | X21: =X3 -> February
A22: =A21+1 -> 45676 | B22: =IF(A22<>"",WEEKDAY(A22,1),"") -> 1 | C22: 7 | D22: 0.75 | E22: 4 | F22: =IF(C22="", " ",C22-D22-E22) -> 2.25 | H22: =H21+1 -> 45707 | I22: =IF(H22<>"",WEEKDAY(H22,1),"") -> 4 | J22: 13 | K22: 6.5 | L22: 0 | M22: =IF(J22="", " ",J22-K22-L22) -> 6.5 | O22: =O21+1 -> 45735 | P22: =IF(O22<>"",WEEKDAY(O22,1),"") -> 4 | Q22: 9 | R22: 3 | S22: 0.5 | T22: =IF(Q22="", " ",Q22-R22-S22) -> 5.5 | W22: Gross Income: | X22: =SUMIF('Business Tracker'!AA6:AA67,MONTH(DATEVALUE($X$3 &" 1")),'Business Tracker'!AF6:AF67) -> 10000 | Y22: =SUMIF('Business Tracker'!T6:T67,MONTH(DATEVALUE($X$3 &" 1"))+1,'Business Tracker'!W6:W67) -> 0
A23: =A22+1 -> 45677 | B23: =IF(A23<>"",WEEKDAY(A23,1),"") -> 2 | C23: 8 | D23: 0.5 | E23: 0 | F23: =IF(C23="", " ",C23-D23-E23) -> 7.5 | H23: =H22+1 -> 45708 | I23: =IF(H23<>"",WEEKDAY(H23,1),"") -> 5 | J23: 8 | K23: 4.5 | L23: 0 | M23: =IF(J23="", " ",J23-K23-L23) -> 3.5 | O23: =O22+1 -> 45736 | P23: =IF(O23<>"",WEEKDAY(O23,1),"") -> 5 | Q23: 11 | R23: 3 | S23: 1.5 | T23: =IF(Q23="", " ",Q23-R23-S23) -> 6.5 | W23: "P" time/hour: | X23: =IF(W7=0,0,X22/Y7) -> 1176.4706
A24: =A23+1 -> 45678 | B24: =IF(A24<>"",WEEKDAY(A24,1),"") -> 3 | C24: 9 | D24: 1 | E24: 1 | F24: =IF(C24="", " ",C24-D24-E24) -> 7 | H24: =H23+1 -> 45709 | I24: =IF(H24<>"",WEEKDAY(H24,1),"") -> 6 | J24: 12 | K24: 3.5 | L24: 0 | M24: =IF(J24="", " ",J24-K24-L24) -> 8.5 | O24: =O23+1 -> 45737 | P24: =IF(O24<>"",WEEKDAY(O24,1),"") -> 6 | Q24: 11 | R24: 2 | S24: 2.25 | T24: =IF(Q24="", " ",Q24-R24-S24) -> 6.75 | W24: "T" time/hour: | X24: =IF(W7=0,0,X22/W7) -> 48.6618
A25: =A24+1 -> 45679 | B25: =IF(A25<>"",WEEKDAY(A25,1),"") -> 4 | C25: 7 | D25: 1 | E25: 2.5 | F25: =IF(C25="", " ",C25-D25-E25) -> 3.5 | H25: =H24+1 -> 45710 | I25: =IF(H25<>"",WEEKDAY(H25,1),"") -> 7 | J25: 3 | K25: 1.5 | L25: 0 | M25: =IF(J25="", " ",J25-K25-L25) -> 1.5 | O25: =O24+1 -> 45738 | P25: =IF(O25<>"",WEEKDAY(O25,1),"") -> 7 | Q25: 4 | R25: 2 | S25: 0 | T25: =IF(Q25="", " ",Q25-R25-S25) -> 2
A26: =A25+1 -> 45680 | B26: =IF(A26<>"",WEEKDAY(A26,1),"") -> 5 | C26: 5.5 | D26: 0.5 | E26: 0.5 | F26: =IF(C26="", " ",C26-D26-E26) -> 4.5 | H26: =H25+1 -> 45711 | I26: =IF(H26<>"",WEEKDAY(H26,1),"") -> 1 | J26: 1 | K26: 0 | L26: 0 | M26: =IF(J26="", " ",J26-K26-L26) -> 1 | O26: =O25+1 -> 45739 | P26: =IF(O26<>"",WEEKDAY(O26,1),"") -> 1 | Q26: 6 | R26: 2 | S26: 2 | T26: =IF(Q26="", " ",Q26-R26-S26) -> 2
A27: =A26+1 -> 45681 | B27: =IF(A27<>"",WEEKDAY(A27,1),"") -> 6 | C27: 6 | D27: 1.5 | E27: 0 | F27: =IF(C27="", " ",C27-D27-E27) -> 4.5 | H27: =H26+1 -> 45712 | I27: =IF(H27<>"",WEEKDAY(H27,1),"") -> 2 | J27: 8 | K27: 2 | L27: 0 | M27: =IF(J27="", " ",J27-K27-L27) -> 6 | O27: =O26+1 -> 45740 | P27: =IF(O27<>"",WEEKDAY(O27,1),"") -> 2 | Q27: 6 | R27: 2 | S27: 0.5 | T27: =IF(Q27="", " ",Q27-R27-S27) -> 3.5
A28: =A27+1 -> 45682 | B28: =IF(A28<>"",WEEKDAY(A28,1),"") -> 7 | C28: 3 | D28: 2 | E28: 1 | F28: =IF(C28="", " ",C28-D28-E28) -> 0 | H28: =H27+1 -> 45713 | I28: =IF(H28<>"",WEEKDAY(H28,1),"") -> 3 | J28: 8 | K28: 2.5 | L28: 0 | M28: =IF(J28="", " ",J28-K28-L28) -> 5.5 | O28: =O27+1 -> 45741 | P28: =IF(O28<>"",WEEKDAY(O28,1),"") -> 3 | Q28: 6 | R28: 2 | S28: 2.5 | T28: =IF(Q28="", " ",Q28-R28-S28) -> 1.5
A29: =A28+1 -> 45683 | B29: =IF(A29<>"",WEEKDAY(A29,1),"") -> 1 | C29: 7 | D29: 1.5 | E29: 0 | F29: =IF(C29="", " ",C29-D29-E29) -> 5.5 | H29: =H28+1 -> 45714 | I29: =IF(H29<>"",WEEKDAY(H29,1),"") -> 4 | J29: 7 | K29: 1.5 | L29: 0 | M29: =IF(J29="", " ",J29-K29-L29) -> 5.5 | O29: =O28+1 -> 45742 | P29: =IF(O29<>"",WEEKDAY(O29,1),"") -> 4 | Q29: 13 | R29: 2.5 | S29: 5.5 | T29: =IF(Q29="", " ",Q29-R29-S29) -> 5
A30: =A29+1 -> 45684 | B30: =IF(A30<>"",WEEKDAY(A30,1),"") -> 2 | C30: 6 | D30: 2 | E30: 0.5 | F30: =IF(C30="", " ",C30-D30-E30) -> 3.5 | H30: =H29+1 -> 45715 | I30: =IF(H30<>"",WEEKDAY(H30,1),"") -> 5 | J30: 10 | K30: 2.5 | L30: 0 | M30: =IF(J30="", " ",J30-K30-L30) -> 7.5 | O30: =O29+1 -> 45743 | P30: =IF(O30<>"",WEEKDAY(O30,1),"") -> 5 | Q30: 11 | R30: 4.5 | S30: 0 | T30: =IF(Q30="", " ",Q30-R30-S30) -> 6.5
A31: =A30+1 -> 45685 | B31: =IF(A31<>"",WEEKDAY(A31,1),"") -> 3 | C31: 9.5 | D31: 2 | E31: 0.75 | F31: =IF(C31="", " ",C31-D31-E31) -> 6.75 | H31: =H30+1 -> 45716 | I31: =IF(H31<>"",WEEKDAY(H31,1),"") -> 6 | J31: 7 | K31: 1 | L31: 2 | M31: =IF(J31="", " ",J31-K31-L31) -> 4 | O31: =O30+1 -> 45744 | P31: =IF(O31<>"",WEEKDAY(O31,1),"") -> 6 | Q31: 5 | R31: 2.5 | S31: 0.5 | T31: =IF(Q31="", " ",Q31-R31-S31) -> 2
A32: =A31+1 -> 45686 | B32: =IF(A32<>"",WEEKDAY(A32,1),"") -> 4 | C32: 8.25 | D32: 2 | E32: 0 | F32: =IF(C32="", " ",C32-D32-E32) -> 6.25 | I32: =IF(H32<>"",WEEKDAY(H32,1),"") | M32: =IF(J32="", " ",J32-K32-L32) | O32: =O31+1 -> 45745 | P32: =IF(O32<>"",WEEKDAY(O32,1),"") -> 7 | Q32: 7 | R32: 3.5 | S32: 0 | T32: =IF(Q32="", " ",Q32-R32-S32) -> 3.5
A33: =A32+1 -> 45687 | B33: =IF(A33<>"",WEEKDAY(A33,1),"") -> 5 | C33: 10 | D33: 1.5 | E33: 0.5 | F33: =IF(C33="", " ",C33-D33-E33) -> 8 | O33: =O32+1 -> 45746 | P33: =IF(O33<>"",WEEKDAY(O33,1),"") -> 1 | Q33: 0 | R33: 0 | S33: 0 | T33: =IF(Q33="", " ",Q33-R33-S33) -> 0
A34: =A33+1 -> 45688 | B34: =IF(A34<>"",WEEKDAY(A34,1),"") -> 6 | C34: 7 | D34: 1 | E34: 0 | F34: =IF(C34="", " ",C34-D34-E34) -> 6 | O34: =O33+1 -> 45747 | P34: =IF(O34<>"",WEEKDAY(O34,1),"") -> 2 | Q34: 11 | R34: 3 | S34: 0 | T34: =IF(Q34="", " ",Q34-R34-S34) -> 8
A37: April | H37: May | O37: June
A38: Date | B38: Day | C38: T | D38: I | E38: P | F38: E | H38: Date | I38: Day | J38: T | K38: I | L38: P | M38: E | O38: Date | P38: Day | Q38: T | R38: I | S38: P | T38: E
A39: =DATEVALUE(CONCATENATE("4/1/",Budget!$A$1)) -> 45748 | B39: =IF(A39<>"",WEEKDAY(A39,1),"") -> 3 | C39: 2 | D39: 0.75 | E39: 0 | F39: =IF(C39="", " ",C39-D39-E39) -> 1.25 | H39: =DATEVALUE(CONCATENATE("5/1/",Budget!$A$1)) -> 45778 | I39: =IF(H39<>"",WEEKDAY(H39,1),"") -> 5 | J39: 8 | K39: 3 | L39: 0 | M39: =IF(J39="", " ",J39-K39-L39) -> 5 | O39: =DATEVALUE(CONCATENATE("6/1/",Budget!$A$1)) -> 45809 | P39: =IF(O39<>"",WEEKDAY(O39,1),"") -> 1 | Q39: 4 | R39: 2 | S39: 0 | T39: =IF(Q39="", " ",Q39-R39-S39) -> 2
A40: =A39+1 -> 45749 | B40: =IF(A40<>"",WEEKDAY(A40,1),"") -> 4 | C40: 8 | D40: 3 | E40: 0 | F40: =IF(C40="", " ",C40-D40-E40) -> 5 | H40: =H39+1 -> 45779 | I40: =IF(H40<>"",WEEKDAY(H40,1),"") -> 6 | J40: 10 | K40: 2 | L40: 0 | M40: =IF(J40="", " ",J40-K40-L40) -> 8 | O40: =O39+1 -> 45810 | P40: =IF(O40<>"",WEEKDAY(O40,1),"") -> 2 | Q40: 6 | R40: 1.5 | S40: 0 | T40: =IF(Q40="", " ",Q40-R40-S40) -> 4.5
A41: =A40+1 -> 45750 | B41: =IF(A41<>"",WEEKDAY(A41,1),"") -> 5 | C41: 8.5 | D41: 2.5 | E41: 0 | F41: =IF(C41="", " ",C41-D41-E41) -> 6 | H41: =H40+1 -> 45780 | I41: =IF(H41<>"",WEEKDAY(H41,1),"") -> 7 | J41: 1 | K41: 1 | L41: 0 | M41: =IF(J41="", " ",J41-K41-L41) -> 0 | O41: =O40+1 -> 45811 | P41: =IF(O41<>"",WEEKDAY(O41,1),"") -> 3 | Q41: 8 | R41: 2.5 | S41: 0 | T41: =IF(Q41="", " ",Q41-R41-S41) -> 5.5
A42: =A41+1 -> 45751 | B42: =IF(A42<>"",WEEKDAY(A42,1),"") -> 6 | C42: 7 | D42: 3 | E42: 0 | F42: =IF(C42="", " ",C42-D42-E42) -> 4 | H42: =H41+1 -> 45781 | I42: =IF(H42<>"",WEEKDAY(H42,1),"") -> 1 | J42: 0 | K42: 0 | L42: 0 | M42: =IF(J42="", " ",J42-K42-L42) -> 0 | O42: =O41+1 -> 45812 | P42: =IF(O42<>"",WEEKDAY(O42,1),"") -> 4 | Q42: 11 | R42: 4.5 | S42: 0 | T42: =IF(Q42="", " ",Q42-R42-S42) -> 6.5
A43: =A42+1 -> 45752 | B43: =IF(A43<>"",WEEKDAY(A43,1),"") -> 7 | C43: 2 | D43: 2 | E43: 0 | F43: =IF(C43="", " ",C43-D43-E43) -> 0 | H43: =H42+1 -> 45782 | I43: =IF(H43<>"",WEEKDAY(H43,1),"") -> 2 | J43: 7.5 | K43: 2 | L43: 0 | M43: =IF(J43="", " ",J43-K43-L43) -> 5.5 | O43: =O42+1 -> 45813 | P43: =IF(O43<>"",WEEKDAY(O43,1),"") -> 5 | Q43: 10 | R43: 4 | S43: 0 | T43: =IF(Q43="", " ",Q43-R43-S43) -> 6
A44: =A43+1 -> 45753 | B44: =IF(A44<>"",WEEKDAY(A44,1),"") -> 1 | C44: 1 | D44: 1 | E44: 0 | F44: =IF(C44="", " ",C44-D44-E44) -> 0 | H44: =H43+1 -> 45783 | I44: =IF(H44<>"",WEEKDAY(H44,1),"") -> 3 | J44: 7 | K44: 0.75 | L44: 0 | M44: =IF(J44="", " ",J44-K44-L44) -> 6.25 | O44: =O43+1 -> 45814 | P44: =IF(O44<>"",WEEKDAY(O44,1),"") -> 6 | Q44: 9 | R44: 1 | S44: 1.25 | T44: =IF(Q44="", " ",Q44-R44-S44) -> 6.75
A45: =A44+1 -> 45754 | B45: =IF(A45<>"",WEEKDAY(A45,1),"") -> 2 | C45: 2 | D45: 2 | E45: 0 | F45: =IF(C45="", " ",C45-D45-E45) -> 0 | H45: =H44+1 -> 45784 | I45: =IF(H45<>"",WEEKDAY(H45,1),"") -> 4 | J45: 11 | K45: 4 | L45: 0.5 | M45: =IF(J45="", " ",J45-K45-L45) -> 6.5 | O45: =O44+1 -> 45815 | P45: =IF(O45<>"",WEEKDAY(O45,1),"") -> 7 | Q45: 2 | R45: 1 | S45: 0 | T45: =IF(Q45="", " ",Q45-R45-S45) -> 1
A46: =A45+1 -> 45755 | B46: =IF(A46<>"",WEEKDAY(A46,1),"") -> 3 | C46: 5 | D46: 0.5 | E46: 0 | F46: =IF(C46="", " ",C46-D46-E46) -> 4.5 | H46: =H45+1 -> 45785 | I46: =IF(H46<>"",WEEKDAY(H46,1),"") -> 5 | J46: 12 | K46: 4.5 | L46: 0 | M46: =IF(J46="", " ",J46-K46-L46) -> 7.5 | O46: =O45+1 -> 45816 | P46: =IF(O46<>"",WEEKDAY(O46,1),"") -> 1 | Q46: 1 | R46: 0 | S46: 0 | T46: =IF(Q46="", " ",Q46-R46-S46) -> 1
A47: =A46+1 -> 45756 | B47: =IF(A47<>"",WEEKDAY(A47,1),"") -> 4 | C47: 12 | D47: 2.25 | E47: 0.75 | F47: =IF(C47="", " ",C47-D47-E47) -> 9 | H47: =H46+1 -> 45786 | I47: =IF(H47<>"",WEEKDAY(H47,1),"") -> 6 | J47: 2 | K47: 1 | L47: 0 | M47: =IF(J47="", " ",J47-K47-L47) -> 1 | O47: =O46+1 -> 45817 | P47: =IF(O47<>"",WEEKDAY(O47,1),"") -> 2 | Q47: 8.5 | R47: 2.5 | S47: 1.5 | T47: =IF(Q47="", " ",Q47-R47-S47) -> 4.5
A48: =A47+1 -> 45757 | B48: =IF(A48<>"",WEEKDAY(A48,1),"") -> 5 | C48: 9 | D48: 3.5 | E48: 0 | F48: =IF(C48="", " ",C48-D48-E48) -> 5.5 | H48: =H47+1 -> 45787 | I48: =IF(H48<>"",WEEKDAY(H48,1),"") -> 7 | J48: 1 | K48: 1 | L48: 0 | M48: =IF(J48="", " ",J48-K48-L48) -> 0 | O48: =O47+1 -> 45818 | P48: =IF(O48<>"",WEEKDAY(O48,1),"") -> 3 | Q48: 10 | R48: 3 | S48: 0.5 | T48: =IF(Q48="", " ",Q48-R48-S48) -> 6.5
A49: =A48+1 -> 45758 | B49: =IF(A49<>"",WEEKDAY(A49,1),"") -> 6 | C49: 8 | D49: 2 | E49: 0 | F49: =IF(C49="", " ",C49-D49-E49) -> 6 | H49: =H48+1 -> 45788 | I49: =IF(H49<>"",WEEKDAY(H49,1),"") -> 1 | J49: 1 | K49: 1 | L49: 0 | M49: =IF(J49="", " ",J49-K49-L49) -> 0 | O49: =O48+1 -> 45819 | P49: =IF(O49<>"",WEEKDAY(O49,1),"") -> 4 | Q49: 7 | R49: 3.25 | S49: 0 | T49: =IF(Q49="", " ",Q49-R49-S49) -> 3.75
A50: =A49+1 -> 45759 | B50: =IF(A50<>"",WEEKDAY(A50,1),"") -> 7 | C50: 2 | D50: 1 | E50: 0 | F50: =IF(C50="", " ",C50-D50-E50) -> 1 | H50: =H49+1 -> 45789 | I50: =IF(H50<>"",WEEKDAY(H50,1),"") -> 2 | J50: 2 | K50: 2 | L50: 0 | M50: =IF(J50="", " ",J50-K50-L50) -> 0 | O50: =O49+1 -> 45820 | P50: =IF(O50<>"",WEEKDAY(O50,1),"") -> 5 | Q50: 11 | R50: 2.5 | S50: 0 | T50: =IF(Q50="", " ",Q50-R50-S50) -> 8.5
A51: =A50+1 -> 45760 | B51: =IF(A51<>"",WEEKDAY(A51,1),"") -> 1 | C51: 8 | D51: 1.5 | E51: 1 | F51: =IF(C51="", " ",C51-D51-E51) -> 5.5 | H51: =H50+1 -> 45790 | I51: =IF(H51<>"",WEEKDAY(H51,1),"") -> 3 | J51: 4 | K51: 1 | L51: 0 | M51: =IF(J51="", " ",J51-K51-L51) -> 3 | O51: =O50+1 -> 45821 | P51: =IF(O51<>"",WEEKDAY(O51,1),"") -> 6 | Q51: 8 | R51: 3 | S51: 0 | T51: =IF(Q51="", " ",Q51-R51-S51) -> 5
... A54: =A53+1 -> 45763 | B54: =IF(A54<>"",WEEKDAY(A54,1),"") -> 4 | C54: 6 | D54: 1.5 | E54: 0 | F54: =IF(C54="", " ",C54-D54-E54) -> 4.5 | H54: =H53+1 -> 45793 | I54: =IF(H54<>"",WEEKDAY(H54,1),"") -> 6 | J54: 4 | K54: 1 | L54: 1.25 | M54: =IF(J54="", " ",J54-K54-L54) -> 1.75 | O54: =O53+1 -> 45824 | P54: =IF(O54<>"",WEEKDAY(O54,1),"") -> 2 | Q54: 6 | R54: 1.5 | S54: 0 | T54: =IF(Q54="", " ",Q54-R54-S54) -> 4.5
A55: =A54+1 -> 45764 | B55: =IF(A55<>"",WEEKDAY(A55,1),"") -> 5 | C55: 8 | D55: 2 | E55: 1 | F55: =IF(C55="", " ",C55-D55-E55) -> 5 | H55: =H54+1 -> 45794 | I55: =IF(H55<>"",WEEKDAY(H55,1),"") -> 7 | J55: 2 | K55: 2 | L55: 0 | M55: =IF(J55="", " ",J55-K55-L55) -> 0 | O55: =O54+1 -> 45825 | P55: =IF(O55<>"",WEEKDAY(O55,1),"") -> 3 | T55: =IF(Q55="", " ",Q55-R55-S55)
A56: =A55+1 -> 45765 | B56: =IF(A56<>"",WEEKDAY(A56,1),"") -> 6 | C56: 5 | D56: 0 | E56: 0 | F56: =IF(C56="", " ",C56-D56-E56) -> 5 | H56: =H55+1 -> 45795 | I56: =IF(H56<>"",WEEKDAY(H56,1),"") -> 1 | J56: 0.5 | K56: 0.5 | L56: 0 | M56: =IF(J56="", " ",J56-K56-L56) -> 0 | O56: =O55+1 -> 45826 | P56: =IF(O56<>"",WEEKDAY(O56,1),"") -> 4 | T56: =IF(Q56="", " ",Q56-R56-S56)
A57: =A56+1 -> 45766 | B57: =IF(A57<>"",WEEKDAY(A57,1),"") -> 7 | C57: 1 | D57: 1 | E57: 0 | F57: =IF(C57="", " ",C57-D57-E57) -> 0 | H57: =H56+1 -> 45796 | I57: =IF(H57<>"",WEEKDAY(H57,1),"") -> 2 | J57: 7.75 | K57: 1.5 | L57: 0 | M57: =IF(J57="", " ",J57-K57-L57) -> 6.25 | O57: =O56+1 -> 45827 | P57: =IF(O57<>"",WEEKDAY(O57,1),"") -> 5 | T57: =IF(Q57="", " ",Q57-R57-S57)
A58: =A57+1 -> 45767 | B58: =IF(A58<>"",WEEKDAY(A58,1),"") -> 1 | C58: 0 | D58: 0 | E58: 0 | F58: =IF(C58="", " ",C58-D58-E58) -> 0 | H58: =H57+1 -> 45797 | I58: =IF(H58<>"",WEEKDAY(H58,1),"") -> 3 | J58: 8 | K58: 2.75 | L58: 0 | M58: =IF(J58="", " ",J58-K58-L58) -> 5.25 | O58: =O57+1 -> 45828 | P58: =IF(O58<>"",WEEKDAY(O58,1),"") -> 6 | T58: =IF(Q58="", " ",Q58-R58-S58)
A59: =A58+1 -> 45768 | B59: =IF(A59<>"",WEEKDAY(A59,1),"") -> 2 | C59: 7 | D59: 1.5 | E59: 1 | F59: =IF(C59="", " ",C59-D59-E59) -> 4.5 | H59: =H58+1 -> 45798 | I59: =IF(H59<>"",WEEKDAY(H59,1),"") -> 4 | J59: 11 | K59: 4.75 | L59: 0.5 | M59: =IF(J59="", " ",J59-K59-L59) -> 5.75 | O59: =O58+1 -> 45829 | P59: =IF(O59<>"",WEEKDAY(O59,1),"") -> 7 | T59: =IF(Q59="", " ",Q59-R59-S59)
A60: =A59+1 -> 45769 | B60: =IF(A60<>"",WEEKDAY(A60,1),"") -> 3 | C60: 8 | D60: 1.25 | E60: 0 | F60: =IF(C60="", " ",C60-D60-E60) -> 6.75 | H60: =H59+1 -> 45799 | I60: =IF(H60<>"",WEEKDAY(H60,1),"") -> 5 | J60: 8 | K60: 3.5 | L60: 0.5 | M60: =IF(J60="", " ",J60-K60-L60) -> 4 | O60: =O59+1 -> 45830 | P60: =IF(O60<>"",WEEKDAY(O60,1),"") -> 1 | T60: =IF(Q60="", " ",Q60-R60-S60)
A61: =A60+1 -> 45770 | B61: =IF(A61<>"",WEEKDAY(A61,1),"") -> 4 | C61: 9 | D61: 1.5 | E61: 0 | F61: =IF(C61="", " ",C61-D61-E61) -> 7.5 | H61: =H60+1 -> 45800 | I61: =IF(H61<>"",WEEKDAY(H61,1),"") -> 6 | J61: 10.5 | K61: 3 | L61: 1 | M61: =IF(J61="", " ",J61-K61-L61) -> 6.5 | O61: =O60+1 -> 45831 | P61: =IF(O61<>"",WEEKDAY(O61,1),"") -> 2 | T61: =IF(Q61="", " ",Q61-R61-S61)
A62: =A61+1 -> 45771 | B62: =IF(A62<>"",WEEKDAY(A62,1),"") -> 5 | C62: 11 | D62: 3.5 | E62: 1.5 | F62: =IF(C62="", " ",C62-D62-E62) -> 6 | H62: =H61+1 -> 45801 | I62: =IF(H62<>"",WEEKDAY(H62,1),"") -> 7 | J62: 1 | K62: 0 | L62: 1 | M62: =IF(J62="", " ",J62-K62-L62) -> 0 | O62: =O61+1 -> 45832 | P62: =IF(O62<>"",WEEKDAY(O62,1),"") -> 3 | T62: =IF(Q62="", " ",Q62-R62-S62)
A63: =A62+1 -> 45772 | B63: =IF(A63<>"",WEEKDAY(A63,1),"") -> 6 | C63: 6.5 | D63: 2 | E63: 1 | F63: =IF(C63="", " ",C63-D63-E63) -> 3.5 | H63: =H62+1 -> 45802 | I63: =IF(H63<>"",WEEKDAY(H63,1),"") -> 1 | J63: 1 | K63: 1 | L63: 0 | M63: =IF(J63="", " ",J63-K63-L63) -> 0 | O63: =O62+1 -> 45833 | P63: =IF(O63<>"",WEEKDAY(O63,1),"") -> 4 | T63: =IF(Q63="", " ",Q63-R63-S63)
A64: =A63+1 -> 45773 | B64: =IF(A64<>"",WEEKDAY(A64,1),"") -> 7 | C64: 0 | D64: 0 | E64: 0 | F64: =IF(C64="", " ",C64-D64-E64) -> 0 | H64: =H63+1 -> 45803 | I64: =IF(H64<>"",WEEKDAY(H64,1),"") -> 2 | J64: 1 | K64: 0 | L64: 0 | M64: =IF(J64="", " ",J64-K64-L64) -> 1 | O64: =O63+1 -> 45834 | P64: =IF(O64<>"",WEEKDAY(O64,1),"") -> 5 | T64: =IF(Q64="", " ",Q64-R64-S64)
A65: =A64+1 -> 45774 | B65: =IF(A65<>"",WEEKDAY(A65,1),"") -> 1 | C65: 2 | D65: 2 | E65: 0 | F65: =IF(C65="", " ",C65-D65-E65) -> 0 | H65: =H64+1 -> 45804 | I65: =IF(H65<>"",WEEKDAY(H65,1),"") -> 3 | J65: 10 | K65: 2 | L65: 0 | M65: =IF(J65="", " ",J65-K65-L65) -> 8 | O65: =O64+1 -> 45835 | P65: =IF(O65<>"",WEEKDAY(O65,1),"") -> 6 | T65: =IF(Q65="", " ",Q65-R65-S65)
A66: =A65+1 -> 45775 | B66: =IF(A66<>"",WEEKDAY(A66,1),"") -> 2 | C66: 5 | D66: 1 | E66: 0 | F66: =IF(C66="", " ",C66-D66-E66) -> 4 | H66: =H65+1 -> 45805 | I66: =IF(H66<>"",WEEKDAY(H66,1),"") -> 4 | J66: 10 | K66: 3 | L66: 0.5 | M66: =IF(J66="", " ",J66-K66-L66) -> 6.5 | O66: =O65+1 -> 45836 | P66: =IF(O66<>"",WEEKDAY(O66,1),"") -> 7 | T66: =IF(Q66="", " ",Q66-R66-S66)
A67: =A66+1 -> 45776 | B67: =IF(A67<>"",WEEKDAY(A67,1),"") -> 3 | C67: 7 | D67: 1.5 | E67: 0.5 | F67: =IF(C67="", " ",C67-D67-E67) -> 5 | H67: =H66+1 -> 45806 | I67: =IF(H67<>"",WEEKDAY(H67,1),"") -> 5 | J67: 10 | K67: 3 | L67: 0 | M67: =IF(J67="", " ",J67-K67-L67) -> 7 | O67: =O66+1 -> 45837 | P67: =IF(O67<>"",WEEKDAY(O67,1),"") -> 1 | T67: =IF(Q67="", " ",Q67-R67-S67)
A68: =A67+1 -> 45777 | B68: =IF(A68<>"",WEEKDAY(A68,1),"") -> 4 | C68: 7 | D68: 4 | E68: 0 | F68: =IF(C68="", " ",C68-D68-E68) -> 3 | H68: =H67+1 -> 45807 | I68: =IF(H68<>"",WEEKDAY(H68,1),"") -> 6 | J68: 9 | K68: 2 | L68: 0.5 | M68: =IF(J68="", " ",J68-K68-L68) -> 6.5 | O68: =O67+1 -> 45838 | P68: =IF(O68<>"",WEEKDAY(O68,1),"") -> 2 | Q68: 7 | R68: 1 | S68: 0 | T68: =IF(Q68="", " ",Q68-R68-S68) -> 6
H69: =H68+1 -> 45808 | I69: =IF(H69<>"",WEEKDAY(H69,1),"") -> 7 | J69: 0 | K69: 0 | L69: 0 | M69: =IF(J69="", " ",J69-K69-L69) -> 0
A72: July | H72: August | O72: September
A73: Date | B73: Day | C73: T | D73: I | E73: P | F73: E | H73: Date | I73: Day | J73: T | K73: I | L73: P | M73: E | O73: Date | P73: Day | Q73: T | R73: I | S73: P | T73: E
A74: =DATEVALUE(CONCATENATE("7/1/",Budget!$A$1)) -> 45839 | B74: =IF(A74<>"",WEEKDAY(A74,1),"") -> 3 | C74: 9 | D74: 1 | E74: 0.5 | F74: =IF(C74="", " ",C74-D74-E74) -> 7.5 | H74: =DATEVALUE(CONCATENATE("8/1/",Budget!$A$1)) -> 45870 | I74: =IF(H74<>"",WEEKDAY(H74,1),"") -> 6 | J74: 9 | K74: 2.5 | L74: 1 | M74: =IF(J74="", " ",J74-K74-L74) -> 5.5 | O74: =DATEVALUE(CONCATENATE("9/1/",Budget!$A$1)) -> 45901 | P74: =IF(O74<>"",WEEKDAY(O74,1),"") -> 2 | Q74: 1 | R74: 1 | S74: 0 | T74: =IF(Q74="", " ",Q74-R74-S74) -> 0
A75: =A74+1 -> 45840 | B75: =IF(A75<>"",WEEKDAY(A75,1),"") -> 4 | C75: 11.5 | D75: 4 | E75: 1.5 | F75: =IF(C75="", " ",C75-D75-E75) -> 6 | H75: =H74+1 -> 45871 | I75: =IF(H75<>"",WEEKDAY(H75,1),"") -> 7 | J75: 4 | K75: 1.5 | L75: 0 | M75: =IF(J75="", " ",J75-K75-L75) -> 2.5 | O75: =O74+1 -> 45902 | P75: =IF(O75<>"",WEEKDAY(O75,1),"") -> 3 | Q75: 3 | R75: 1 | S75: 0 | T75: =IF(Q75="", " ",Q75-R75-S75) -> 2
A76: =A75+1 -> 45841 | B76: =IF(A76<>"",WEEKDAY(A76,1),"") -> 5 | C76: 8 | D76: 0.5 | E76: 0 | F76: =IF(C76="", " ",C76-D76-E76) -> 7.5 | H76: =H75+1 -> 45872 | I76: =IF(H76<>"",WEEKDAY(H76,1),"") -> 1 | J76: 0.5 | K76: 0.5 | L76: 0 | M76: =IF(J76="", " ",J76-K76-L76) -> 0 | O76: =O75+1 -> 45903 | P76: =IF(O76<>"",WEEKDAY(O76,1),"") -> 4 | Q76: 8 | R76: 3 | S76: 0 | T76: =IF(Q76="", " ",Q76-R76-S76) -> 5
A77: =A76+1 -> 45842 | B77: =IF(A77<>"",WEEKDAY(A77,1),"") -> 6 | C77: 1.5 | D77: 1.5 | E77: 0 | F77: =IF(C77="", " ",C77-D77-E77) -> 0 | H77: =H76+1 -> 45873 | I77: =IF(H77<>"",WEEKDAY(H77,1),"") -> 2 | J77: 4 | K77: 0.5 | L77: 0 | M77: =IF(J77="", " ",J77-K77-L77) -> 3.5 | O77: =O76+1 -> 45904 | P77: =IF(O77<>"",WEEKDAY(O77,1),"") -> 5 | Q77: 4 | R77: 2 | S77: 0 | T77: =IF(Q77="", " ",Q77-R77-S77) -> 2
A78: =A77+1 -> 45843 | B78: =IF(A78<>"",WEEKDAY(A78,1),"") -> 7 | C78: 0 | D78: 0 | E78: 0 | F78: =IF(C78="", " ",C78-D78-E78) -> 0 | H78: =H77+1 -> 45874 | I78: =IF(H78<>"",WEEKDAY(H78,1),"") -> 3 | J78: 9 | K78: 1.75 | L78: 0 | M78: =IF(J78="", " ",J78-K78-L78) -> 7.25 | O78: =O77+1 -> 45905 | P78: =IF(O78<>"",WEEKDAY(O78,1),"") -> 6 | Q78: 1 | R78: 1 | S78: 0 | T78: =IF(Q78="", " ",Q78-R78-S78) -> 0
A79: =A78+1 -> 45844 | B79: =IF(A79<>"",WEEKDAY(A79,1),"") -> 1 | C79: 0 | D79: 0 | E79: 0 | F79: =IF(C79="", " ",C79-D79-E79) -> 0 | H79: =H78+1 -> 45875 | I79: =IF(H79<>"",WEEKDAY(H79,1),"") -> 4 | J79: 14 | K79: 6.5 | L79: 0 | M79: =IF(J79="", " ",J79-K79-L79) -> 7.5 | O79: =O78+1 -> 45906 | P79: =IF(O79<>"",WEEKDAY(O79,1),"") -> 7 | Q79: 0 | R79: 0 | S79: 0 | T79: =IF(Q79="", " ",Q79-R79-S79) -> 0
A80: =A79+1 -> 45845 | B80: =IF(A80<>"",WEEKDAY(A80,1),"") -> 2 | C80: 5 | D80: 0.5 | E80: 0 | F80: =IF(C80="", " ",C80-D80-E80) -> 4.5 | H80: =H79+1 -> 45876 | I80: =IF(H80<>"",WEEKDAY(H80,1),"") -> 5 | J80: 12.5 | K80: 6.25 | L80: 0 | M80: =IF(J80="", " ",J80-K80-L80) -> 6.25 | O80: =O79+1 -> 45907 | P80: =IF(O80<>"",WEEKDAY(O80,1),"") -> 1 | Q80: 0 | R80: 0 | S80: 0 | T80: =IF(Q80="", " ",Q80-R80-S80) -> 0
A81: =A80+1 -> 45846 | B81: =IF(A81<>"",WEEKDAY(A81,1),"") -> 3 | C81: 10 | D81: 3 | E81: 0 | F81: =IF(C81="", " ",C81-D81-E81) -> 7 | H81: =H80+1 -> 45877 | I81: =IF(H81<>"",WEEKDAY(H81,1),"") -> 6 | J81: 11 | K81: 2.5 | L81: 0 | M81: =IF(J81="", " ",J81-K81-L81) -> 8.5 | O81: =O80+1 -> 45908 | P81: =IF(O81<>"",WEEKDAY(O81,1),"") -> 2 | Q81: 7 | R81: 2 | S81: 0 | T81: =IF(Q81="", " ",Q81-R81-S81) -> 5
A82: =A81+1 -> 45847 | B82: =IF(A82<>"",WEEKDAY(A82,1),"") -> 4 | C82: 7 | D82: 2.5 | E82: 0 | F82: =IF(C82="", " ",C82-D82-E82) -> 4.5 | H82: =H81+1 -> 45878 | I82: =IF(H82<>"",WEEKDAY(H82,1),"") -> 7 | J82: 4 | K82: 2 | L82: 0.5 | M82: =IF(J82="", " ",J82-K82-L82) -> 1.5 | O82: =O81+1 -> 45909 | P82: =IF(O82<>"",WEEKDAY(O82,1),"") -> 3 | Q82: 10 | R82: 0.5 | S82: 0 | T82: =IF(Q82="", " ",Q82-R82-S82) -> 9.5
A83: =A82+1 -> 45848 | B83: =IF(A83<>"",WEEKDAY(A83,1),"") -> 5 | C83: 10 | D83: 2 | E83: 0 | F83: =IF(C83="", " ",C83-D83-E83) -> 8 | H83: =H82+1 -> 45879 | I83: =IF(H83<>"",WEEKDAY(H83,1),"") -> 1 | J83: 1.5 | K83: 1 | L83: 0.5 | M83: =IF(J83="", " ",J83-K83-L83) -> 0 | O83: =O82+1 -> 45910 | P83: =IF(O83<>"",WEEKDAY(O83,1),"") -> 4 | Q83: 14 | R83: 2 | S83: 1 | T83: =IF(Q83="", " ",Q83-R83-S83) -> 11
A84: =A83+1 -> 45849 | B84: =IF(A84<>"",WEEKDAY(A84,1),"") -> 6 | C84: 2 | D84: 0 | E84: 0 | F84: =IF(C84="", " ",C84-D84-E84) -> 2 | H84: =H83+1 -> 45880 | I84: =IF(H84<>"",WEEKDAY(H84,1),"") -> 2 | J84: 12 | K84: 2.5 | L84: 0 | M84: =IF(J84="", " ",J84-K84-L84) -> 9.5 | O84: =O83+1 -> 45911 | P84: =IF(O84<>"",WEEKDAY(O84,1),"") -> 5 | Q84: 10 | R84: 1 | S84: 0 | T84: =IF(Q84="", " ",Q84-R84-S84) -> 9
A85: =A84+1 -> 45850 | B85: =IF(A85<>"",WEEKDAY(A85,1),"") -> 7 | C85: 0 | D85: 0 | E85: 0 | F85: =IF(C85="", " ",C85-D85-E85) -> 0 | H85: =H84+1 -> 45881 | I85: =IF(H85<>"",WEEKDAY(H85,1),"") -> 3 | J85: 9 | K85: 2 | L85: 1 | M85: =IF(J85="", " ",J85-K85-L85) -> 6 | O85: =O84+1 -> 45912 | P85: =IF(O85<>"",WEEKDAY(O85,1),"") -> 6 | Q85: 7 | R85: 1 | S85: 0 | T85: =IF(Q85="", " ",Q85-R85-S85) -> 6
A86: =A85+1 -> 45851 | B86: =IF(A86<>"",WEEKDAY(A86,1),"") -> 1 | C86: 0 | D86: 0 | E86: 0 | F86: =IF(C86="", " ",C86-D86-E86) -> 0 | H86: =H85+1 -> 45882 | I86: =IF(H86<>"",WEEKDAY(H86,1),"") -> 4 | J86: 7 | K86: 2 | L86: 1 | M86: =IF(J86="", " ",J86-K86-L86) -> 4 | O86: =O85+1 -> 45913 | P86: =IF(O86<>"",WEEKDAY(O86,1),"") -> 7 | Q86: 0 | R86: 0 | S86: 0 | T86: =IF(Q86="", " ",Q86-R86-S86) -> 0
... A103: =A102+1 -> 45868 | B103: =IF(A103<>"",WEEKDAY(A103,1),"") -> 4 | C103: 10 | D103: 1.5 | E103: 0 | F103: =IF(C103="", " ",C103-D103-E103) -> 8.5 | H103: =H102+1 -> 45899 | I103: =IF(H103<>"",WEEKDAY(H103,1),"") -> 7 | J103: 1 | K103: 1 | L103: 0 | M103: =IF(J103="", " ",J103-K103-L103) -> 0 | O103: =O102+1 -> 45930 | P103: =IF(O103<>"",WEEKDAY(O103,1),"") -> 3 | Q103: 9 | R103: 2.5 | S103: 0 | T103: =IF(Q103="", " ",Q103-R103-S103) -> 6.5
A104: =A103+1 -> 45869 | B104: =IF(A104<>"",WEEKDAY(A104,1),"") -> 5 | C104: 12 | D104: 2 | E104: 0 | F104: =IF(C104="", " ",C104-D104-E104) -> 10 | H104: =H103+1 -> 45900 | I104: =IF(H104<>"",WEEKDAY(H104,1),"") -> 1 | J104: 1 | K104: 1 | L104: 0 | M104: =IF(J104="", " ",J104-K104-L104) -> 0
A107: October | H107: November | O107: December
A108: Date | B108: Day | C108: T | D108: I | E108: P | F108: E | H108: Date | I108: Day | J108: T | K108: I | L108: P | M108: E | O108: Date | P108: Day | Q108: T | R108: I | S108: P | T108: E
A109: =DATEVALUE(CONCATENATE("10/1/",Budget!$A$1)) -> 45931 | B109: =IF(A109<>"",WEEKDAY(A109,1),"") -> 4 | C109: 11 | D109: 2.5 | E109: 0 | F109: =IF(C109="", " ",C109-D109-E109) -> 8.5 | H109: =DATEVALUE(CONCATENATE("9/1/",Budget!$A$1)) -> 45901 | I109: =IF(H109<>"",WEEKDAY(H109,1),"") -> 2 | J109: 0 | K109: 0 | L109: 0 | M109: =IF(K109="", " ",K109-#REF!-L109) -> #REF! | O109: =DATEVALUE(CONCATENATE("10/1/",Budget!$A$1)) -> 45931 | P109: =IF(O109<>"",WEEKDAY(O109,1),"") -> 4 | Q109: 9 | R109: 1 | S109: 1 | T109: =IF(Q109="", " ",Q109-R109-S109) -> 7
A110: =A109+1 -> 45932 | B110: =IF(A110<>"",WEEKDAY(A110,1),"") -> 5 | C110: 6 | D110: 0.5 | E110: 0 | F110: =IF(C110="", " ",C110-D110-E110) -> 5.5 | H110: =H109+1 -> 45902 | I110: =IF(H110<>"",WEEKDAY(H110,1),"") -> 3 | J110: 0 | K110: 0 | L110: 0 | M110: =IF(J110="", " ",J110-K110-L110) -> 0 | O110: =O109+1 -> 45932 | P110: =IF(O110<>"",WEEKDAY(O110,1),"") -> 5 | Q110: 6 | R110: 0.5 | S110: 0 | T110: =IF(Q110="", " ",Q110-R110-S110) -> 5.5
A111: =A110+1 -> 45933 | B111: =IF(A111<>"",WEEKDAY(A111,1),"") -> 6 | C111: 8 | D111: 2 | E111: 0 | F111: =IF(C111="", " ",C111-D111-E111) -> 6 | H111: =H110+1 -> 45903 | I111: =IF(H111<>"",WEEKDAY(H111,1),"") -> 4 | J111: 10 | K111: 1.5 | L111: 0.75 | M111: =IF(J111="", " ",J111-K111-L111) -> 7.75 | O111: =O110+1 -> 45933 | P111: =IF(O111<>"",WEEKDAY(O111,1),"") -> 6 | Q111: 12 | R111: 4 | S111: 0.25 | T111: =IF(Q111="", " ",Q111-R111-S111) -> 7.75
A112: =A111+1 -> 45934 | B112: =IF(A112<>"",WEEKDAY(A112,1),"") -> 7 | C112: 2 | D112: 2 | E112: 0 | F112: =IF(C112="", " ",C112-D112-E112) -> 0 | H112: =H111+1 -> 45904 | I112: =IF(H112<>"",WEEKDAY(H112,1),"") -> 5 | J112: 7 | K112: 2.5 | L112: 0 | M112: =IF(J112="", " ",J112-K112-L112) -> 4.5 | O112: =O111+1 -> 45934 | P112: =IF(O112<>"",WEEKDAY(O112,1),"") -> 7 | Q112: 9 | R112: 4 | S112: 0 | T112: =IF(Q112="", " ",Q112-R112-S112) -> 5
A113: =A112+1 -> 45935 | B113: =IF(A113<>"",WEEKDAY(A113,1),"") -> 1 | C113: 1 | D113: 1 | E113: 0 | F113: =IF(C113="", " ",C113-D113-E113) -> 0 | H113: =H112+1 -> 45905 | I113: =IF(H113<>"",WEEKDAY(H113,1),"") -> 6 | J113: 11 | K113: 3.75 | L113: 0.5 | M113: =IF(J113="", " ",J113-K113-L113) -> 6.75 | O113: =O112+1 -> 45935 | P113: =IF(O113<>"",WEEKDAY(O113,1),"") -> 1 | Q113: 7 | R113: 3.75 | S113: 0 | T113: =IF(Q113="", " ",Q113-R113-S113) -> 3.25
A114: =A113+1 -> 45936 | B114: =IF(A114<>"",WEEKDAY(A114,1),"") -> 2 | C114: 7 | D114: 1 | E114: 0 | F114: =IF(C114="", " ",C114-D114-E114) -> 6 | H114: =H113+1 -> 45906 | I114: =IF(H114<>"",WEEKDAY(H114,1),"") -> 7 | J114: 8 | K114: 1 | L114: 0.25 | M114: =IF(J114="", " ",J114-K114-L114) -> 6.75 | O114: =O113+1 -> 45936 | P114: =IF(O114<>"",WEEKDAY(O114,1),"") -> 2 | Q114: 0 | R114: 0 | S114: 0 | T114: =IF(Q114="", " ",Q114-R114-S114) -> 0
A115: =A114+1 -> 45937 | B115: =IF(A115<>"",WEEKDAY(A115,1),"") -> 3 | C115: 8 | D115: 0.5 | E115: 0 | F115: =IF(C115="", " ",C115-D115-E115) -> 7.5 | H115: =H114+1 -> 45907 | I115: =IF(H115<>"",WEEKDAY(H115,1),"") -> 1 | J115: 10 | K115: 4.5 | L115: 0 | M115: =IF(J115="", " ",J115-K115-L115) -> 5.5 | O115: =O114+1 -> 45937 | P115: =IF(O115<>"",WEEKDAY(O115,1),"") -> 3 | Q115: 1 | R115: 0 | S115: 0 | T115: =IF(Q115="", " ",Q115-R115-S115) -> 1
A116: =A115+1 -> 45938 | B116: =IF(A116<>"",WEEKDAY(A116,1),"") -> 4 | C116: 8 | D116: 1 | E116: 0 | F116: =IF(C116="", " ",C116-D116-E116) -> 7 | H116: =H115+1 -> 45908 | I116: =IF(H116<>"",WEEKDAY(H116,1),"") -> 2 | J116: 0 | K116: 0 | L116: 0 | M116: =IF(J116="", " ",J116-K116-L116) -> 0 | O116: =O115+1 -> 45938 | P116: =IF(O116<>"",WEEKDAY(O116,1),"") -> 4 | Q116: 9 | R116: 3 | S116: 0 | T116: =IF(Q116="", " ",Q116-R116-S116) -> 6
A117: =A116+1 -> 45939 | B117: =IF(A117<>"",WEEKDAY(A117,1),"") -> 5 | C117: 8 | D117: 1 | E117: 0 | F117: =IF(C117="", " ",C117-D117-E117) -> 7 | H117: =H116+1 -> 45909 | I117: =IF(H117<>"",WEEKDAY(H117,1),"") -> 3 | J117: 0 | K117: 0 | L117: 0 | M117: =IF(J117="", " ",J117-K117-L117) -> 0 | O117: =O116+1 -> 45939 | P117: =IF(O117<>"",WEEKDAY(O117,1),"") -> 5 | Q117: 9 | R117: 1.5 | S117: 0 | T117: =IF(Q117="", " ",Q117-R117-S117) -> 7.5
A118: =A117+1 -> 45940 | B118: =IF(A118<>"",WEEKDAY(A118,1),"") -> 6 | C118: 8 | D118: 1 | E118: 0 | F118: =IF(C118="", " ",C118-D118-E118) -> 7 | H118: =H117+1 -> 45910 | I118: =IF(H118<>"",WEEKDAY(H118,1),"") -> 4 | J118: 0 | K118: 0 | L118: 0 | M118: =IF(J118="", " ",J118-K118-L118) -> 0 | O118: =O117+1 -> 45940 | P118: =IF(O118<>"",WEEKDAY(O118,1),"") -> 6 | Q118: 9 | R118: 4.25 | S118: 0 | T118: =IF(Q118="", " ",Q118-R118-S118) -> 4.75
A119: =A118+1 -> 45941 | B119: =IF(A119<>"",WEEKDAY(A119,1),"") -> 7 | C119: 8 | D119: 5 | E119: 0 | F119: =IF(C119="", " ",C119-D119-E119) -> 3 | H119: =H118+1 -> 45911 | I119: =IF(H119<>"",WEEKDAY(H119,1),"") -> 5 | J119: 0 | K119: 0 | L119: 0 | M119: =IF(J119="", " ",J119-K119-L119) -> 0 | O119: =O118+1 -> 45941 | P119: =IF(O119<>"",WEEKDAY(O119,1),"") -> 7 | Q119: 5.25 | R119: 2 | S119: 0 | T119: =IF(Q119="", " ",Q119-R119-S119) -> 3.25
A120: =A119+1 -> 45942 | B120: =IF(A120<>"",WEEKDAY(A120,1),"") -> 1 | C120: 0 | D120: 0 | E120: 0 | F120: =IF(C120="", " ",C120-D120-E120) -> 0 | H120: =H119+1 -> 45912 | I120: =IF(H120<>"",WEEKDAY(H120,1),"") -> 6 | J120: 6 | K120: 1 | L120: 0 | M120: =IF(J120="", " ",J120-K120-L120) -> 5 | O120: =O119+1 -> 45942 | P120: =IF(O120<>"",WEEKDAY(O120,1),"") -> 1 | Q120: 10 | R120: 2.75 | S120: 0 | T120: =IF(Q120="", " ",Q120-R120-S120) -> 7.25
A121: =A120+1 -> 45943 | B121: =IF(A121<>"",WEEKDAY(A121,1),"") -> 2 | C121: 4 | D121: 1 | E121: 0 | F121: =IF(C121="", " ",C121-D121-E121) -> 3 | H121: =H120+1 -> 45913 | I121: =IF(H121<>"",WEEKDAY(H121,1),"") -> 7 | J121: 8 | K121: 3 | L121: 0.5 | M121: =IF(J121="", " ",J121-K121-L121) -> 4.5 | O121: =O120+1 -> 45943 | P121: =IF(O121<>"",WEEKDAY(O121,1),"") -> 2 | Q121: 0 | R121: 0 | S121: 0 | T121: =IF(Q121="", " ",Q121-R121-S121) -> 0
A122: =A121+1 -> 45944 | B122: =IF(A122<>"",WEEKDAY(A122,1),"") -> 3 | C122: 9.25 | D122: 2 | E122: 0 | F122: =IF(C122="", " ",C122-D122-E122) -> 7.25 | H122: =H121+1 -> 45914 | I122: =IF(H122<>"",WEEKDAY(H122,1),"") -> 1 | J122: 6 | K122: 0.5 | L122: 0 | M122: =IF(J122="", " ",J122-K122-L122) -> 5.5 | O122: =O121+1 -> 45944 | P122: =IF(O122<>"",WEEKDAY(O122,1),"") -> 3 | Q122: 0 | R122: 0 | S122: 0 | T122: =IF(Q122="", " ",Q122-R122-S122) -> 0
A123: =A122+1 -> 45945 | B123: =IF(A123<>"",WEEKDAY(A123,1),"") -> 4 | C123: 10 | D123: 4.5 | E123: 0 | F123: =IF(C123="", " ",C123-D123-E123) -> 5.5 | H123: =H122+1 -> 45915 | I123: =IF(H123<>"",WEEKDAY(H123,1),"") -> 2 | J123: 0 | K123: 0 | L123: 0 | M123: =IF(J123="", " ",J123-K123-L123) -> 0 | O123: =O122+1 -> 45945 | P123: =IF(O123<>"",WEEKDAY(O123,1),"") -> 4 | T123: =IF(Q123="", " ",Q123-R123-S123)
A124: =A123+1 -> 45946 | B124: =IF(A124<>"",WEEKDAY(A124,1),"") -> 5 | C124: 5 | D124: 1.5 | E124: 0 | F124: =IF(C124="", " ",C124-D124-E124) -> 3.5 | H124: =H123+1 -> 45916 | I124: =IF(H124<>"",WEEKDAY(H124,1),"") -> 3 | J124: 3.5 | K124: 0 | L124: 1 | M124: =IF(J124="", " ",J124-K124-L124) -> 2.5 | O124: =O123+1 -> 45946 | P124: =IF(O124<>"",WEEKDAY(O124,1),"") -> 5 | T124: =IF(Q124="", " ",Q124-R124-S124)
...

Sheet PIE YTD-Overview
C1: Visual of this year's progress and overall totals. Add a note, your affirmation or your why in the tan cell. Only the tan cell can be typed in, the rest is a visual overview.
B2: Year: | C2: 2025 | E2: Total Days Worked: | F2: =SUM(U3:U14) -> 296 | H2: S | P2: Monthly Totals | Q2: T | R2: I | S2: P | T2: E | U2: Days worked | V2: Monthly Net Income | W2: Gross Income | X2: Month
P3: Jan | Q3: ='PIE Tracker'!AD4 -> 228.58333 | R3: ='PIE Tracker'!AE4 -> 61.24 | S3: ='PIE Tracker'!AF4 -> 23.75 | T3: ='PIE Tracker'!AG4 -> 143.59333 | U3: ='PIE Tracker'!AH4 -> 31 | V3: ='Closed Transactions'!Q66+'Closed Transactions'!R66 -> 10370 | W3: =SUMIF('Business Tracker'!$AA$6:$AA$67,MONTH(DATEVALUE(P3 &" 1")),'Business Tracker'!$AF$6:$AF$67) -> 15250 | X3: 1
P4: Feb | Q4: ='PIE Tracker'!AD5 -> 205.5 | R4: ='PIE Tracker'!AE5 -> 53.25 | S4: ='PIE Tracker'!AF5 -> 8.5 | T4: ='PIE Tracker'!AG5 -> 143.75 | U4: ='PIE Tracker'!AH5 -> 27 | V4: ='Closed Transactions'!S66+'Closed Transactions'!T66 -> 6880 | W4: =SUMIF('Business Tracker'!$AA$6:$AA$67,MONTH(DATEVALUE(P4 &" 1")),'Business Tracker'!$AF$6:$AF$67) -> 10000 | X4: 1
B5: Total Hrs | C5: Total "I" Hrs | D5: Total "P" Hrs | E5: Total "E" Hrs | P5: Mar | Q5: ='PIE Tracker'!AD6 -> 216.83 | R5: ='PIE Tracker'!AE6 -> 66.75 | S5: ='PIE Tracker'!AF6 -> 21.75 | T5: ='PIE Tracker'!AG6 -> 128.33 | U5: ='PIE Tracker'!AH6 -> 29 | V5: ='Closed Transactions'!U66+'Closed Transactions'!V66 -> 4381.325 | W5: =SUMIF('Business Tracker'!$AA$6:$AA$67,MONTH(DATEVALUE(P5 &" 1")),'Business Tracker'!$AF$6:$AF$67) -> 3657.5 | X5: 1
B6: =SUM(Q3:Q14) -> 1991.2133 | C6: =SUM(R3:R14) -> 576.69 | D6: =SUM(S3:S14) -> 100.5 | E6: =(B6-C6-D6) -> 1314.0233 | P6: Apr | Q6: ='PIE Tracker'!AD7 -> 166 | R6: ='PIE Tracker'!AE7 -> 50.25 | S6: ='PIE Tracker'!AF7 -> 7.5 | T6: ='PIE Tracker'!AG7 -> 108.25 | U6: ='PIE Tracker'!AH7 -> 28 | V6: ='Closed Transactions'!W66+'Closed Transactions'!X66 -> 52275 | W6: =SUMIF('Business Tracker'!$AA$6:$AA$67,MONTH(DATEVALUE(P6 &" 1")),'Business Tracker'!$AF$6:$AF$67) -> 61500 | X6: 1
P7: May | Q7: ='PIE Tracker'!AD8 -> 164.75 | R7: ='PIE Tracker'!AE8 -> 57.25 | S7: ='PIE Tracker'!AF8 -> 6.25 | T7: ='PIE Tracker'!AG8 -> 101.25 | U7: ='PIE Tracker'!AH8 -> 29 | V7: ='Closed Transactions'!Y66+'Closed Transactions'!Z66 -> 0 | W7: =SUMIF('Business Tracker'!$AA$6:$AA$67,MONTH(DATEVALUE(P7 &" 1")),'Business Tracker'!$AF$6:$AF$67) -> 0 | X7: 1
P8: Jun | Q8: ='PIE Tracker'!AD9 -> 110.5 | R8: ='PIE Tracker'!AE9 -> 35.25 | S8: ='PIE Tracker'!AF9 -> 3.25 | T8: ='PIE Tracker'!AG9 -> 72 | U8: ='PIE Tracker'!AH9 -> 17 | V8: ='Closed Transactions'!AA66+'Closed Transactions'!AB66 -> 4972.5 | W8: =SUMIF('Business Tracker'!$AA$6:$AA$67,MONTH(DATEVALUE(P8 &" 1")),'Business Tracker'!$AF$6:$AF$67) -> 2925 | X8: 1
C9: "I" Hrs % | D9: "P" Hrs % | E9: "N" Hrs % | P9: Jul | Q9: ='PIE Tracker'!AD10 -> 186.75 | R9: ='PIE Tracker'!AE10 -> 48.75 | S9: ='PIE Tracker'!AF10 -> 11.5 | T9: ='PIE Tracker'!AG10 -> 126.5 | U9: ='PIE Tracker'!AH10 -> 24 | V9: ='Closed Transactions'!AC66+'Closed Transactions'!AD66 -> 4546.4381 | W9: =SUMIF('Business Tracker'!$AA$6:$AA$67,MONTH(DATEVALUE(P9 &" 1")),'Business Tracker'!$AF$6:$AF$67) -> 7148.7507 | X9: 1
C10: =IF(B6=0,"0",C6/B6) -> 0.28961739 | D10: =IF(C6=0,"0",D6/B6) -> 0.050471739 | E10: =IF(D6=0,"0",E6/B6) -> 0.65991087 | P10: Aug | Q10: ='PIE Tracker'!AD11 -> 186 | R10: ='PIE Tracker'!AE11 -> 60 | S10: ='PIE Tracker'!AF11 -> 4.5 | T10: ='PIE Tracker'!AG11 -> 121.5 | U10: ='PIE Tracker'!AH11 -> 31 | V10: ='Closed Transactions'!AE66+'Closed Transactions'!AF66 -> 4201.125 | W10: =SUMIF('Business Tracker'!$AA$6:$AA$67,MONTH(DATEVALUE(P10 &" 1")),'Business Tracker'!$AF$6:$AF$67) -> 3295 | X10: 1
P11: Sep | Q11: ='PIE Tracker'!AD12 -> 161 | R11: ='PIE Tracker'!AE12 -> 44.5 | S11: ='PIE Tracker'!AF12 -> 5 | T11: ='PIE Tracker'!AG12 -> 111.5 | U11: ='PIE Tracker'!AH12 -> 26 | V11: ='Closed Transactions'!AG66+'Closed Transactions'!AH66 -> 13090 | W11: =SUMIF('Business Tracker'!$AA$6:$AA$67,MONTH(DATEVALUE(P11 &" 1")),'Business Tracker'!$AF$6:$AF$67) -> 15400 | X11: 1
P12: Oct | Q12: ='PIE Tracker'!AD13 -> 172.3 | R12: ='PIE Tracker'!AE13 -> 43.95 | S12: ='PIE Tracker'!AF13 -> 3.25 | T12: ='PIE Tracker'!AG13 -> 125.1 | U12: ='PIE Tracker'!AH13 -> 27 | V12: ='Closed Transactions'!AI66+'Closed Transactions'!AJ66 -> 0 | W12: =SUMIF('Business Tracker'!$AA$6:$AA$67,MONTH(DATEVALUE(P12 &" 1")),'Business Tracker'!$AF$6:$AF$67) -> 0 | X12: 1
B13: Ave. Hrs | C13: Ave. "I" | D13: Ave. "P" | E13: Ave. "N" | P13: Nov | Q13: ='PIE Tracker'!AD14 -> 106.75 | R13: ='PIE Tracker'!AE14 -> 28.75 | S13: ='PIE Tracker'!AF14 -> 4 | T13: ='PIE Tracker'!AG14 -> #REF! | U13: ='PIE Tracker'!AH14 -> 16 | V13: ='Closed Transactions'!AK66+'Closed Transactions'!AL66 -> 0 | W13: =SUMIF('Business Tracker'!$AA$6:$AA$67,MONTH(DATEVALUE(P13 &" 1")),'Business Tracker'!$AF$6:$AF$67) -> 0 | X13: 1
B14: Per Day | C14: Hrs/Day | D14: Hrs/Day | E14: Hrs/Day | P14: Dec | Q14: ='PIE Tracker'!AD15 -> 86.25 | R14: ='PIE Tracker'!AE15 -> 26.75 | S14: ='PIE Tracker'!AF15 -> 1.25 | T14: ='PIE Tracker'!AG15 -> 58.25 | U14: ='PIE Tracker'!AH15 -> 11 | V14: ='Closed Transactions'!AM66+'Closed Transactions'!AN66 -> 0 | W14: =SUMIF('Business Tracker'!$AA$6:$AA$67,MONTH(DATEVALUE(P14 &" 1")),'Business Tracker'!$AF$6:$AF$67) -> 0 | X14: 1
B15: =IF(B6=0,"0",B6/F2) -> 6.7270721 | C15: =IF(C6=0,"0",C6/F2) -> 1.948277 | D15: =IF(D6=0,"0",D6/F2) -> 0.33952703 | E15: =(B15)*(E10) -> 4.439268
C17: Hourly Yield Ratio
C18: =IF(B6=0,"0",(C6)/(D6)) -> 5.738209 | D18: to | E18: 1
C20: Agent Net Income: | D20: ='Closed Transactions'!M66 -> 94220.476
C21: "P" time/hour: | D21: =IF(B6=0,"0",D20/D6) -> 937.51717
C22: "T" time/hour: | D22: =IF(B6=0,"0",D20/B6) -> 47.318122

Sheet PIE Planner
C1: Only tan cell are to be typed in.
C2: Where Do You Stand?
C3: Fill in the tan cells to see where you are in relation to your goals. All other cells will self-populate.
H4: Goal: | I4: ='Goals & Fees'!L4 -> 200000
C5: Instant Check Up | F5: Remaining to reach Net Income Goal | I5: =I4-'Closed Transactions'!M66 -> 105779.52
G7: Days to work | I7: 90
C9: "P" Total Hours | E9: =I5/'PIE YTD-Overview'!D21 -> 112.82943 | G9: "P" hours per day | I9: =E9/I7 -> 1.2536603
C10: "I" Total Hours | E10: =E9*'PIE YTD-Overview'!C18 -> 647.43882 | G10: "I" hours per day | I10: =E10/I7 -> 7.1937647
C11: **This pulls information from the PIE YTD Overview.
C14: What Do You Need To Meet Your Goals?
B15: Allows you to use #s from previous year to help write business plan for current year. Use this calculator to play with 'your numbers to see where you need to improve to meet your goals.
C16: Fill in the tan cells to see where you are in relation to your goals. All other cells will self-populate.
C18: Goal Setting Tool | G18: Year End Goal | I18: 85000
C20: "P" $ per hour | E20: 1090 | G20: Days Left to Work | I20: 90
C21: "I" to "P" Ratio | E21: 4.71
C23: "P" Total Hours | E23: =I18/E20 -> 77.981651 | G23: "P" Hours Per Day | I23: =E23/I20 -> 0.86646279
C24: "I" Total Hours | E24: =E23*E21 -> 367.29358 | G24: "I" Hours Per Day | I24: =E24/I20 -> 4.0810398

Sheet RE Reviews
A1: Monthly Real Estate Reviews
A2: Name | B2: Address | C2: Location | D2: Purchase Price | E2: Purchase date | F2: Date Done | G2: Delivery Method | H2: Comments
A3: January
A14: February
A25: March
A36: April
A46: May
A56: June
A67: July
A78: August
A89: September
A100: October
A111: November
A122: December
... A126: Lynn Graham

Sheet Post Closing Calls
A1: POST CLOSING CALLS
A2: Current Year clients and COE will autofill from your Closed Transactions, once you overwrite a cell, manual entry is required. Just insert date (tan cells) of the last contact with your client.
A3: Current Year Clients | B3: COE | C3: Jan | D3: Feb | E3: Mar | F3: Apr | G3: May | H3: Jun | I3: Jul | J3: Aug | K3: Sep | L3: Oct | M3: Nov | N3: Dec
A4: =IF('Closed Transactions'!F3="","",'Closed Transactions'!F3) -> Kevin Zhao | B4: =IF('Closed Transactions'!A3="","",'Closed Transactions'!A3) -> 45667
A5: =IF('Closed Transactions'!F4="","",'Closed Transactions'!F4) -> Cristina Samaha | B5: =IF('Closed Transactions'!A4="","",'Closed Transactions'!A4) -> 45706
A6: =IF('Closed Transactions'!F5="","",'Closed Transactions'!F5) -> Kim & Damon Sidur | B6: =IF('Closed Transactions'!A5="","",'Closed Transactions'!A5) -> 45717
A7: =IF('Closed Transactions'!F6="","",'Closed Transactions'!F6) -> Anne Duffy, Elizabeth & Ariel | B7: =IF('Closed Transactions'!A6="","",'Closed Transactions'!A6) -> 45724
A8: =IF('Closed Transactions'!F7="","",'Closed Transactions'!F7) -> Lindsey Jasper & Ben Fielder | B8: =IF('Closed Transactions'!A7="","",'Closed Transactions'!A7) -> 45757
A9: =IF('Closed Transactions'!F8="","",'Closed Transactions'!F8) -> Doug Church | B9: =IF('Closed Transactions'!A8="","",'Closed Transactions'!A8) -> 45758
A10: =IF('Closed Transactions'!F9="","",'Closed Transactions'!F9) -> Ashraf Kadri | B10: =IF('Closed Transactions'!A9="","",'Closed Transactions'!A9) -> 45828
A11: =IF('Closed Transactions'!F10="","",'Closed Transactions'!F10) -> Nathan Desnoyers | B11: =IF('Closed Transactions'!A10="","",'Closed Transactions'!A10) -> 45838
A12: =IF('Closed Transactions'!F11="","",'Closed Transactions'!F11) -> Saria Alshaikhalia | B12: =IF('Closed Transactions'!A11="","",'Closed Transactions'!A11) -> 45839
A13: =IF('Closed Transactions'!F12="","",'Closed Transactions'!F12) -> Sneha Durgapal & Alex Hennessy | B13: =IF('Closed Transactions'!A12="","",'Closed Transactions'!A12) -> 45839
A14: =IF('Closed Transactions'!F13="","",'Closed Transactions'!F13) -> Jared Traggic & Kiana Spearman | B14: =IF('Closed Transactions'!A13="","",'Closed Transactions'!A13) -> 45845
A15: =IF('Closed Transactions'!F14="","",'Closed Transactions'!F14) -> Kristine & Ken Delos Reyes | B15: =IF('Closed Transactions'!A14="","",'Closed Transactions'!A14) -> 45853
... A53: =IF('Closed Transactions'!F52="","",'Closed Transactions'!F52) | B53: =IF('Closed Transactions'!A52="","",'Closed Transactions'!A52)
A54: =IF('Closed Transactions'!F58="","",'Closed Transactions'!F58) | B54: =IF('Closed Transactions'!A53="","",'Closed Transactions'!A53)
A55: =IF('Closed Transactions'!F61="","",'Closed Transactions'!F61) | B55: =IF('Closed Transactions'!A54="","",'Closed Transactions'!A54)
A56: =IF('Closed Transactions'!F62="","",'Closed Transactions'!F62) | B56: =IF('Closed Transactions'!A55="","",'Closed Transactions'!A55)
A57: =IF('Closed Transactions'!F63="","",'Closed Transactions'!F63) | B57: =IF('Closed Transactions'!A56="","",'Closed Transactions'!A56)
A58: =IF('Closed Transactions'!F64="","",'Closed Transactions'!F64) | B58: =IF('Closed Transactions'!A57="","",'Closed Transactions'!A57)

Sheet Fee calc_closed Transactions
B1: Referral taken out first | D1: Commision | E1: Referral fee reduced commission used for calculations | F1: Agent Net Income | G1: Brokerage Income | H1: Franchise fee Percentage taken | I1: Franchise flat fee | J1: Franchise Fee Transaction Calculation | K1: Franchise Fee Running total | L1: Markering Percentage Taken | M1: Marketing Flat Fee | N1: Marketing Calculation | O1: Marketing fee running total | P1: Option 1 Office fee-Split that agent keeps | Q1: Option 1 Office Amount | R1: Office Running Total | S1: Option 2 Office split | W1: Result of 1/2 Option Commission | X1: Final Office Split Amount
B2: Data From Goals & Fees | C2: Closed Transactions Sheet | H2: Comm Times Percent | S2: Agent Comm | T2: Agent Running total | U2: Office Split Amount
A3: ='Goals & Fees'!N9 -> 0 | B3: Franchise fee Percentage taken | C3: Row 2 | D3: ='Closed Transactions'!K3 -> 15250 | E3: ='Closed Transactions'!L3 -> 0 | F3: =IFERROR(D3-E3-G3,0) -> 10370 | G3: =IFERROR(X3+N3+J3,0) -> 4880 | H3: =IFERROR((D3-E3)*$A$3,0) -> 0 | I3: =IF($A$4<>"",$A$4,"") -> 0 | J3: =IF(D3="", 0,IF(H3>=A5,A5,IF(H3<1,I3,H3))) -> 0 | K3: =IF(D3="",0,J3) -> 0 | L3: =IFERROR((D3-E3)*$A$7,0) -> 0 | M3: =IF($A$8<>"",$A$8,"") -> 0 | N3: =IF(D3="", 0,IF(L3>=$A$9,$A$9,IF(L3<1,M3,L3))) -> 0 | O3: =IF(D3="",0,N3) -> 0 | P3: =IF(D3="",0,(D3-E3)*$A$12) -> 10370 | Q3: =IF(D3="",0,IF($A$14=0,(100%-$A$12)*D4,IF($A$14<D3-E3-P3,$A$14,D3-E3-P3))) -> 4880 | R3: =Q3 -> 4880 | S3: =IF('Goals & Fees'!E30>1,0,(D3-E3)*A35) -> 0 | T3: =S3 -> 0 | U3: =IF(D3="", "",D3-E3-S3) -> 15250 | W3: =IF(P3>0,Q3,S3) -> 4880 | X3: =IF(P3>0,Q3,U3) -> 4880
A4: ='Goals & Fees'!L9 -> 0 | B4: Franchise flat fee | C4: Row 3 | D4: ='Closed Transactions'!K4 -> 10000 | E4: ='Closed Transactions'!L4 -> 0 | F4: =IFERROR(D4-E4-G4,0) -> 6880 | G4: =IFERROR(X4+N4+J4,0) -> 3120 | H4: =IFERROR((D4-E4)*$A$3,0) -> 0 | I4: =IF($A$4<>"",$A$4,"") -> 0 | J4: =IF(D4="",0,IF((IF(K3>=$A$5,0,IF(H4<1,I4,H4))+K3)>$A$5,$A$5-K3,IF(K3>=$A$5,0,IF(H4<1,I4,H4)))) -> 0 | K4: =IF(D4="",0,J4+K3) -> 0 | L4: =IFERROR((D4-E4)*$A$7,0) -> 0 | M4: =IF($A$8<>"",$A$8,"") -> 0 | N4: =IF(D4="",0,IF((IF(O3>=$A$9,0,IF(L4<1,M4,L4))+O3)>$A$9,$A$9-O3,IF(O3>=$A$9,0,IF(L4<1,M4,L4)))) -> 0 | O4: =IF(D4="",0,N4+O3) -> 0 | P4: =IF(D4="",0,(D4-E4)*$A$12) -> 6800 | Q4: =IF(D4="",0,IF($A$14=0,(100%-$A$12)*D4,IF(R3>=$A$14,(100%-$A$13)*(D4-E4),IF(R3+(D4-E4-P4)>=$A$14,$A$14-R3,(D4-E4-P4))))) -> 3120 | R4: =Q4+R3 -> 8000 | S4: =_xlfn.XLOOKUP(T3,$B$35:$B$40,$A$35:$A$40,,1)*(D4-E4) -> 0 | T4: =S4+T3 -> 0 | U4: =D4-E4-S4 -> 10000 | W4: =IF(P4>0,Q4,S4) -> 3120 | X4: =IF(P4>0,Q4,U4) -> 3120
A5: ='Goals & Fees'!L13 -> 0 | B5: Franchise Fee Cap | C5: Row 4 | D5: ='Closed Transactions'!K5 -> 662.5 | E5: ='Closed Transactions'!L5 -> 0 | F5: =IFERROR(D5-E5-G5,0) -> 563.125 | G5: =IFERROR(X5+N5+J5,0) -> 99.375 | H5: =IFERROR((D5-E5)*$A$3,0) -> 0 | I5: =IF($A$4<>"",$A$4,"") -> 0 | J5: =IF(D5="",0,IF((IF(K4>=$A$5,0,IF(H5<1,I5,H5))+K4)>$A$5,$A$5-K4,IF(K4>=$A$5,0,IF(H5<1,I5,H5)))) -> 0 | K5: =IF(D5="",0,J5+K4) -> 0 | L5: =IFERROR((D5-E5)*$A$7,0) -> 0 | M5: =IF($A$8<>"",$A$8,"") -> 0 | N5: =IF(D5="",0,IF((IF(O4>=$A$9,0,IF(L5<1,M5,L5))+O4)>$A$9,$A$9-O4,IF(O4>=$A$9,0,IF(L5<1,M5,L5)))) -> 0 | O5: =IF(D5="",0,N5+O4) -> 0 | P5: =IF(D5="",0,(D5-E5)*$A$12) -> 450.5 | Q5: =IF(D5="",0,IF($A$14=0,(100%-$A$12)*D5,IF(R4>=$A$14,(100%-$A$13)*(D5-E5),IF(R4+(D5-E5-P5)>=$A$14,$A$14-R4,(D5-E5-P5))))) -> 99.375 | R5: =Q5+R4 -> 8099.375 | S5: =_xlfn.XLOOKUP(T4,$B$35:$B$40,$A$35:$A$40,,1)*(D5-E5) -> 0 | T5: =S5+T4 -> 0 | U5: =D5-E5-S5 -> 662.5 | W5: =IF(P5>0,Q5,S5) -> 99.375 | X5: =IF(P5>0,Q5,U5) -> 99.375
A6: =SUM(J3:J64) -> 0 | B6: Franchise paid to date | C6: Row 5 | D6: ='Closed Transactions'!K6 -> 2995 | E6: ='Closed Transactions'!L6 -> 749 | F6: =IFERROR(D6-E6-G6,0) -> 1909.1 | G6: =IFERROR(X6+N6+J6,0) -> 336.9 | H6: =IFERROR((D6-E6)*$A$3,0) -> 0 | I6: =IF($A$4<>"",$A$4,"") -> 0 | J6: =IF(D6="",0,IF((IF(K5>=$A$5,0,IF(H6<1,I6,H6))+K5)>$A$5,$A$5-K5,IF(K5>=$A$5,0,IF(H6<1,I6,H6)))) -> 0 | K6: =IF(D6="",0,J6+K5) -> 0 | L6: =IFERROR((D6-E6)*$A$7,0) -> 0 | M6: =IF($A$8<>"",$A$8,"") -> 0 | N6: =IF(D6="",0,IF((IF(O5>=$A$9,0,IF(L6<1,M6,L6))+O5)>$A$9,$A$9-O5,IF(O5>=$A$9,0,IF(L6<1,M6,L6)))) -> 0 | O6: =IF(D6="",0,N6+O5) -> 0 | P6: =IF(D6="",0,(D6-E6)*$A$12) -> 1527.28 | Q6: =IF(D6="",0,IF($A$14=0,(100%-$A$12)*D6,IF(R5>=$A$14,(100%-$A$13)*(D6-E6),IF(R5+(D6-E6-P6)>=$A$14,$A$14-R5,(D6-E6-P6))))) -> 336.9 | R6: =Q6+R5 -> 8436.275 | S6: =_xlfn.XLOOKUP(T5,$B$35:$B$40,$A$35:$A$40,,1)*(D6-E6) -> 0 | T6: =S6+T5 -> 0 | U6: =D6-E6-S6 -> 2246 | W6: =IF(P6>0,Q6,S6) -> 336.9 | X6: =IF(P6>0,Q6,U6) -> 336.9
A7: ='Goals & Fees'!N18 -> 0 | B7: Markering Percentage Taken | C7: Row 6 | D7: ='Closed Transactions'!K7 -> 22500 | E7: ='Closed Transactions'!L7 -> 0 | F7: =IFERROR(D7-E7-G7,0) -> 19125 | G7: =IFERROR(X7+N7+J7,0) -> 3375 | H7: =IFERROR((D7-E7)*$A$3,0) -> 0 | I7: =IF($A$4<>"",$A$4,"") -> 0 | J7: =IF(D7="",0,IF((IF(K6>=$A$5,0,IF(H7<1,I7,H7))+K6)>$A$5,$A$5-K6,IF(K6>=$A$5,0,IF(H7<1,I7,H7)))) -> 0 | K7: =IF(D7="",0,J7+K6) -> 0 | L7: =IFERROR((D7-E7)*$A$7,0) -> 0 | M7: =IF($A$8<>"",$A$8,"") -> 0 | N7: =IF(D7="",0,IF((IF(O6>=$A$9,0,IF(L7<1,M7,L7))+O6)>$A$9,$A$9-O6,IF(O6>=$A$9,0,IF(L7<1,M7,L7)))) -> 0 | O7: =IF(D7="",0,N7+O6) -> 0 | P7: =IF(D7="",0,(D7-E7)*$A$12) -> 15300 | Q7: =IF(D7="",0,IF($A$14=0,(100%-$A$12)*D7,IF(R6>=$A$14,(100%-$A$13)*(D7-E7),IF(R6+(D7-E7-P7)>=$A$14,$A$14-R6,(D7-E7-P7))))) -> 3375 | R7: =Q7+R6 -> 11811.275 | S7: =_xlfn.XLOOKUP(T6,$B$35:$B$40,$A$35:$A$40,,1)*(D7-E7) -> 0 | T7: =S7+T6 -> 0 | U7: =D7-E7-S7 -> 22500 | W7: =IF(P7>0,Q7,S7) -> 3375 | X7: =IF(P7>0,Q7,U7) -> 3375
A8: ='Goals & Fees'!L18 -> 0 | B8: Marketing Flat Fee | C8: Row 7 | D8: ='Closed Transactions'!K8 -> 39000 | E8: ='Closed Transactions'!L8 -> 0 | F8: =IFERROR(D8-E8-G8,0) -> 33150 | G8: =IFERROR(X8+N8+J8,0) -> 5850 | H8: =IFERROR((D8-E8)*$A$3,0) -> 0 | I8: =IF($A$4<>"",$A$4,"") -> 0 | J8: =IF(D8="",0,IF((IF(K7>=$A$5,0,IF(H8<1,I8,H8))+K7)>$A$5,$A$5-K7,IF(K7>=$A$5,0,IF(H8<1,I8,H8)))) -> 0 | K8: =IF(D8="",0,J8+K7) -> 0 | L8: =IFERROR((D8-E8)*$A$7,0) -> 0 | M8: =IF($A$8<>"",$A$8,"") -> 0 | N8: =IF(D8="",0,IF((IF(O7>=$A$9,0,IF(L8<1,M8,L8))+O7)>$A$9,$A$9-O7,IF(O7>=$A$9,0,IF(L8<1,M8,L8)))) -> 0 | O8: =IF(D8="",0,N8+O7) -> 0 | P8: =IF(D8="",0,(D8-E8)*$A$12) -> 26520 | Q8: =IF(D8="",0,IF($A$14=0,(100%-$A$12)*D8,IF(R7>=$A$14,(100%-$A$13)*(D8-E8),IF(R7+(D8-E8-P8)>=$A$14,$A$14-R7,(D8-E8-P8))))) -> 5850 | R8: =Q8+R7 -> 17661.275 | S8: =_xlfn.XLOOKUP(T7,$B$35:$B$40,$A$35:$A$40,,1)*(D8-E8) -> 0 | T8: =S8+T7 -> 0 | U8: =D8-E8-S8 -> 39000 | W8: =IF(P8>0,Q8,S8) -> 5850 | X8: =IF(P8>0,Q8,U8) -> 5850
A9: ='Goals & Fees'!L22 -> 0 | B9: Marketing Cap | C9: Row 8 | D9: ='Closed Transactions'!K9 -> 2925 | E9: ='Closed Transactions'!L9 -> 0 | F9: =IFERROR(D9-E9-G9,0) -> 2486.25 | G9: =IFERROR(X9+N9+J9,0) -> 438.75 | H9: =IFERROR((D9-E9)*$A$3,0) -> 0 | I9: =IF($A$4<>"",$A$4,"") -> 0 | J9: =IF(D9="",0,IF((IF(K8>=$A$5,0,IF(H9<1,I9,H9))+K8)>$A$5,$A$5-K8,IF(K8>=$A$5,0,IF(H9<1,I9,H9)))) -> 0 | K9: =IF(D9="",0,J9+K8) -> 0 | L9: =IFERROR((D9-E9)*$A$7,0) -> 0 | M9: =IF($A$8<>"",$A$8,"") -> 0 | N9: =IF(D9="",0,IF((IF(O8>=$A$9,0,IF(L9<1,M9,L9))+O8)>$A$9,$A$9-O8,IF(O8>=$A$9,0,IF(L9<1,M9,L9)))) -> 0 | O9: =IF(D9="",0,N9+O8) -> 0 | P9: =IF(D9="",0,(D9-E9)*$A$12) -> 1989 | Q9: =IF(D9="",0,IF($A$14=0,(100%-$A$12)*D9,IF(R8>=$A$14,(100%-$A$13)*(D9-E9),IF(R8+(D9-E9-P9)>=$A$14,$A$14-R8,(D9-E9-P9))))) -> 438.75 | R9: =Q9+R8 -> 18100.025 | S9: =_xlfn.XLOOKUP(T8,$B$35:$B$40,$A$35:$A$40,,1)*(D9-E9) -> 0 | T9: =S9+T8 -> 0 | U9: =D9-E9-S9 -> 2925 | W9: =IF(P9>0,Q9,S9) -> 438.75 | X9: =IF(P9>0,Q9,U9) -> 438.75
A10: =SUM(N3:N64) -> 0 | B10: Marketing Fee pd to date | C10: Row 9 | D10: ='Closed Transactions'!K10 -> 0 | E10: ='Closed Transactions'!L10 -> 0 | F10: =IFERROR(D10-E10-G10,0) -> 0 | G10: =IFERROR(X10+N10+J10,0) -> 0 | H10: =IFERROR((D10-E10)*$A$3,0) -> 0 | I10: =IF($A$4<>"",$A$4,"") -> 0 | J10: =IF(D10="",0,IF((IF(K9>=$A$5,0,IF(H10<1,I10,H10))+K9)>$A$5,$A$5-K9,IF(K9>=$A$5,0,IF(H10<1,I10,H10)))) -> 0 | K10: =IF(D10="",0,J10+K9) -> 0 | L10: =IFERROR((D10-E10)*$A$7,0) -> 0 | M10: =IF($A$8<>"",$A$8,"") -> 0 | N10: =IF(D10="",0,IF((IF(O9>=$A$9,0,IF(L10<1,M10,L10))+O9)>$A$9,$A$9-O9,IF(O9>=$A$9,0,IF(L10<1,M10,L10)))) -> 0 | O10: =IF(D10="",0,N10+O9) -> 0 | P10: =IF(D10="",0,(D10-E10)*$A$12) -> 0 | Q10: =IF(D10="",0,IF($A$14=0,(100%-$A$12)*D10,IF(R9>=$A$14,(100%-$A$13)*(D10-E10),IF(R9+(D10-E10-P10)>=$A$14,$A$14-R9,(D10-E10-P10))))) -> 0 | R10: =Q10+R9 -> 18100.025 | S10: =_xlfn.XLOOKUP(T9,$B$35:$B$40,$A$35:$A$40,,1)*(D10-E10) -> 0 | T10: =S10+T9 -> 0 | U10: =D10-E10-S10 -> 0 | W10: =IF(P10>0,Q10,S10) -> 0 | X10: =IF(P10>0,Q10,U10) -> 0
B11: Option 1 | C11: Row 10 | D11: ='Closed Transactions'!K11 -> 548.75 | E11: ='Closed Transactions'!L11 -> 0 | F11: =IFERROR(D11-E11-G11,0) -> 466.4375 | G11: =IFERROR(X11+N11+J11,0) -> 82.3125 | H11: =IFERROR((D11-E11)*$A$3,0) -> 0 | I11: =IF($A$4<>"",$A$4,"") -> 0 | J11: =IF(D11="",0,IF((IF(K10>=$A$5,0,IF(H11<1,I11,H11))+K10)>$A$5,$A$5-K10,IF(K10>=$A$5,0,IF(H11<1,I11,H11)))) -> 0 | K11: =IF(D11="",0,J11+K10) -> 0 | L11: =IFERROR((D11-E11)*$A$7,0) -> 0 | M11: =IF($A$8<>"",$A$8,"") -> 0 | N11: =IF(D11="",0,IF((IF(O10>=$A$9,0,IF(L11<1,M11,L11))+O10)>$A$9,$A$9-O10,IF(O10>=$A$9,0,IF(L11<1,M11,L11)))) -> 0 | O11: =IF(D11="",0,N11+O10) -> 0 | P11: =IF(D11="",0,(D11-E11)*$A$12) -> 373.15 | Q11: =IF(D11="",0,IF($A$14=0,(100%-$A$12)*D11,IF(R10>=$A$14,(100%-$A$13)*(D11-E11),IF(R10+(D11-E11-P11)>=$A$14,$A$14-R10,(D11-E11-P11))))) -> 82.3125 | R11: =Q11+R10 -> 18182.338 | S11: =_xlfn.XLOOKUP(T10,$B$35:$B$40,$A$35:$A$40,,1)*(D11-E11) -> 0 | T11: =S11+T10 -> 0 | U11: =D11-E11-S11 -> 548.75 | W11: =IF(P11>0,Q11,S11) -> 82.3125 | X11: =IF(P11>0,Q11,U11) -> 82.3125
A12: ='Goals & Fees'!F35 -> 0.68 | B12: Split that agent keeps | C12: Row 11 | D12: ='Closed Transactions'!K12 -> 0 | E12: ='Closed Transactions'!L12 -> 0 | F12: =IFERROR(D12-E12-G12,0) -> 0 | G12: =IFERROR(X12+N12+J12,0) -> 0 | H12: =IFERROR((D12-E12)*$A$3,0) -> 0 | I12: =IF($A$4<>"",$A$4,"") -> 0 | J12: =IF(D12="",0,IF((IF(K11>=$A$5,0,IF(H12<1,I12,H12))+K11)>$A$5,$A$5-K11,IF(K11>=$A$5,0,IF(H12<1,I12,H12)))) -> 0 | K12: =IF(D12="",0,J12+K11) -> 0 | L12: =IFERROR((D12-E12)*$A$7,0) -> 0 | M12: =IF($A$8<>"",$A$8,"") -> 0 | N12: =IF(D12="",0,IF((IF(O11>=$A$9,0,IF(L12<1,M12,L12))+O11)>$A$9,$A$9-O11,IF(O11>=$A$9,0,IF(L12<1,M12,L12)))) -> 0 | O12: =IF(D12="",0,N12+O11) -> 0 | P12: =IF(D12="",0,(D12-E12)*$A$12) -> 0 | Q12: =IF(D12="",0,IF($A$14=0,(100%-$A$12)*D12,IF(R11>=$A$14,(100%-$A$13)*(D12-E12),IF(R11+(D12-E12-P12)>=$A$14,$A$14-R11,(D12-E12-P12))))) -> 0 | R12: =Q12+R11 -> 18182.338 | S12: =_xlfn.XLOOKUP(T11,$B$35:$B$40,$A$35:$A$40,,1)*(D12-E12) -> 0 | T12: =S12+T11 -> 0 | U12: =D12-E12-S12 -> 0 | W12: =IF(P12>0,Q12,S12) -> 0 | X12: =IF(P12>0,Q12,U12) -> 0
A13: ='Goals & Fees'!F40 -> 0.85 | B13: Second split that agent keeps once Cap is met | C13: Row 12 | D13: ='Closed Transactions'!K13 -> 600 | E13: ='Closed Transactions'!L13 -> 0 | F13: =IFERROR(D13-E13-G13,0) -> 510 | G13: =IFERROR(X13+N13+J13,0) -> 90 | H13: =IFERROR((D13-E13)*$A$3,0) -> 0 | I13: =IF($A$4<>"",$A$4,"") -> 0 | J13: =IF(D13="",0,IF((IF(K12>=$A$5,0,IF(H13<1,I13,H13))+K12)>$A$5,$A$5-K12,IF(K12>=$A$5,0,IF(H13<1,I13,H13)))) -> 0 | K13: =IF(D13="",0,J13+K12) -> 0 | L13: =IFERROR((D13-E13)*$A$7,0) -> 0 | M13: =IF($A$8<>"",$A$8,"") -> 0 | N13: =IF(D13="",0,IF((IF(O12>=$A$9,0,IF(L13<1,M13,L13))+O12)>$A$9,$A$9-O12,IF(O12>=$A$9,0,IF(L13<1,M13,L13)))) -> 0 | O13: =IF(D13="",0,N13+O12) -> 0 | P13: =IF(D13="",0,(D13-E13)*$A$12) -> 408 | Q13: =IF(D13="",0,IF($A$14=0,(100%-$A$12)*D13,IF(R12>=$A$14,(100%-$A$13)*(D13-E13),IF(R12+(D13-E13-P13)>=$A$14,$A$14-R12,(D13-E13-P13))))) -> 90 | R13: =Q13+R12 -> 18272.338 | S13: =_xlfn.XLOOKUP(T12,$B$35:$B$40,$A$35:$A$40,,1)*(D13-E13) -> 0 | T13: =S13+T12 -> 0 | U13: =D13-E13-S13 -> 600 | W13: =IF(P13>0,Q13,S13) -> 90 | X13: =IF(P13>0,Q13,U13) -> 90
A14: ='Goals & Fees'!E30 -> 8000 | B14: Office CAP | C14: Row 13 | D14: ='Closed Transactions'!K14 -> 6000.0007 | E14: ='Closed Transactions'!L14 -> 1800 | F14: =IFERROR(D14-E14-G14,0) -> 3570.0006 | G14: =IFERROR(X14+N14+J14,0) -> 630.0001 | H14: =IFERROR((D14-E14)*$A$3,0) -> 0 | I14: =IF($A$4<>"",$A$4,"") -> 0 | J14: =IF(D14="",0,IF((IF(K13>=$A$5,0,IF(H14<1,I14,H14))+K13)>$A$5,$A$5-K13,IF(K13>=$A$5,0,IF(H14<1,I14,H14)))) -> 0 | K14: =IF(D14="",0,J14+K13) -> 0 | L14: =IFERROR((D14-E14)*$A$7,0) -> 0 | M14: =IF($A$8<>"",$A$8,"") -> 0 | N14: =IF(D14="",0,IF((IF(O13>=$A$9,0,IF(L14<1,M14,L14))+O13)>$A$9,$A$9-O13,IF(O13>=$A$9,0,IF(L14<1,M14,L14)))) -> 0 | O14: =IF(D14="",0,N14+O13) -> 0 | P14: =IF(D14="",0,(D14-E14)*$A$12) -> 2856.0004 | Q14: =IF(D14="",0,IF($A$14=0,(100%-$A$12)*D14,IF(R13>=$A$14,(100%-$A$13)*(D14-E14),IF(R13+(D14-E14-P14)>=$A$14,$A$14-R13,(D14-E14-P14))))) -> 630.0001 | R14: =Q14+R13 -> 18902.338 | S14: =_xlfn.XLOOKUP(T13,$B$35:$B$40,$A$35:$A$40,,1)*(D14-E14) -> 0 | T14: =S14+T13 -> 0 | U14: =D14-E14-S14 -> 4200.0007 | W14: =IF(P14>0,Q14,S14) -> 630.0001 | X14: =IF(P14>0,Q14,U14) -> 630.0001
A15: =SUM(Q3:Q64) -> 21583.025 | B15: Office Fee pd to Date | C15: Row 14 | D15: ='Closed Transactions'!K15 -> 3295 | E15: ='Closed Transactions'!L15 -> 823.75 | F15: =IFERROR(D15-E15-G15,0) -> 2100.5625 | G15: =IFERROR(X15+N15+J15,0) -> 370.6875 | H15: =IFERROR((D15-E15)*$A$3,0) -> 0 | I15: =IF($A$4<>"",$A$4,"") -> 0 | J15: =IF(D15="",0,IF((IF(K14>=$A$5,0,IF(H15<1,I15,H15))+K14)>$A$5,$A$5-K14,IF(K14>=$A$5,0,IF(H15<1,I15,H15)))) -> 0 | K15: =IF(D15="",0,J15+K14) -> 0 | L15: =IFERROR((D15-E15)*$A$7,0) -> 0 | M15: =IF($A$8<>"",$A$8,"") -> 0 | N15: =IF(D15="",0,IF((IF(O14>=$A$9,0,IF(L15<1,M15,L15))+O14)>$A$9,$A$9-O14,IF(O14>=$A$9,0,IF(L15<1,M15,L15)))) -> 0 | O15: =IF(D15="",0,N15+O14) -> 0 | P15: =IF(D15="",0,(D15-E15)*$A$12) -> 1680.45 | Q15: =IF(D15="",0,IF($A$14=0,(100%-$A$12)*D15,IF(R14>=$A$14,(100%-$A$13)*(D15-E15),IF(R14+(D15-E15-P15)>=$A$14,$A$14-R14,(D15-E15-P15))))) -> 370.6875 | R15: =Q15+R14 -> 19273.025 | S15: =_xlfn.XLOOKUP(T14,$B$35:$B$40,$A$35:$A$40,,1)*(D15-E15) -> 0 | T15: =S15+T14 -> 0 | U15: =D15-E15-S15 -> 2471.25 | W15: =IF(P15>0,Q15,S15) -> 370.6875 | X15: =IF(P15>0,Q15,U15) -> 370.6875
C16: Row 15 | D16: ='Closed Transactions'!K16 -> 0 | E16: ='Closed Transactions'!L16 -> 0 | F16: =IFERROR(D16-E16-G16,0) -> 0 | G16: =IFERROR(X16+N16+J16,0) -> 0 | H16: =IFERROR((D16-E16)*$A$3,0) -> 0 | I16: =IF($A$4<>"",$A$4,"") -> 0 | J16: =IF(D16="",0,IF((IF(K15>=$A$5,0,IF(H16<1,I16,H16))+K15)>$A$5,$A$5-K15,IF(K15>=$A$5,0,IF(H16<1,I16,H16)))) -> 0 | K16: =IF(D16="",0,J16+K15) -> 0 | L16: =IFERROR((D16-E16)*$A$7,0) -> 0 | M16: =IF($A$8<>"",$A$8,"") -> 0 | N16: =IF(D16="",0,IF((IF(O15>=$A$9,0,IF(L16<1,M16,L16))+O15)>$A$9,$A$9-O15,IF(O15>=$A$9,0,IF(L16<1,M16,L16)))) -> 0 | O16: =IF(D16="",0,N16+O15) -> 0 | P16: =IF(D16="",0,(D16-E16)*$A$12) -> 0 | Q16: =IF(D16="",0,IF($A$14=0,(100%-$A$12)*D16,IF(R15>=$A$14,(100%-$A$13)*(D16-E16),IF(R15+(D16-E16-P16)>=$A$14,$A$14-R15,(D16-E16-P16))))) -> 0 | R16: =Q16+R15 -> 19273.025 | S16: =_xlfn.XLOOKUP(T15,$B$35:$B$40,$A$35:$A$40,,1)*(D16-E16) -> 0 | T16: =S16+T15 -> 0 | U16: =D16-E16-S16 -> 0 | W16: =IF(P16>0,Q16,S16) -> 0 | X16: =IF(P16>0,Q16,U16) -> 0
B17: Charts data for YTD Summary | C17: Row 16 | D17: ='Closed Transactions'!K17 -> 15400 | E17: ='Closed Transactions'!L17 -> 0 | F17: =IFERROR(D17-E17-G17,0) -> 13090 | G17: =IFERROR(X17+N17+J17,0) -> 2310 | H17: =IFERROR((D17-E17)*$A$3,0) -> 0 | I17: =IF($A$4<>"",$A$4,"") -> 0 | J17: =IF(D17="",0,IF((IF(K16>=$A$5,0,IF(H17<1,I17,H17))+K16)>$A$5,$A$5-K16,IF(K16>=$A$5,0,IF(H17<1,I17,H17)))) -> 0 | K17: =IF(D17="",0,J17+K16) -> 0 | L17: =IFERROR((D17-E17)*$A$7,0) -> 0 | M17: =IF($A$8<>"",$A$8,"") -> 0 | N17: =IF(D17="",0,IF((IF(O16>=$A$9,0,IF(L17<1,M17,L17))+O16)>$A$9,$A$9-O16,IF(O16>=$A$9,0,IF(L17<1,M17,L17)))) -> 0 | O17: =IF(D17="",0,N17+O16) -> 0 | P17: =IF(D17="",0,(D17-E17)*$A$12) -> 10472 | Q17: =IF(D17="",0,IF($A$14=0,(100%-$A$12)*D17,IF(R16>=$A$14,(100%-$A$13)*(D17-E17),IF(R16+(D17-E17-P17)>=$A$14,$A$14-R16,(D17-E17-P17))))) -> 2310 | R17: =Q17+R16 -> 21583.025 | S17: =_xlfn.XLOOKUP(T16,$B$35:$B$40,$A$35:$A$40,,1)*(D17-E17) -> 0 | T17: =S17+T16 -> 0 | U17: =D17-E17-S17 -> 15400 | W17: =IF(P17>0,Q17,S17) -> 2310 | X17: =IF(P17>0,Q17,U17) -> 2310
A18: Marketing Cap | B18: =A9 -> 0 | C18: Row 17 | D18: ='Closed Transactions'!K18 -> 0 | E18: ='Closed Transactions'!L18 -> 0 | F18: =IFERROR(D18-E18-G18,0) -> 0 | G18: =IFERROR(X18+N18+J18,0) -> 0 | H18: =IFERROR((D18-E18)*$A$3,0) -> 0 | I18: =IF($A$4<>"",$A$4,"") -> 0 | J18: =IF(D18="",0,IF((IF(K17>=$A$5,0,IF(H18<1,I18,H18))+K17)>$A$5,$A$5-K17,IF(K17>=$A$5,0,IF(H18<1,I18,H18)))) -> 0 | K18: =IF(D18="",0,J18+K17) -> 0 | L18: =IFERROR((D18-E18)*$A$7,0) -> 0 | M18: =IF($A$8<>"",$A$8,"") -> 0 | N18: =IF(D18="",0,IF((IF(O17>=$A$9,0,IF(L18<1,M18,L18))+O17)>$A$9,$A$9-O17,IF(O17>=$A$9,0,IF(L18<1,M18,L18)))) -> 0 | O18: =IF(D18="",0,N18+O17) -> 0 | P18: =IF(D18="",0,(D18-E18)*$A$12) -> 0 | Q18: =IF(D18="",0,IF($A$14=0,(100%-$A$12)*D18,IF(R17>=$A$14,(100%-$A$13)*(D18-E18),IF(R17+(D18-E18-P18)>=$A$14,$A$14-R17,(D18-E18-P18))))) -> 0 | R18: =Q18+R17 -> 21583.025 | S18: =_xlfn.XLOOKUP(T17,$B$35:$B$40,$A$35:$A$40,,1)*(D18-E18) -> 0 | T18: =S18+T17 -> 0 | U18: =D18-E18-S18 -> 0 | W18: =IF(P18>0,Q18,S18) -> 0 | X18: =IF(P18>0,Q18,U18) -> 0
A19: Marketing Fee pd to date | B19: =A10 -> 0 | C19: Row 18 | D19: ='Closed Transactions'!K19 -> 0 | E19: ='Closed Transactions'!L19 -> 0 | F19: =IFERROR(D19-E19-G19,0) -> 0 | G19: =IFERROR(X19+N19+J19,0) -> 0 | H19: =IFERROR((D19-E19)*$A$3,0) -> 0 | I19: =IF($A$4<>"",$A$4,"") -> 0 | J19: =IF(D19="",0,IF((IF(K18>=$A$5,0,IF(H19<1,I19,H19))+K18)>$A$5,$A$5-K18,IF(K18>=$A$5,0,IF(H19<1,I19,H19)))) -> 0 | K19: =IF(D19="",0,J19+K18) -> 0 | L19: =IFERROR((D19-E19)*$A$7,0) -> 0 | M19: =IF($A$8<>"",$A$8,"") -> 0 | N19: =IF(D19="",0,IF((IF(O18>=$A$9,0,IF(L19<1,M19,L19))+O18)>$A$9,$A$9-O18,IF(O18>=$A$9,0,IF(L19<1,M19,L19)))) -> 0 | O19: =IF(D19="",0,N19+O18) -> 0 | P19: =IF(D19="",0,(D19-E19)*$A$12) -> 0 | Q19: =IF(D19="",0,IF($A$14=0,(100%-$A$12)*D19,IF(R18>=$A$14,(100%-$A$13)*(D19-E19),IF(R18+(D19-E19-P19)>=$A$14,$A$14-R18,(D19-E19-P19))))) -> 0 | R19: =Q19+R18 -> 21583.025 | S19: =_xlfn.XLOOKUP(T18,$B$35:$B$40,$A$35:$A$40,,1)*(D19-E19) -> 0 | T19: =S19+T18 -> 0 | U19: =D19-E19-S19 -> 0 | W19: =IF(P19>0,Q19,S19) -> 0 | X19: =IF(P19>0,Q19,U19) -> 0
A20: Performance | B20: =B19/B18 -> #DIV/0! | C20: Row 19 | D20: ='Closed Transactions'!K20 | E20: ='Closed Transactions'!L20 -> 0 | F20: =IFERROR(D20-E20-G20,0) -> 0 | G20: =IFERROR(X20+N20+J20,0) -> 0 | H20: =IFERROR((D20-E20)*$A$3,0) -> 0 | I20: =IF($A$4<>"",$A$4,"") -> 0 | J20: =IF(D20="",0,IF((IF(K19>=$A$5,0,IF(H20<1,I20,H20))+K19)>$A$5,$A$5-K19,IF(K19>=$A$5,0,IF(H20<1,I20,H20)))) -> 0 | K20: =IF(D20="",0,J20+K19) -> 0 | L20: =IFERROR((D20-E20)*$A$7,0) -> 0 | M20: =IF($A$8<>"",$A$8,"") -> 0 | N20: =IF(D20="",0,IF((IF(O19>=$A$9,0,IF(L20<1,M20,L20))+O19)>$A$9,$A$9-O19,IF(O19>=$A$9,0,IF(L20<1,M20,L20)))) -> 0 | O20: =IF(D20="",0,N20+O19) -> 0 | P20: =IF(D20="",0,(D20-E20)*$A$12) -> 0 | Q20: =IF(D20="",0,IF($A$14=0,(100%-$A$12)*D20,IF(R19>=$A$14,(100%-$A$13)*(D20-E20),IF(R19+(D20-E20-P20)>=$A$14,$A$14-R19,(D20-E20-P20))))) -> 0 | R20: =Q20+R19 -> 21583.025 | S20: =_xlfn.XLOOKUP(T19,$B$35:$B$40,$A$35:$A$40,,1)*(D20-E20) -> #VALUE! | T20: =S20+T19 -> #VALUE! | U20: =D20-E20-S20 -> #VALUE! | W20: =IF(P20>0,Q20,S20) -> #VALUE! | X20: =IF(P20>0,Q20,U20) -> #VALUE!
C21: Row 20 | D21: ='Closed Transactions'!K21 | E21: ='Closed Transactions'!L21 -> 0 | F21: =IFERROR(D21-E21-G21,0) -> 0 | G21: =IFERROR(X21+N21+J21,0) -> 0 | H21: =IFERROR((D21-E21)*$A$3,0) -> 0 | I21: =IF($A$4<>"",$A$4,"") -> 0 | J21: =IF(D21="",0,IF((IF(K20>=$A$5,0,IF(H21<1,I21,H21))+K20)>$A$5,$A$5-K20,IF(K20>=$A$5,0,IF(H21<1,I21,H21)))) -> 0 | K21: =IF(D21="",0,J21+K20) -> 0 | L21: =IFERROR((D21-E21)*$A$7,0) -> 0 | M21: =IF($A$8<>"",$A$8,"") -> 0 | N21: =IF(D21="",0,IF((IF(O20>=$A$9,0,IF(L21<1,M21,L21))+O20)>$A$9,$A$9-O20,IF(O20>=$A$9,0,IF(L21<1,M21,L21)))) -> 0 | O21: =IF(D21="",0,N21+O20) -> 0 | P21: =IF(D21="",0,(D21-E21)*$A$12) -> 0 | Q21: =IF(D21="",0,IF($A$14=0,(100%-$A$12)*D21,IF(R20>=$A$14,(100%-$A$13)*(D21-E21),IF(R20+(D21-E21-P21)>=$A$14,$A$14-R20,(D21-E21-P21))))) -> 0 | R21: =Q21+R20 -> 21583.025 | S21: =_xlfn.XLOOKUP(T20,$B$35:$B$40,$A$35:$A$40,,1)*(D21-E21) -> #VALUE! | T21: =S21+T20 -> #VALUE! | U21: =D21-E21-S21 -> #VALUE! | W21: =IF(P21>0,Q21,S21) -> #VALUE! | X21: =IF(P21>0,Q21,U21) -> #VALUE!
A22: Office CAP | B22: =A14 -> 8000 | C22: Row 21 | D22: ='Closed Transactions'!K22 | E22: ='Closed Transactions'!L22 -> 0 | F22: =IFERROR(D22-E22-G22,0) -> 0 | G22: =IFERROR(X22+N22+J22,0) -> 0 | H22: =IFERROR((D22-E22)*$A$3,0) -> 0 | I22: =IF($A$4<>"",$A$4,"") -> 0 | J22: =IF(D22="",0,IF((IF(K21>=$A$5,0,IF(H22<1,I22,H22))+K21)>$A$5,$A$5-K21,IF(K21>=$A$5,0,IF(H22<1,I22,H22)))) -> 0 | K22: =IF(D22="",0,J22+K21) -> 0 | L22: =IFERROR((D22-E22)*$A$7,0) -> 0 | M22: =IF($A$8<>"",$A$8,"") -> 0 | N22: =IF(D22="",0,IF((IF(O21>=$A$9,0,IF(L22<1,M22,L22))+O21)>$A$9,$A$9-O21,IF(O21>=$A$9,0,IF(L22<1,M22,L22)))) -> 0 | O22: =IF(D22="",0,N22+O21) -> 0 | P22: =IF(D22="",0,(D22-E22)*$A$12) -> 0 | Q22: =IF(D22="",0,IF($A$14=0,(100%-$A$12)*D22,IF(R21>=$A$14,(100%-$A$13)*(D22-E22),IF(R21+(D22-E22-P22)>=$A$14,$A$14-R21,(D22-E22-P22))))) -> 0 | R22: =Q22+R21 -> 21583.025 | S22: =_xlfn.XLOOKUP(T21,$B$35:$B$40,$A$35:$A$40,,1)*(D22-E22) -> #VALUE! | T22: =S22+T21 -> #VALUE! | U22: =D22-E22-S22 -> #VALUE! | W22: =IF(P22>0,Q22,S22) -> #VALUE! | X22: =IF(P22>0,Q22,U22) -> #VALUE!
A23: Office Fee pd to Date | B23: =A15 -> 21583.025 | C23: Row 22 | D23: ='Closed Transactions'!K23 | E23: ='Closed Transactions'!L23 -> 0 | F23: =IFERROR(D23-E23-G23,0) -> 0 | G23: =IFERROR(X23+N23+J23,0) -> 0 | H23: =IFERROR((D23-E23)*$A$3,0) -> 0 | I23: =IF($A$4<>"",$A$4,"") -> 0 | J23: =IF(D23="",0,IF((IF(K22>=$A$5,0,IF(H23<1,I23,H23))+K22)>$A$5,$A$5-K22,IF(K22>=$A$5,0,IF(H23<1,I23,H23)))) -> 0 | K23: =IF(D23="",0,J23+K22) -> 0 | L23: =IFERROR((D23-E23)*$A$7,0) -> 0 | M23: =IF($A$8<>"",$A$8,"") -> 0 | N23: =IF(D23="",0,IF((IF(O22>=$A$9,0,IF(L23<1,M23,L23))+O22)>$A$9,$A$9-O22,IF(O22>=$A$9,0,IF(L23<1,M23,L23)))) -> 0 | O23: =IF(D23="",0,N23+O22) -> 0 | P23: =IF(D23="",0,(D23-E23)*$A$12) -> 0 | Q23: =IF(D23="",0,IF($A$14=0,(100%-$A$12)*D23,IF(R22>=$A$14,(100%-$A$13)*(D23-E23),IF(R22+(D23-E23-P23)>=$A$14,$A$14-R22,(D23-E23-P23))))) -> 0 | R23: =Q23+R22 -> 21583.025 | S23: =_xlfn.XLOOKUP(T22,$B$35:$B$40,$A$35:$A$40,,1)*(D23-E23) -> #VALUE! | T23: =S23+T22 -> #VALUE! | U23: =D23-E23-S23 -> #VALUE! | W23: =IF(P23>0,Q23,S23) -> #VALUE! | X23: =IF(P23>0,Q23,U23) -> #VALUE!
A24: Performance | B24: =B23/B22 -> 2.6978781 | C24: Row 23 | D24: ='Closed Transactions'!K24 | E24: ='Closed Transactions'!L24 -> 0 | F24: =IFERROR(D24-E24-G24,0) -> 0 | G24: =IFERROR(X24+N24+J24,0) -> 0 | H24: =IFERROR((D24-E24)*$A$3,0) -> 0 | I24: =IF($A$4<>"",$A$4,"") -> 0 | J24: =IF(D24="",0,IF((IF(K23>=$A$5,0,IF(H24<1,I24,H24))+K23)>$A$5,$A$5-K23,IF(K23>=$A$5,0,IF(H24<1,I24,H24)))) -> 0 | K24: =IF(D24="",0,J24+K23) -> 0 | L24: =IFERROR((D24-E24)*$A$7,0) -> 0 | M24: =IF($A$8<>"",$A$8,"") -> 0 | N24: =IF(D24="",0,IF((IF(O23>=$A$9,0,IF(L24<1,M24,L24))+O23)>$A$9,$A$9-O23,IF(O23>=$A$9,0,IF(L24<1,M24,L24)))) -> 0 | O24: =IF(D24="",0,N24+O23) -> 0 | P24: =IF(D24="",0,(D24-E24)*$A$12) -> 0 | Q24: =IF(D24="",0,IF($A$14=0,(100%-$A$12)*D24,IF(R23>=$A$14,(100%-$A$13)*(D24-E24),IF(R23+(D24-E24-P24)>=$A$14,$A$14-R23,(D24-E24-P24))))) -> 0 | R24: =Q24+R23 -> 21583.025 | S24: =_xlfn.XLOOKUP(T23,$B$35:$B$40,$A$35:$A$40,,1)*(D24-E24) -> #VALUE! | T24: =S24+T23 -> #VALUE! | U24: =D24-E24-S24 -> #VALUE! | W24: =IF(P24>0,Q24,S24) -> #VALUE! | X24: =IF(P24>0,Q24,U24) -> #VALUE!
C25: Row 24 | D25: ='Closed Transactions'!K25 | E25: ='Closed Transactions'!L25 -> 0 | F25: =IFERROR(D25-E25-G25,0) -> 0 | G25: =IFERROR(X25+N25+J25,0) -> 0 | H25: =IFERROR((D25-E25)*$A$3,0) -> 0 | I25: =IF($A$4<>"",$A$4,"") -> 0 | J25: =IF(D25="",0,IF((IF(K24>=$A$5,0,IF(H25<1,I25,H25))+K24)>$A$5,$A$5-K24,IF(K24>=$A$5,0,IF(H25<1,I25,H25)))) -> 0 | K25: =IF(D25="",0,J25+K24) -> 0 | L25: =IFERROR((D25-E25)*$A$7,0) -> 0 | M25: =IF($A$8<>"",$A$8,"") -> 0 | N25: =IF(D25="",0,IF((IF(O24>=$A$9,0,IF(L25<1,M25,L25))+O24)>$A$9,$A$9-O24,IF(O24>=$A$9,0,IF(L25<1,M25,L25)))) -> 0 | O25: =IF(D25="",0,N25+O24) -> 0 | P25: =IF(D25="",0,(D25-E25)*$A$12) -> 0 | Q25: =IF(D25="",0,IF($A$14=0,(100%-$A$12)*D25,IF(R24>=$A$14,(100%-$A$13)*(D25-E25),IF(R24+(D25-E25-P25)>=$A$14,$A$14-R24,(D25-E25-P25))))) -> 0 | R25: =Q25+R24 -> 21583.025 | S25: =_xlfn.XLOOKUP(T24,$B$35:$B$40,$A$35:$A$40,,1)*(D25-E25) -> #VALUE! | T25: =S25+T24 -> #VALUE! | U25: =D25-E25-S25 -> #VALUE! | W25: =IF(P25>0,Q25,S25) -> #VALUE! | X25: =IF(P25>0,Q25,U25) -> #VALUE!
A26: Franchise Fee Cap | B26: =A5 -> 0 | C26: Row 25 | D26: ='Closed Transactions'!K26 | E26: ='Closed Transactions'!L26 -> 0 | F26: =IFERROR(D26-E26-G26,0) -> 0 | G26: =IFERROR(X26+N26+J26,0) -> 0 | H26: =IFERROR((D26-E26)*$A$3,0) -> 0 | I26: =IF($A$4<>"",$A$4,"") -> 0 | J26: =IF(D26="",0,IF((IF(K25>=$A$5,0,IF(H26<1,I26,H26))+K25)>$A$5,$A$5-K25,IF(K25>=$A$5,0,IF(H26<1,I26,H26)))) -> 0 | K26: =IF(D26="",0,J26+K25) -> 0 | L26: =IFERROR((D26-E26)*$A$7,0) -> 0 | M26: =IF($A$8<>"",$A$8,"") -> 0 | N26: =IF(D26="",0,IF((IF(O25>=$A$9,0,IF(L26<1,M26,L26))+O25)>$A$9,$A$9-O25,IF(O25>=$A$9,0,IF(L26<1,M26,L26)))) -> 0 | O26: =IF(D26="",0,N26+O25) -> 0 | P26: =IF(D26="",0,(D26-E26)*$A$12) -> 0 | Q26: =IF(D26="",0,IF($A$14=0,(100%-$A$12)*D26,IF(R25>=$A$14,(100%-$A$13)*(D26-E26),IF(R25+(D26-E26-P26)>=$A$14,$A$14-R25,(D26-E26-P26))))) -> 0 | R26: =Q26+R25 -> 21583.025 | S26: =_xlfn.XLOOKUP(T25,$B$35:$B$40,$A$35:$A$40,,1)*(D26-E26) -> #VALUE! | T26: =S26+T25 -> #VALUE! | U26: =D26-E26-S26 -> #VALUE! | W26: =IF(P26>0,Q26,S26) -> #VALUE! | X26: =IF(P26>0,Q26,U26) -> #VALUE!
A27: Franchise paid to date | B27: =A6 -> 0 | C27: Row 26 | D27: ='Closed Transactions'!K27 | E27: ='Closed Transactions'!L27 -> 0 | F27: =IFERROR(D27-E27-G27,0) -> 0 | G27: =IFERROR(X27+N27+J27,0) -> 0 | H27: =IFERROR((D27-E27)*$A$3,0) -> 0 | I27: =IF($A$4<>"",$A$4,"") -> 0 | J27: =IF(D27="",0,IF((IF(K26>=$A$5,0,IF(H27<1,I27,H27))+K26)>$A$5,$A$5-K26,IF(K26>=$A$5,0,IF(H27<1,I27,H27)))) -> 0 | K27: =IF(D27="",0,J27+K26) -> 0 | L27: =IFERROR((D27-E27)*$A$7,0) -> 0 | M27: =IF($A$8<>"",$A$8,"") -> 0 | N27: =IF(D27="",0,IF((IF(O26>=$A$9,0,IF(L27<1,M27,L27))+O26)>$A$9,$A$9-O26,IF(O26>=$A$9,0,IF(L27<1,M27,L27)))) -> 0 | O27: =IF(D27="",0,N27+O26) -> 0 | P27: =IF(D27="",0,(D27-E27)*$A$12) -> 0 | Q27: =IF(D27="",0,IF($A$14=0,(100%-$A$12)*D27,IF(R26>=$A$14,(100%-$A$13)*(D27-E27),IF(R26+(D27-E27-P27)>=$A$14,$A$14-R26,(D27-E27-P27))))) -> 0 | R27: =Q27+R26 -> 21583.025 | S27: =_xlfn.XLOOKUP(T26,$B$35:$B$40,$A$35:$A$40,,1)*(D27-E27) -> #VALUE! | T27: =S27+T26 -> #VALUE! | U27: =D27-E27-S27 -> #VALUE! | W27: =IF(P27>0,Q27,S27) -> #VALUE! | X27: =IF(P27>0,Q27,U27) -> #VALUE!
A28: left to go | B28: =B27/B26 -> #DIV/0! | C28: Row 27 | D28: ='Closed Transactions'!K28 | E28: ='Closed Transactions'!L28 -> 0 | F28: =IFERROR(D28-E28-G28,0) -> 0 | G28: =IFERROR(X28+N28+J28,0) -> 0 | H28: =IFERROR((D28-E28)*$A$3,0) -> 0 | I28: =IF($A$4<>"",$A$4,"") -> 0 | J28: =IF(D28="",0,IF((IF(K27>=$A$5,0,IF(H28<1,I28,H28))+K27)>$A$5,$A$5-K27,IF(K27>=$A$5,0,IF(H28<1,I28,H28)))) -> 0 | K28: =IF(D28="",0,J28+K27) -> 0 | L28: =IFERROR((D28-E28)*$A$7,0) -> 0 | M28: =IF($A$8<>"",$A$8,"") -> 0 | N28: =IF(D28="",0,IF((IF(O27>=$A$9,0,IF(L28<1,M28,L28))+O27)>$A$9,$A$9-O27,IF(O27>=$A$9,0,IF(L28<1,M28,L28)))) -> 0 | O28: =IF(D28="",0,N28+O27) -> 0 | P28: =IF(D28="",0,(D28-E28)*$A$12) -> 0 | Q28: =IF(D28="",0,IF($A$14=0,(100%-$A$12)*D28,IF(R27>=$A$14,(100%-$A$13)*(D28-E28),IF(R27+(D28-E28-P28)>=$A$14,$A$14-R27,(D28-E28-P28))))) -> 0 | R28: =Q28+R27 -> 21583.025 | S28: =_xlfn.XLOOKUP(T27,$B$35:$B$40,$A$35:$A$40,,1)*(D28-E28) -> #VALUE! | T28: =S28+T27 -> #VALUE! | U28: =D28-E28-S28 -> #VALUE! | W28: =IF(P28>0,Q28,S28) -> #VALUE! | X28: =IF(P28>0,Q28,U28) -> #VALUE!
C29: Row 28 | D29: ='Closed Transactions'!K29 | E29: ='Closed Transactions'!L29 -> 0 | F29: =IFERROR(D29-E29-G29,0) -> 0 | G29: =IFERROR(X29+N29+J29,0) -> 0 | H29: =IFERROR((D29-E29)*$A$3,0) -> 0 | I29: =IF($A$4<>"",$A$4,"") -> 0 | J29: =IF(D29="",0,IF((IF(K28>=$A$5,0,IF(H29<1,I29,H29))+K28)>$A$5,$A$5-K28,IF(K28>=$A$5,0,IF(H29<1,I29,H29)))) -> 0 | K29: =IF(D29="",0,J29+K28) -> 0 | L29: =IFERROR((D29-E29)*$A$7,0) -> 0 | M29: =IF($A$8<>"",$A$8,"") -> 0 | N29: =IF(D29="",0,IF((IF(O28>=$A$9,0,IF(L29<1,M29,L29))+O28)>$A$9,$A$9-O28,IF(O28>=$A$9,0,IF(L29<1,M29,L29)))) -> 0 | O29: =IF(D29="",0,N29+O28) -> 0 | P29: =IF(D29="",0,(D29-E29)*$A$12) -> 0 | Q29: =IF(D29="",0,IF($A$14=0,(100%-$A$12)*D29,IF(R28>=$A$14,(100%-$A$13)*(D29-E29),IF(R28+(D29-E29-P29)>=$A$14,$A$14-R28,(D29-E29-P29))))) -> 0 | R29: =Q29+R28 -> 21583.025 | S29: =_xlfn.XLOOKUP(T28,$B$35:$B$40,$A$35:$A$40,,1)*(D29-E29) -> #VALUE! | T29: =S29+T28 -> #VALUE! | U29: =D29-E29-S29 -> #VALUE! | W29: =IF(P29>0,Q29,S29) -> #VALUE! | X29: =IF(P29>0,Q29,U29) -> #VALUE!
C30: Row 29 | D30: ='Closed Transactions'!K30 | E30: ='Closed Transactions'!L30 -> 0 | F30: =IFERROR(D30-E30-G30,0) -> 0 | G30: =IFERROR(X30+N30+J30,0) -> 0 | H30: =IFERROR((D30-E30)*$A$3,0) -> 0 | I30: =IF($A$4<>"",$A$4,"") -> 0 | J30: =IF(D30="",0,IF((IF(K29>=$A$5,0,IF(H30<1,I30,H30))+K29)>$A$5,$A$5-K29,IF(K29>=$A$5,0,IF(H30<1,I30,H30)))) -> 0 | K30: =IF(D30="",0,J30+K29) -> 0 | L30: =IFERROR((D30-E30)*$A$7,0) -> 0 | M30: =IF($A$8<>"",$A$8,"") -> 0 | N30: =IF(D30="",0,IF((IF(O29>=$A$9,0,IF(L30<1,M30,L30))+O29)>$A$9,$A$9-O29,IF(O29>=$A$9,0,IF(L30<1,M30,L30)))) -> 0 | O30: =IF(D30="",0,N30+O29) -> 0 | P30: =IF(D30="",0,(D30-E30)*$A$12) -> 0 | Q30: =IF(D30="",0,IF($A$14=0,(100%-$A$12)*D30,IF(R29>=$A$14,(100%-$A$13)*(D30-E30),IF(R29+(D30-E30-P30)>=$A$14,$A$14-R29,(D30-E30-P30))))) -> 0 | R30: =Q30+R29 -> 21583.025 | S30: =_xlfn.XLOOKUP(T29,$B$35:$B$40,$A$35:$A$40,,1)*(D30-E30) -> #VALUE! | T30: =S30+T29 -> #VALUE! | U30: =D30-E30-S30 -> #VALUE! | W30: =IF(P30>0,Q30,S30) -> #VALUE! | X30: =IF(P30>0,Q30,U30) -> #VALUE!
C31: Row 30 | D31: ='Closed Transactions'!K31 | E31: ='Closed Transactions'!L31 -> 0 | F31: =IFERROR(D31-E31-G31,0) -> 0 | G31: =IFERROR(X31+N31+J31,0) -> 0 | H31: =IFERROR((D31-E31)*$A$3,0) -> 0 | I31: =IF($A$4<>"",$A$4,"") -> 0 | J31: =IF(D31="",0,IF((IF(K30>=$A$5,0,IF(H31<1,I31,H31))+K30)>$A$5,$A$5-K30,IF(K30>=$A$5,0,IF(H31<1,I31,H31)))) -> 0 | K31: =IF(D31="",0,J31+K30) -> 0 | L31: =IFERROR((D31-E31)*$A$7,0) -> 0 | M31: =IF($A$8<>"",$A$8,"") -> 0 | N31: =IF(D31="",0,IF((IF(O30>=$A$9,0,IF(L31<1,M31,L31))+O30)>$A$9,$A$9-O30,IF(O30>=$A$9,0,IF(L31<1,M31,L31)))) -> 0 | O31: =IF(D31="",0,N31+O30) -> 0 | P31: =IF(D31="",0,(D31-E31)*$A$12) -> 0 | Q31: =IF(D31="",0,IF($A$14=0,(100%-$A$12)*D31,IF(R30>=$A$14,(100%-$A$13)*(D31-E31),IF(R30+(D31-E31-P31)>=$A$14,$A$14-R30,(D31-E31-P31))))) -> 0 | R31: =Q31+R30 -> 21583.025 | S31: =_xlfn.XLOOKUP(T30,$B$35:$B$40,$A$35:$A$40,,1)*(D31-E31) -> #VALUE! | T31: =S31+T30 -> #VALUE! | U31: =D31-E31-S31 -> #VALUE! | W31: =IF(P31>0,Q31,S31) -> #VALUE! | X31: =IF(P31>0,Q31,U31) -> #VALUE!
C32: Row 31 | D32: ='Closed Transactions'!K32 | E32: ='Closed Transactions'!L32 -> 0 | F32: =IFERROR(D32-E32-G32,0) -> 0 | G32: =IFERROR(X32+N32+J32,0) -> 0 | H32: =IFERROR((D32-E32)*$A$3,0) -> 0 | I32: =IF($A$4<>"",$A$4,"") -> 0 | J32: =IF(D32="",0,IF((IF(K31>=$A$5,0,IF(H32<1,I32,H32))+K31)>$A$5,$A$5-K31,IF(K31>=$A$5,0,IF(H32<1,I32,H32)))) -> 0 | K32: =IF(D32="",0,J32+K31) -> 0 | L32: =IFERROR((D32-E32)*$A$7,0) -> 0 | M32: =IF($A$8<>"",$A$8,"") -> 0 | N32: =IF(D32="",0,IF((IF(O31>=$A$9,0,IF(L32<1,M32,L32))+O31)>$A$9,$A$9-O31,IF(O31>=$A$9,0,IF(L32<1,M32,L32)))) -> 0 | O32: =IF(D32="",0,N32+O31) -> 0 | P32: =IF(D32="",0,(D32-E32)*$A$12) -> 0 | Q32: =IF(D32="",0,IF($A$14=0,(100%-$A$12)*D32,IF(R31>=$A$14,(100%-$A$13)*(D32-E32),IF(R31+(D32-E32-P32)>=$A$14,$A$14-R31,(D32-E32-P32))))) -> 0 | R32: =Q32+R31 -> 21583.025 | S32: =_xlfn.XLOOKUP(T31,$B$35:$B$40,$A$35:$A$40,,1)*(D32-E32) -> #VALUE! | T32: =S32+T31 -> #VALUE! | U32: =D32-E32-S32 -> #VALUE! | W32: =IF(P32>0,Q32,S32) -> #VALUE! | X32: =IF(P32>0,Q32,U32) -> #VALUE!
C33: Row 32 | D33: ='Closed Transactions'!K33 | E33: ='Closed Transactions'!L33 -> 0 | F33: =IFERROR(D33-E33-G33,0) -> 0 | G33: =IFERROR(X33+N33+J33,0) -> 0 | H33: =IFERROR((D33-E33)*$A$3,0) -> 0 | I33: =IF($A$4<>"",$A$4,"") -> 0 | J33: =IF(D33="",0,IF((IF(K32>=$A$5,0,IF(H33<1,I33,H33))+K32)>$A$5,$A$5-K32,IF(K32>=$A$5,0,IF(H33<1,I33,H33)))) -> 0 | K33: =IF(D33="",0,J33+K32) -> 0 | L33: =IFERROR((D33-E33)*$A$7,0) -> 0 | M33: =IF($A$8<>"",$A$8,"") -> 0 | N33: =IF(D33="",0,IF((IF(O32>=$A$9,0,IF(L33<1,M33,L33))+O32)>$A$9,$A$9-O32,IF(O32>=$A$9,0,IF(L33<1,M33,L33)))) -> 0 | O33: =IF(D33="",0,N33+O32) -> 0 | P33: =IF(D33="",0,(D33-E33)*$A$12) -> 0 | Q33: =IF(D33="",0,IF($A$14=0,(100%-$A$12)*D33,IF(R32>=$A$14,(100%-$A$13)*(D33-E33),IF(R32+(D33-E33-P33)>=$A$14,$A$14-R32,(D33-E33-P33))))) -> 0 | R33: =Q33+R32 -> 21583.025 | S33: =_xlfn.XLOOKUP(T32,$B$35:$B$40,$A$35:$A$40,,1)*(D33-E33) -> #VALUE! | T33: =S33+T32 -> #VALUE! | U33: =D33-E33-S33 -> #VALUE! | W33: =IF(P33>0,Q33,S33) -> #VALUE! | X33: =IF(P33>0,Q33,U33) -> #VALUE!
A34: option 2 Agent split | B34: Income Tier | C34: Row 33 | D34: ='Closed Transactions'!K34 | E34: ='Closed Transactions'!L34 -> 0 | F34: =IFERROR(D34-E34-G34,0) -> 0 | G34: =IFERROR(X34+N34+J34,0) -> 0 | H34: =IFERROR((D34-E34)*$A$3,0) -> 0 | I34: =IF($A$4<>"",$A$4,"") -> 0 | J34: =IF(D34="",0,IF((IF(K33>=$A$5,0,IF(H34<1,I34,H34))+K33)>$A$5,$A$5-K33,IF(K33>=$A$5,0,IF(H34<1,I34,H34)))) -> 0 | K34: =IF(D34="",0,J34+K33) -> 0 | L34: =IFERROR((D34-E34)*$A$7,0) -> 0 | M34: =IF($A$8<>"",$A$8,"") -> 0 | N34: =IF(D34="",0,IF((IF(O33>=$A$9,0,IF(L34<1,M34,L34))+O33)>$A$9,$A$9-O33,IF(O33>=$A$9,0,IF(L34<1,M34,L34)))) -> 0 | O34: =IF(D34="",0,N34+O33) -> 0 | P34: =IF(D34="",0,(D34-E34)*$A$12) -> 0 | Q34: =IF(D34="",0,IF($A$14=0,(100%-$A$12)*D34,IF(R33>=$A$14,(100%-$A$13)*(D34-E34),IF(R33+(D34-E34-P34)>=$A$14,$A$14-R33,(D34-E34-P34))))) -> 0 | R34: =Q34+R33 -> 21583.025 | S34: =_xlfn.XLOOKUP(T33,$B$35:$B$40,$A$35:$A$40,,1)*(D34-E34) -> #VALUE! | T34: =S34+T33 -> #VALUE! | U34: =D34-E34-S34 -> #VALUE! | W34: =IF(P34>0,Q34,S34) -> #VALUE! | X34: =IF(P34>0,Q34,U34) -> #VALUE!
A35: ='Goals & Fees'!L32 -> 0 | B35: ='Goals & Fees'!Q32 -> 0 | C35: Row 34 | D35: ='Closed Transactions'!K35 | E35: ='Closed Transactions'!L35 -> 0 | F35: =IFERROR(D35-E35-G35,0) -> 0 | G35: =IFERROR(X35+N35+J35,0) -> 0 | H35: =IFERROR((D35-E35)*$A$3,0) -> 0 | I35: =IF($A$4<>"",$A$4,"") -> 0 | J35: =IF(D35="",0,IF((IF(K34>=$A$5,0,IF(H35<1,I35,H35))+K34)>$A$5,$A$5-K34,IF(K34>=$A$5,0,IF(H35<1,I35,H35)))) -> 0 | K35: =IF(D35="",0,J35+K34) -> 0 | L35: =IFERROR((D35-E35)*$A$7,0) -> 0 | M35: =IF($A$8<>"",$A$8,"") -> 0 | N35: =IF(D35="",0,IF((IF(O34>=$A$9,0,IF(L35<1,M35,L35))+O34)>$A$9,$A$9-O34,IF(O34>=$A$9,0,IF(L35<1,M35,L35)))) -> 0 | O35: =IF(D35="",0,N35+O34) -> 0 | P35: =IF(D35="",0,(D35-E35)*$A$12) -> 0 | Q35: =IF(D35="",0,IF($A$14=0,(100%-$A$12)*D35,IF(R34>=$A$14,(100%-$A$13)*(D35-E35),IF(R34+(D35-E35-P35)>=$A$14,$A$14-R34,(D35-E35-P35))))) -> 0 | R35: =Q35+R34 -> 21583.025 | S35: =_xlfn.XLOOKUP(T34,$B$35:$B$40,$A$35:$A$40,,1)*(D35-E35) -> #VALUE! | T35: =S35+T34 -> #VALUE! | U35: =D35-E35-S35 -> #VALUE! | W35: =IF(P35>0,Q35,S35) -> #VALUE! | X35: =IF(P35>0,Q35,U35) -> #VALUE!
A36: ='Goals & Fees'!L34 -> 0 | B36: ='Goals & Fees'!Q34 -> 0 | C36: Row 35 | D36: ='Closed Transactions'!K36 | E36: ='Closed Transactions'!L36 -> 0 | F36: =IFERROR(D36-E36-G36,0) -> 0 | G36: =IFERROR(X36+N36+J36,0) -> 0 | H36: =IFERROR((D36-E36)*$A$3,0) -> 0 | I36: =IF($A$4<>"",$A$4,"") -> 0 | J36: =IF(D36="",0,IF((IF(K35>=$A$5,0,IF(H36<1,I36,H36))+K35)>$A$5,$A$5-K35,IF(K35>=$A$5,0,IF(H36<1,I36,H36)))) -> 0 | K36: =IF(D36="",0,J36+K35) -> 0 | L36: =IFERROR((D36-E36)*$A$7,0) -> 0 | M36: =IF($A$8<>"",$A$8,"") -> 0 | N36: =IF(D36="",0,IF((IF(O35>=$A$9,0,IF(L36<1,M36,L36))+O35)>$A$9,$A$9-O35,IF(O35>=$A$9,0,IF(L36<1,M36,L36)))) -> 0 | O36: =IF(D36="",0,N36+O35) -> 0 | P36: =IF(D36="",0,(D36-E36)*$A$12) -> 0 | Q36: =IF(D36="",0,IF($A$14=0,(100%-$A$12)*D36,IF(R35>=$A$14,(100%-$A$13)*(D36-E36),IF(R35+(D36-E36-P36)>=$A$14,$A$14-R35,(D36-E36-P36))))) -> 0 | R36: =Q36+R35 -> 21583.025 | S36: =_xlfn.XLOOKUP(T35,$B$35:$B$40,$A$35:$A$40,,1)*(D36-E36) -> #VALUE! | T36: =S36+T35 -> #VALUE! | U36: =D36-E36-S36 -> #VALUE! | W36: =IF(P36>0,Q36,S36) -> #VALUE! | X36: =IF(P36>0,Q36,U36) -> #VALUE!
A37: ='Goals & Fees'!L36 -> 0 | B37: ='Goals & Fees'!Q36 -> 0 | C37: Row 36 | D37: ='Closed Transactions'!K37 | E37: ='Closed Transactions'!L37 -> 0 | F37: =IFERROR(D37-E37-G37,0) -> 0 | G37: =IFERROR(X37+N37+J37,0) -> 0 | H37: =IFERROR((D37-E37)*$A$3,0) -> 0 | I37: =IF($A$4<>"",$A$4,"") -> 0 | J37: =IF(D37="",0,IF((IF(K36>=$A$5,0,IF(H37<1,I37,H37))+K36)>$A$5,$A$5-K36,IF(K36>=$A$5,0,IF(H37<1,I37,H37)))) -> 0 | K37: =IF(D37="",0,J37+K36) -> 0 | L37: =IFERROR((D37-E37)*$A$7,0) -> 0 | M37: =IF($A$8<>"",$A$8,"") -> 0 | N37: =IF(D37="",0,IF((IF(O36>=$A$9,0,IF(L37<1,M37,L37))+O36)>$A$9,$A$9-O36,IF(O36>=$A$9,0,IF(L37<1,M37,L37)))) -> 0 | O37: =IF(D37="",0,N37+O36) -> 0 | P37: =IF(D37="",0,(D37-E37)*$A$12) -> 0 | Q37: =IF(D37="",0,IF($A$14=0,(100%-$A$12)*D37,IF(R36>=$A$14,(100%-$A$13)*(D37-E37),IF(R36+(D37-E37-P37)>=$A$14,$A$14-R36,(D37-E37-P37))))) -> 0 | R37: =Q37+R36 -> 21583.025 | S37: =_xlfn.XLOOKUP(T36,$B$35:$B$40,$A$35:$A$40,,1)*(D37-E37) -> #VALUE! | T37: =S37+T36 -> #VALUE! | U37: =D37-E37-S37 -> #VALUE! | W37: =IF(P37>0,Q37,S37) -> #VALUE! | X37: =IF(P37>0,Q37,U37) -> #VALUE!
A38: ='Goals & Fees'!L38 -> 0 | B38: ='Goals & Fees'!Q38 -> 0 | C38: Row 37 | D38: ='Closed Transactions'!K38 | E38: ='Closed Transactions'!L38 -> 0 | F38: =IFERROR(D38-E38-G38,0) -> 0 | G38: =IFERROR(X38+N38+J38,0) -> 0 | H38: =IFERROR((D38-E38)*$A$3,0) -> 0 | I38: =IF($A$4<>"",$A$4,"") -> 0 | J38: =IF(D38="",0,IF((IF(K37>=$A$5,0,IF(H38<1,I38,H38))+K37)>$A$5,$A$5-K37,IF(K37>=$A$5,0,IF(H38<1,I38,H38)))) -> 0 | K38: =IF(D38="",0,J38+K37) -> 0 | L38: =IFERROR((D38-E38)*$A$7,0) -> 0 | M38: =IF($A$8<>"",$A$8,"") -> 0 | N38: =IF(D38="",0,IF((IF(O37>=$A$9,0,IF(L38<1,M38,L38))+O37)>$A$9,$A$9-O37,IF(O37>=$A$9,0,IF(L38<1,M38,L38)))) -> 0 | O38: =IF(D38="",0,N38+O37) -> 0 | P38: =IF(D38="",0,(D38-E38)*$A$12) -> 0 | Q38: =IF(D38="",0,IF($A$14=0,(100%-$A$12)*D38,IF(R37>=$A$14,(100%-$A$13)*(D38-E38),IF(R37+(D38-E38-P38)>=$A$14,$A$14-R37,(D38-E38-P38))))) -> 0 | R38: =Q38+R37 -> 21583.025 | S38: =_xlfn.XLOOKUP(T37,$B$35:$B$40,$A$35:$A$40,,1)*(D38-E38) -> #VALUE! | T38: =S38+T37 -> #VALUE! | U38: =D38-E38-S38 -> #VALUE! | W38: =IF(P38>0,Q38,S38) -> #VALUE! | X38: =IF(P38>0,Q38,U38) -> #VALUE!
A39: ='Goals & Fees'!L40 -> 0 | B39: ='Goals & Fees'!Q40 -> 0 | C39: Row 38 | D39: ='Closed Transactions'!K39 | E39: ='Closed Transactions'!L39 -> 0 | F39: =IFERROR(D39-E39-G39,0) -> 0 | G39: =IFERROR(X39+N39+J39,0) -> 0 | H39: =IFERROR((D39-E39)*$A$3,0) -> 0 | I39: =IF($A$4<>"",$A$4,"") -> 0 | J39: =IF(D39="",0,IF((IF(K38>=$A$5,0,IF(H39<1,I39,H39))+K38)>$A$5,$A$5-K38,IF(K38>=$A$5,0,IF(H39<1,I39,H39)))) -> 0 | K39: =IF(D39="",0,J39+K38) -> 0 | L39: =IFERROR((D39-E39)*$A$7,0) -> 0 | M39: =IF($A$8<>"",$A$8,"") -> 0 | N39: =IF(D39="",0,IF((IF(O38>=$A$9,0,IF(L39<1,M39,L39))+O38)>$A$9,$A$9-O38,IF(O38>=$A$9,0,IF(L39<1,M39,L39)))) -> 0 | O39: =IF(D39="",0,N39+O38) -> 0 | P39: =IF(D39="",0,(D39-E39)*$A$12) -> 0 | Q39: =IF(D39="",0,IF($A$14=0,(100%-$A$12)*D39,IF(R38>=$A$14,(100%-$A$13)*(D39-E39),IF(R38+(D39-E39-P39)>=$A$14,$A$14-R38,(D39-E39-P39))))) -> 0 | R39: =Q39+R38 -> 21583.025 | S39: =_xlfn.XLOOKUP(T38,$B$35:$B$40,$A$35:$A$40,,1)*(D39-E39) -> #VALUE! | T39: =S39+T38 -> #VALUE! | U39: =D39-E39-S39 -> #VALUE! | W39: =IF(P39>0,Q39,S39) -> #VALUE! | X39: =IF(P39>0,Q39,U39) -> #VALUE!
A40: ='Goals & Fees'!L42 -> 0 | C40: Row 39 | D40: ='Closed Transactions'!K40 | E40: ='Closed Transactions'!L40 -> 0 | F40: =IFERROR(D40-E40-G40,0) -> 0 | G40: =IFERROR(X40+N40+J40,0) -> 0 | H40: =IFERROR((D40-E40)*$A$3,0) -> 0 | I40: =IF($A$4<>"",$A$4,"") -> 0 | J40: =IF(D40="",0,IF((IF(K39>=$A$5,0,IF(H40<1,I40,H40))+K39)>$A$5,$A$5-K39,IF(K39>=$A$5,0,IF(H40<1,I40,H40)))) -> 0 | K40: =IF(D40="",0,J40+K39) -> 0 | L40: =IFERROR((D40-E40)*$A$7,0) -> 0 | M40: =IF($A$8<>"",$A$8,"") -> 0 | N40: =IF(D40="",0,IF((IF(O39>=$A$9,0,IF(L40<1,M40,L40))+O39)>$A$9,$A$9-O39,IF(O39>=$A$9,0,IF(L40<1,M40,L40)))) -> 0 | O40: =IF(D40="",0,N40+O39) -> 0 | P40: =IF(D40="",0,(D40-E40)*$A$12) -> 0 | Q40: =IF(D40="",0,IF($A$14=0,(100%-$A$12)*D40,IF(R39>=$A$14,(100%-$A$13)*(D40-E40),IF(R39+(D40-E40-P40)>=$A$14,$A$14-R39,(D40-E40-P40))))) -> 0 | R40: =Q40+R39 -> 21583.025 | S40: =_xlfn.XLOOKUP(T39,$B$35:$B$40,$A$35:$A$40,,1)*(D40-E40) -> #VALUE! | T40: =S40+T39 -> #VALUE! | U40: =D40-E40-S40 -> #VALUE! | W40: =IF(P40>0,Q40,S40) -> #VALUE! | X40: =IF(P40>0,Q40,U40) -> #VALUE!
C41: Row 40 | D41: ='Closed Transactions'!K41 | E41: ='Closed Transactions'!L41 -> 0 | F41: =IFERROR(D41-E41-G41,0) -> 0 | G41: =IFERROR(X41+N41+J41,0) -> 0 | H41: =IFERROR((D41-E41)*$A$3,0) -> 0 | I41: =IF($A$4<>"",$A$4,"") -> 0 | J41: =IF(D41="",0,IF((IF(K40>=$A$5,0,IF(H41<1,I41,H41))+K40)>$A$5,$A$5-K40,IF(K40>=$A$5,0,IF(H41<1,I41,H41)))) -> 0 | K41: =IF(D41="",0,J41+K40) -> 0 | L41: =IFERROR((D41-E41)*$A$7,0) -> 0 | M41: =IF($A$8<>"",$A$8,"") -> 0 | N41: =IF(D41="",0,IF((IF(O40>=$A$9,0,IF(L41<1,M41,L41))+O40)>$A$9,$A$9-O40,IF(O40>=$A$9,0,IF(L41<1,M41,L41)))) -> 0 | O41: =IF(D41="",0,N41+O40) -> 0 | P41: =IF(D41="",0,(D41-E41)*$A$12) -> 0 | Q41: =IF(D41="",0,IF($A$14=0,(100%-$A$12)*D41,IF(R40>=$A$14,(100%-$A$13)*(D41-E41),IF(R40+(D41-E41-P41)>=$A$14,$A$14-R40,(D41-E41-P41))))) -> 0 | R41: =Q41+R40 -> 21583.025 | S41: =_xlfn.XLOOKUP(T40,$B$35:$B$40,$A$35:$A$40,,1)*(D41-E41) -> #VALUE! | T41: =S41+T40 -> #VALUE! | U41: =D41-E41-S41 -> #VALUE! | W41: =IF(P41>0,Q41,S41) -> #VALUE! | X41: =IF(P41>0,Q41,U41) -> #VALUE!
C42: Row 41 | D42: ='Closed Transactions'!K42 | E42: ='Closed Transactions'!L42 -> 0 | F42: =IFERROR(D42-E42-G42,0) -> 0 | G42: =IFERROR(X42+N42+J42,0) -> 0 | H42: =IFERROR((D42-E42)*$A$3,0) -> 0 | I42: =IF($A$4<>"",$A$4,"") -> 0 | J42: =IF(D42="",0,IF((IF(K41>=$A$5,0,IF(H42<1,I42,H42))+K41)>$A$5,$A$5-K41,IF(K41>=$A$5,0,IF(H42<1,I42,H42)))) -> 0 | K42: =IF(D42="",0,J42+K41) -> 0 | L42: =IFERROR((D42-E42)*$A$7,0) -> 0 | M42: =IF($A$8<>"",$A$8,"") -> 0 | N42: =IF(D42="",0,IF((IF(O41>=$A$9,0,IF(L42<1,M42,L42))+O41)>$A$9,$A$9-O41,IF(O41>=$A$9,0,IF(L42<1,M42,L42)))) -> 0 | O42: =IF(D42="",0,N42+O41) -> 0 | P42: =IF(D42="",0,(D42-E42)*$A$12) -> 0 | Q42: =IF(D42="",0,IF($A$14=0,(100%-$A$12)*D42,IF(R41>=$A$14,(100%-$A$13)*(D42-E42),IF(R41+(D42-E42-P42)>=$A$14,$A$14-R41,(D42-E42-P42))))) -> 0 | R42: =Q42+R41 -> 21583.025 | S42: =_xlfn.XLOOKUP(T41,$B$35:$B$40,$A$35:$A$40,,1)*(D42-E42) -> #VALUE! | T42: =S42+T41 -> #VALUE! | U42: =D42-E42-S42 -> #VALUE! | W42: =IF(P42>0,Q42,S42) -> #VALUE! | X42: =IF(P42>0,Q42,U42) -> #VALUE!
C43: Row 42 | D43: ='Closed Transactions'!K43 | E43: ='Closed Transactions'!L43 -> 0 | F43: =IFERROR(D43-E43-G43,0) -> 0 | G43: =IFERROR(X43+N43+J43,0) -> 0 | H43: =IFERROR((D43-E43)*$A$3,0) -> 0 | I43: =IF($A$4<>"",$A$4,"") -> 0 | J43: =IF(D43="",0,IF((IF(K42>=$A$5,0,IF(H43<1,I43,H43))+K42)>$A$5,$A$5-K42,IF(K42>=$A$5,0,IF(H43<1,I43,H43)))) -> 0 | K43: =IF(D43="",0,J43+K42) -> 0 | L43: =IFERROR((D43-E43)*$A$7,0) -> 0 | M43: =IF($A$8<>"",$A$8,"") -> 0 | N43: =IF(D43="",0,IF((IF(O42>=$A$9,0,IF(L43<1,M43,L43))+O42)>$A$9,$A$9-O42,IF(O42>=$A$9,0,IF(L43<1,M43,L43)))) -> 0 | O43: =IF(D43="",0,N43+O42) -> 0 | P43: =IF(D43="",0,(D43-E43)*$A$12) -> 0 | Q43: =IF(D43="",0,IF($A$14=0,(100%-$A$12)*D43,IF(R42>=$A$14,(100%-$A$13)*(D43-E43),IF(R42+(D43-E43-P43)>=$A$14,$A$14-R42,(D43-E43-P43))))) -> 0 | R43: =Q43+R42 -> 21583.025 | S43: =_xlfn.XLOOKUP(T42,$B$35:$B$40,$A$35:$A$40,,1)*(D43-E43) -> #VALUE! | T43: =S43+T42 -> #VALUE! | U43: =D43-E43-S43 -> #VALUE! | W43: =IF(P43>0,Q43,S43) -> #VALUE! | X43: =IF(P43>0,Q43,U43) -> #VALUE!
C44: Row 43 | D44: ='Closed Transactions'!K44 | E44: ='Closed Transactions'!L44 -> 0 | F44: =IFERROR(D44-E44-G44,0) -> 0 | G44: =IFERROR(X44+N44+J44,0) -> 0 | H44: =IFERROR((D44-E44)*$A$3,0) -> 0 | I44: =IF($A$4<>"",$A$4,"") -> 0 | J44: =IF(D44="",0,IF((IF(K43>=$A$5,0,IF(H44<1,I44,H44))+K43)>$A$5,$A$5-K43,IF(K43>=$A$5,0,IF(H44<1,I44,H44)))) -> 0 | K44: =IF(D44="",0,J44+K43) -> 0 | L44: =IFERROR((D44-E44)*$A$7,0) -> 0 | M44: =IF($A$8<>"",$A$8,"") -> 0 | N44: =IF(D44="",0,IF((IF(O43>=$A$9,0,IF(L44<1,M44,L44))+O43)>$A$9,$A$9-O43,IF(O43>=$A$9,0,IF(L44<1,M44,L44)))) -> 0 | O44: =IF(D44="",0,N44+O43) -> 0 | P44: =IF(D44="",0,(D44-E44)*$A$12) -> 0 | Q44: =IF(D44="",0,IF($A$14=0,(100%-$A$12)*D44,IF(R43>=$A$14,(100%-$A$13)*(D44-E44),IF(R43+(D44-E44-P44)>=$A$14,$A$14-R43,(D44-E44-P44))))) -> 0 | R44: =Q44+R43 -> 21583.025 | S44: =_xlfn.XLOOKUP(T43,$B$35:$B$40,$A$35:$A$40,,1)*(D44-E44) -> #VALUE! | T44: =S44+T43 -> #VALUE! | U44: =D44-E44-S44 -> #VALUE! | W44: =IF(P44>0,Q44,S44) -> #VALUE! | X44: =IF(P44>0,Q44,U44) -> #VALUE!
C45: Row 44 | D45: ='Closed Transactions'!K45 | E45: ='Closed Transactions'!L45 -> 0 | F45: =IFERROR(D45-E45-G45,0) -> 0 | G45: =IFERROR(X45+N45+J45,0) -> 0 | H45: =IFERROR((D45-E45)*$A$3,0) -> 0 | I45: =IF($A$4<>"",$A$4,"") -> 0 | J45: =IF(D45="",0,IF((IF(K44>=$A$5,0,IF(H45<1,I45,H45))+K44)>$A$5,$A$5-K44,IF(K44>=$A$5,0,IF(H45<1,I45,H45)))) -> 0 | K45: =IF(D45="",0,J45+K44) -> 0 | L45: =IFERROR((D45-E45)*$A$7,0) -> 0 | M45: =IF($A$8<>"",$A$8,"") -> 0 | N45: =IF(D45="",0,IF((IF(O44>=$A$9,0,IF(L45<1,M45,L45))+O44)>$A$9,$A$9-O44,IF(O44>=$A$9,0,IF(L45<1,M45,L45)))) -> 0 | O45: =IF(D45="",0,N45+O44) -> 0 | P45: =IF(D45="",0,(D45-E45)*$A$12) -> 0 | Q45: =IF(D45="",0,IF($A$14=0,(100%-$A$12)*D45,IF(R44>=$A$14,(100%-$A$13)*(D45-E45),IF(R44+(D45-E45-P45)>=$A$14,$A$14-R44,(D45-E45-P45))))) -> 0 | R45: =Q45+R44 -> 21583.025 | S45: =_xlfn.XLOOKUP(T44,$B$35:$B$40,$A$35:$A$40,,1)*(D45-E45) -> #VALUE! | T45: =S45+T44 -> #VALUE! | U45: =D45-E45-S45 -> #VALUE! | W45: =IF(P45>0,Q45,S45) -> #VALUE! | X45: =IF(P45>0,Q45,U45) -> #VALUE!
C46: Row 45 | D46: ='Closed Transactions'!K46 | E46: ='Closed Transactions'!L46 -> 0 | F46: =IFERROR(D46-E46-G46,0) -> 0 | G46: =IFERROR(X46+N46+J46,0) -> 0 | H46: =IFERROR((D46-E46)*$A$3,0) -> 0 | I46: =IF($A$4<>"",$A$4,"") -> 0 | J46: =IF(D46="",0,IF((IF(K45>=$A$5,0,IF(H46<1,I46,H46))+K45)>$A$5,$A$5-K45,IF(K45>=$A$5,0,IF(H46<1,I46,H46)))) -> 0 | K46: =IF(D46="",0,J46+K45) -> 0 | L46: =IFERROR((D46-E46)*$A$7,0) -> 0 | M46: =IF($A$8<>"",$A$8,"") -> 0 | N46: =IF(D46="",0,IF((IF(O45>=$A$9,0,IF(L46<1,M46,L46))+O45)>$A$9,$A$9-O45,IF(O45>=$A$9,0,IF(L46<1,M46,L46)))) -> 0 | O46: =IF(D46="",0,N46+O45) -> 0 | P46: =IF(D46="",0,(D46-E46)*$A$12) -> 0 | Q46: =IF(D46="",0,IF($A$14=0,(100%-$A$12)*D46,IF(R45>=$A$14,(100%-$A$13)*(D46-E46),IF(R45+(D46-E46-P46)>=$A$14,$A$14-R45,(D46-E46-P46))))) -> 0 | R46: =Q46+R45 -> 21583.025 | S46: =_xlfn.XLOOKUP(T45,$B$35:$B$40,$A$35:$A$40,,1)*(D46-E46) -> #VALUE! | T46: =S46+T45 -> #VALUE! | U46: =D46-E46-S46 -> #VALUE! | W46: =IF(P46>0,Q46,S46) -> #VALUE! | X46: =IF(P46>0,Q46,U46) -> #VALUE!
C47: Row 46 | D47: ='Closed Transactions'!K47 | E47: ='Closed Transactions'!L47 -> 0 | F47: =IFERROR(D47-E47-G47,0) -> 0 | G47: =IFERROR(X47+N47+J47,0) -> 0 | H47: =IFERROR((D47-E47)*$A$3,0) -> 0 | I47: =IF($A$4<>"",$A$4,"") -> 0 | J47: =IF(D47="",0,IF((IF(K46>=$A$5,0,IF(H47<1,I47,H47))+K46)>$A$5,$A$5-K46,IF(K46>=$A$5,0,IF(H47<1,I47,H47)))) -> 0 | K47: =IF(D47="",0,J47+K46) -> 0 | L47: =IFERROR((D47-E47)*$A$7,0) -> 0 | M47: =IF($A$8<>"",$A$8,"") -> 0 | N47: =IF(D47="",0,IF((IF(O46>=$A$9,0,IF(L47<1,M47,L47))+O46)>$A$9,$A$9-O46,IF(O46>=$A$9,0,IF(L47<1,M47,L47)))) -> 0 | O47: =IF(D47="",0,N47+O46) -> 0 | P47: =IF(D47="",0,(D47-E47)*$A$12) -> 0 | Q47: =IF(D47="",0,IF($A$14=0,(100%-$A$12)*D47,IF(R46>=$A$14,(100%-$A$13)*(D47-E47),IF(R46+(D47-E47-P47)>=$A$14,$A$14-R46,(D47-E47-P47))))) -> 0 | R47: =Q47+R46 -> 21583.025 | S47: =_xlfn.XLOOKUP(T46,$B$35:$B$40,$A$35:$A$40,,1)*(D47-E47) -> #VALUE! | T47: =S47+T46 -> #VALUE! | U47: =D47-E47-S47 -> #VALUE! | W47: =IF(P47>0,Q47,S47) -> #VALUE! | X47: =IF(P47>0,Q47,U47) -> #VALUE!
